{"type": "Feature", "id": 56068911, "properties": {"woe:id": 56068911, "woe:parent_id": 12695823, "woe:name": "Brondesbury College For Boys", "woe:placetype": 20, "woe:placetype_name": "POI", "woe:lang": "ENG", "iso:country": "GB", "meta:provider": ["geoplanet:7.3.1", "geoplanet:7.3.2", "geoplanet:7.4.0", "geoplanet:7.4.1", "geoplanet:7.5.1", "geoplanet:7.5.2", "geoplanet:7.6.0", "geoplanet:7.8.1", "geoplanet:7.9.0", "geoplanet:7.10.0", "geoplanet:8.0.0", "woeplanet:8.0.0"], "meta:indexed": "2020-08-20T19:45:34.408382", "meta:updated": "2020-08-22T02:03:57.847025", "woe:hierarchy": {"continent": 24865675, "country": 23424975, "town": 0, "planet": 1, "county": 23416974, "suburb": 0, "state": 24554868, "region": 0, "localadmin": 12695823}, "woe:timezone_id": 28350903, "woe:hash": "gcpv5nvxvkqh", "woe:centroid": [-0.21194, 51.542339], "geom:latitude": 51.542339, "geom:longitude": -0.21194, "geom:hash": "gcpv5nvxvkqh", "woe:latitude": 51.542339, "geom:centroid": [-0.21194, 51.542339], "woe:longitude": -0.21194, "woe:repo": "woeplanet-poi-gb"}, "geometry": {"coordinates": [-0.21194, 51.542339], "type": "Point"}}