{"type": "Feature", "id": 22485808, "properties": {"woe:id": 22485808, "woe:parent_id": 33700, "woe:name": "Royston Railway Station", "woe:placetype": 20, "woe:placetype_name": "POI", "woe:lang": "ENG", "iso:country": "GB", "meta:provider": ["geoplanet:7.3.1", "geoplanet:7.3.2", "geoplanet:7.4.0", "geoplanet:7.4.1", "geoplanet:7.5.1", "geoplanet:7.5.2", "geoplanet:7.6.0", "geoplanet:7.8.1", "geoplanet:7.9.0", "geoplanet:7.10.0", "geoplanet:8.0.0", "woeplanet:8.0.0"], "meta:indexed": "2020-08-20T19:45:33.274711", "woe:alias_ENG_V": ["Royston Station"], "meta:updated": "2020-08-22T02:03:29.514414", "woe:hierarchy": {"continent": 24865675, "country": 23424975, "town": 0, "planet": 1, "county": 12602170, "suburb": 0, "state": 24554868, "region": 0, "localadmin": 12695979}, "woe:timezone_id": 28350903, "woe:hash": "gcrbp7umbbb5", "woe:centroid": [-0.02709, 52.052841], "geom:latitude": 52.052841, "geom:longitude": -0.02709, "geom:hash": "gcrbp7umbbb5", "woe:latitude": 52.052841, "geom:centroid": [-0.02709, 52.052841], "woe:longitude": -0.02709, "woe:repo": "woeplanet-poi-gb"}, "geometry": {"coordinates": [-0.02709, 52.052841], "type": "Point"}}