{"type": "Feature", "id": 20093193, "geometry": {"type": "Point", "coordinates": [-0.07347, 51.72031]}, "properties": {"woe:id": 20093193, "woe:parent_id": 21298, "woe:name": "Hammond Street", "woe:placetype": 20, "woe:placetype_name": "POI", "woe:lang": "ENG", "iso:country": "GB", "meta:provider": ["geoplanet:7.3.1", "geoplanet:7.3.2", "geoplanet:7.4.0", "geoplanet:7.4.1", "geoplanet:7.5.1", "geoplanet:7.5.2", "geoplanet:7.6.0", "geoplanet:7.8.1", "geoplanet:7.9.0", "geoplanet:7.10.0", "geoplanet:8.0.0", "woeplanet:8.0.0"], "meta:indexed": "2020-08-20T19:45:30.894216", "meta:updated": "2020-10-14T11:22:10.634273", "woe:hierarchy": {"continent": 24865675, "country": 23424975, "town": 0, "planet": 1, "county": 12602170, "suburb": 0, "state": 24554868, "region": 0, "localadmin": 12695975}, "woe:timezone_id": 28350903, "woe:hash": "gcpynr6s8h8f", "woe:centroid": [-0.07347, 51.72031], "geom:latitude": 51.72031, "geom:longitude": -0.07347, "geom:hash": "gcpynr6s8h8f", "woe:latitude": 51.72031, "geom:centroid": [-0.07347, 51.72031], "woe:longitude": -0.07347, "woe:repo": "woeplanet-poi-gb", "geom:area": 0.0, "woe:scale": 19}}