{"type": "Feature", "id": 28349996, "properties": {"woe:id": 28349996, "woe:parent_id": 10411, "woe:name": "Lebanon Road Tram Stop", "woe:placetype": 20, "woe:placetype_name": "POI", "woe:lang": "ENG", "iso:country": "GB", "meta:provider": ["geoplanet:7.3.1", "geoplanet:7.3.2", "geoplanet:7.4.0", "geoplanet:7.4.1", "geoplanet:7.5.1", "geoplanet:7.5.2", "geoplanet:7.6.0", "geoplanet:7.8.1", "geoplanet:7.9.0", "geoplanet:7.10.0", "geoplanet:8.0.0", "woeplanet:8.0.0"], "meta:indexed": "2020-08-20T19:45:34.049873", "meta:updated": "2020-08-22T02:03:29.837981", "woe:hierarchy": {"continent": 24865675, "country": 23424975, "town": 0, "planet": 1, "county": 23416974, "suburb": 0, "state": 24554868, "region": 0, "localadmin": 12695825}, "woe:timezone_id": 28350903, "woe:hash": "gcpuq0d9b4me", "woe:centroid": [-0.08445, 51.37513], "geom:latitude": 51.37513, "geom:longitude": -0.08445, "geom:hash": "gcpuq0d9b4me", "woe:latitude": 51.37513, "geom:centroid": [-0.08445, 51.37513], "woe:longitude": -0.08445, "woe:repo": "woeplanet-poi-gb"}, "geometry": {"coordinates": [-0.08445, 51.37513], "type": "Point"}}