{"type": "Feature", "id": 23702160, "properties": {"woe:id": 23702160, "woe:parent_id": 43985, "woe:name": "Newnham College", "woe:placetype": 20, "woe:placetype_name": "POI", "woe:lang": "ENG", "iso:country": "GB", "meta:provider": ["geoplanet:7.3.1", "geoplanet:7.3.2", "geoplanet:7.4.0", "geoplanet:7.4.1", "geoplanet:7.5.1", "geoplanet:7.5.2", "geoplanet:7.6.0", "geoplanet:7.8.1", "geoplanet:7.9.0", "geoplanet:7.10.0", "geoplanet:8.0.0", "woeplanet:8.0.0"], "meta:indexed": "2020-08-20T19:45:34.171621", "meta:updated": "2020-08-22T02:03:57.963041", "woe:hierarchy": {"continent": 24865675, "country": 23424975, "town": 0, "planet": 1, "county": 12602140, "suburb": 0, "state": 24554868, "region": 0, "localadmin": 12695882}, "woe:timezone_id": 28350903, "woe:hash": "u120fqz90w3q", "woe:centroid": [0.1092, 52.200371], "geom:latitude": 52.200371, "geom:longitude": 0.1092, "geom:hash": "u120fqz90w3q", "woe:latitude": 52.200371, "geom:centroid": [0.1092, 52.200371], "woe:longitude": 0.1092, "woe:repo": "woeplanet-poi-gb"}, "geometry": {"coordinates": [0.1092, 52.200371], "type": "Point"}}