{"type": "Feature", "id": 22467850, "properties": {"woe:id": 22467850, "woe:parent_id": 22619, "woe:name": "Hastings Railway Station", "woe:placetype": 20, "woe:placetype_name": "POI", "woe:lang": "ENG", "iso:country": "GB", "meta:provider": ["geoplanet:7.3.1", "geoplanet:7.3.2", "geoplanet:7.4.0", "geoplanet:7.4.1", "geoplanet:7.5.1", "geoplanet:7.5.2", "geoplanet:7.6.0", "geoplanet:7.8.1", "geoplanet:7.9.0", "geoplanet:7.10.0", "geoplanet:8.0.0", "woeplanet:8.0.0"], "meta:indexed": "2020-08-20T19:45:32.041717", "woe:alias_ENG_V": ["Hastings Station"], "meta:updated": "2020-08-22T02:03:28.925833", "woe:hierarchy": {"continent": 24865675, "country": 23424975, "town": 0, "planet": 1, "county": 12602167, "suburb": 0, "state": 24554868, "region": 0, "localadmin": 12695936}, "woe:timezone_id": 28350903, "woe:hash": "u103m47um6sm", "woe:centroid": [0.57667, 50.85783], "geom:latitude": 50.85783, "geom:longitude": 0.57667, "geom:hash": "u103m47um6sm", "woe:latitude": 50.85783, "geom:centroid": [0.57667, 50.85783], "woe:longitude": 0.57667, "woe:repo": "woeplanet-poi-gb"}, "geometry": {"coordinates": [0.57667, 50.85783], "type": "Point"}}