{"type": "Feature", "id": 23701945, "properties": {"woe:id": 23701945, "woe:parent_id": 36094, "woe:name": "Broadhall Way", "woe:placetype": 20, "woe:placetype_name": "POI", "woe:lang": "ENG", "iso:country": "GB", "meta:provider": ["geoplanet:7.3.1", "geoplanet:7.3.2", "geoplanet:7.4.0", "geoplanet:7.4.1", "geoplanet:7.5.1", "geoplanet:7.5.2", "geoplanet:7.6.0", "geoplanet:7.8.1", "geoplanet:7.9.0", "geoplanet:7.10.0", "geoplanet:8.0.0", "woeplanet:8.0.0"], "meta:indexed": "2020-08-20T19:45:33.907779", "meta:updated": "2020-08-22T02:03:29.809298", "woe:hierarchy": {"continent": 24865675, "country": 23424975, "town": 0, "planet": 1, "county": 12602170, "suburb": 0, "state": 24554868, "region": 0, "localadmin": 12695981}, "woe:timezone_id": 28350903, "woe:hash": "gcpz5w4gtw0c", "woe:centroid": [-0.19374, 51.889061], "geom:latitude": 51.889061, "geom:longitude": -0.19374, "geom:hash": "gcpz5w4gtw0c", "woe:latitude": 51.889061, "geom:centroid": [-0.19374, 51.889061], "woe:longitude": -0.19374, "woe:repo": "woeplanet-poi-gb"}, "geometry": {"coordinates": [-0.19374, 51.889061], "type": "Point"}}