{"type": "Feature", "id": 22454611, "geometry": {"type": "Point", "coordinates": [-1.93592, 52.441929]}, "properties": {"woe:id": 22454611, "woe:parent_id": 25092, "woe:name": "Selly Oak Railway Station", "woe:placetype": 20, "woe:placetype_name": "POI", "woe:lang": "ENG", "iso:country": "GB", "meta:provider": ["geoplanet:7.3.1", "geoplanet:7.3.2", "geoplanet:7.4.0", "geoplanet:7.4.1", "geoplanet:7.5.1", "geoplanet:7.5.2", "geoplanet:7.6.0", "geoplanet:7.8.1", "geoplanet:7.9.0", "geoplanet:7.10.0", "geoplanet:8.0.0", "woeplanet:8.0.0"], "meta:indexed": "2020-08-20T19:45:31.221280", "woe:alias_ENG_V": ["Selly Oak Station"], "meta:updated": "2020-10-14T11:22:08.067518", "woe:hierarchy": {"continent": 24865675, "country": 23424975, "town": 0, "planet": 1, "county": 12602191, "suburb": 0, "state": 24554868, "region": 0, "localadmin": 12695863}, "woe:timezone_id": 28350903, "woe:hash": "gcqd7fy23u17", "woe:centroid": [-1.93592, 52.441929], "geom:latitude": 52.441929, "geom:longitude": -1.93592, "geom:hash": "gcqd7fy23u17", "woe:latitude": 52.441929, "geom:centroid": [-1.93592, 52.441929], "woe:longitude": -1.93592, "woe:repo": "woeplanet-poi-gb", "geom:area": 0.0, "woe:scale": 19}}