{"type": "Feature", "id": 22459338, "geometry": {"type": "Point", "coordinates": [-1.92806, 51.9683]}, "properties": {"woe:id": 22459338, "woe:parent_id": 22134, "woe:name": "Hailes Abbey", "woe:placetype": 20, "woe:placetype_name": "POI", "woe:lang": "ENG", "iso:country": "GB", "meta:provider": ["geoplanet:7.3.1", "geoplanet:7.3.2", "geoplanet:7.4.0", "geoplanet:7.4.1", "geoplanet:7.5.1", "geoplanet:7.5.2", "geoplanet:7.6.0", "geoplanet:7.8.1", "geoplanet:7.9.0", "geoplanet:7.10.0", "geoplanet:8.0.0", "woeplanet:8.0.0"], "meta:indexed": "2020-08-20T19:45:31.482701", "meta:updated": "2020-10-14T11:22:08.641021", "woe:hierarchy": {"continent": 24865675, "country": 23424975, "town": 0, "planet": 1, "county": 12602184, "suburb": 0, "state": 24554868, "region": 0, "localadmin": 12695957}, "woe:timezone_id": 28350903, "woe:hash": "gcnxshs12cq2", "woe:centroid": [-1.92806, 51.9683], "geom:latitude": 51.9683, "geom:longitude": -1.92806, "geom:hash": "gcnxshs12cq2", "woe:latitude": 51.9683, "geom:centroid": [-1.92806, 51.9683], "woe:longitude": -1.92806, "woe:repo": "woeplanet-poi-gb", "geom:area": 0.0, "woe:scale": 19}}