{"type": "Feature", "id": 22477127, "geometry": {"type": "Point", "coordinates": [-0.41986, 51.86446]}, "properties": {"woe:id": 22477127, "woe:parent_id": 31897, "woe:name": "Stockwood Park Golf Club", "woe:placetype": 20, "woe:placetype_name": "POI", "woe:lang": "ENG", "iso:country": "GB", "meta:provider": ["geoplanet:7.3.1", "geoplanet:7.3.2", "geoplanet:7.4.0", "geoplanet:7.4.1", "geoplanet:7.5.1", "geoplanet:7.5.2", "geoplanet:7.6.0", "geoplanet:7.8.1", "geoplanet:7.9.0", "geoplanet:7.10.0", "geoplanet:8.0.0", "woeplanet:8.0.0"], "meta:indexed": "2020-08-20T19:45:32.786314", "meta:updated": "2020-10-14T11:22:08.413078", "woe:alias_ENG_V": ["Stockwood Park Golf Centre"], "woe:hierarchy": {"continent": 24865675, "country": 23424975, "town": 0, "planet": 1, "county": 12602163, "suburb": 0, "state": 24554868, "region": 0, "localadmin": 12696155}, "woe:timezone_id": 28350903, "woe:hash": "gcpxn3wk2s1d", "woe:centroid": [-0.41986, 51.86446], "geom:latitude": 51.86446, "geom:longitude": -0.41986, "geom:hash": "gcpxn3wk2s1d", "woe:latitude": 51.86446, "geom:centroid": [-0.41986, 51.86446], "woe:longitude": -0.41986, "woe:repo": "woeplanet-poi-gb", "geom:area": 0.0, "woe:scale": 19}}