{"type": "Feature", "id": 22494288, "geometry": {"type": "Point", "coordinates": [-2.73331, 53.378731]}, "properties": {"woe:id": 22494288, "woe:parent_id": 19963, "woe:name": "Widnes Railway Station", "woe:placetype": 20, "woe:placetype_name": "POI", "woe:lang": "ENG", "iso:country": "GB", "meta:provider": ["geoplanet:7.3.1", "geoplanet:7.3.2", "geoplanet:7.4.0", "geoplanet:7.4.1", "geoplanet:7.5.1", "geoplanet:7.5.2", "geoplanet:7.6.0", "geoplanet:7.8.1", "geoplanet:7.9.0", "geoplanet:7.10.0", "geoplanet:8.0.0", "woeplanet:8.0.0"], "meta:indexed": "2020-08-20T19:45:33.738624", "woe:alias_ENG_V": ["Widnes Station"], "meta:updated": "2020-10-14T11:22:07.905735", "woe:hierarchy": {"continent": 24865675, "country": 23424975, "town": 0, "planet": 1, "county": 12602157, "suburb": 0, "state": 24554868, "region": 0, "localadmin": 12696171}, "woe:timezone_id": 28350903, "woe:hash": "gcqp9v39tk8m", "woe:centroid": [-2.73331, 53.378731], "geom:latitude": 53.378731, "geom:longitude": -2.73331, "geom:hash": "gcqp9v39tk8m", "woe:latitude": 53.378731, "geom:centroid": [-2.73331, 53.378731], "woe:longitude": -2.73331, "woe:repo": "woeplanet-poi-gb", "geom:area": 0.0, "woe:scale": 19}}