{"type": "Feature", "id": 22464538, "properties": {"woe:id": 22464538, "woe:parent_id": 28048, "woe:name": "A la Ronde", "woe:placetype": 20, "woe:placetype_name": "POI", "woe:lang": "ENG", "iso:country": "GB", "meta:provider": ["geoplanet:7.3.1", "geoplanet:7.3.2", "geoplanet:7.4.0", "geoplanet:7.4.1", "geoplanet:7.5.1", "geoplanet:7.5.2", "geoplanet:7.6.0", "geoplanet:7.8.1", "geoplanet:7.9.0", "geoplanet:7.10.0", "geoplanet:8.0.0", "woeplanet:8.0.0"], "meta:indexed": "2020-08-20T19:45:31.784780", "meta:updated": "2020-08-22T02:03:58.035145", "woe:hierarchy": {"continent": 24865675, "country": 23424975, "town": 0, "planet": 1, "county": 12602182, "suburb": 0, "state": 24554868, "region": 0, "localadmin": 12695914}, "woe:timezone_id": 28350903, "woe:hash": "gcj847jc31q3", "woe:centroid": [-3.4088, 50.641701], "geom:latitude": 50.641701, "geom:longitude": -3.4088, "geom:hash": "gcj847jc31q3", "woe:latitude": 50.641701, "geom:centroid": [-3.4088, 50.641701], "woe:longitude": -3.4088, "woe:repo": "woeplanet-poi-gb"}, "geometry": {"coordinates": [-3.4088, 50.641701], "type": "Point"}}