{"type": "Feature", "id": 22474656, "geometry": {"type": "Point", "coordinates": [-0.28818, 51.510319]}, "properties": {"woe:id": 22474656, "woe:parent_id": 20089545, "woe:name": "Ealing Common Underground Station", "woe:placetype": 20, "woe:placetype_name": "POI", "woe:lang": "ENG", "iso:country": "GB", "meta:provider": ["geoplanet:7.3.1", "geoplanet:7.3.2", "geoplanet:7.4.0", "geoplanet:7.4.1", "geoplanet:7.5.1", "geoplanet:7.5.2", "geoplanet:7.6.0", "geoplanet:7.8.1", "geoplanet:7.9.0", "geoplanet:7.10.0", "geoplanet:8.0.0", "woeplanet:8.0.0"], "meta:indexed": "2020-08-20T19:45:32.472961", "woe:alias_ENG_V": ["Ealing Common Tube", "Ealing Common Underground", "Ealing Common Station", "Ealing Common Tube Station"], "meta:updated": "2020-10-14T11:22:08.842330", "woe:hierarchy": {"continent": 24865675, "country": 23424975, "town": 0, "planet": 1, "county": 23416974, "suburb": 0, "state": 24554868, "region": 0, "localadmin": 12695826}, "woe:timezone_id": 28350903, "woe:hash": "gcpv13njkgmm", "woe:centroid": [-0.28818, 51.510319], "geom:latitude": 51.510319, "geom:longitude": -0.28818, "geom:hash": "gcpv13njkgmm", "woe:latitude": 51.510319, "geom:centroid": [-0.28818, 51.510319], "woe:longitude": -0.28818, "woe:repo": "woeplanet-poi-gb", "geom:area": 0.0, "woe:scale": 19}}