{"type": "Feature", "id": 22492506, "geometry": {"type": "Point", "coordinates": [-0.47924, 51.546089]}, "properties": {"woe:id": 22492506, "woe:parent_id": 38838, "woe:name": "Uxbridge Underground Station", "woe:placetype": 20, "woe:placetype_name": "POI", "woe:lang": "ENG", "iso:country": "GB", "meta:provider": ["geoplanet:7.3.1", "geoplanet:7.3.2", "geoplanet:7.4.0", "geoplanet:7.4.1", "geoplanet:7.5.1", "geoplanet:7.5.2", "geoplanet:7.6.0", "geoplanet:7.8.1", "geoplanet:7.9.0", "geoplanet:7.10.0", "geoplanet:8.0.0", "woeplanet:8.0.0"], "meta:indexed": "2020-08-20T19:45:33.636048", "woe:alias_ENG_V": ["Uxbridge Tube", "Uxbridge Underground", "Uxbridge Station", "Uxbridge Tube Station"], "meta:updated": "2020-10-14T11:22:07.927013", "woe:hierarchy": {"continent": 24865675, "country": 23424975, "town": 0, "planet": 1, "county": 23416974, "suburb": 0, "state": 24554868, "region": 0, "localadmin": 12695831}, "woe:timezone_id": 28350903, "woe:hash": "gcptjpej8zkv", "woe:centroid": [-0.47924, 51.546089], "geom:latitude": 51.546089, "geom:longitude": -0.47924, "geom:hash": "gcptjpej8zkv", "woe:latitude": 51.546089, "geom:centroid": [-0.47924, 51.546089], "woe:longitude": -0.47924, "woe:repo": "woeplanet-poi-gb", "geom:area": 0.0, "woe:scale": 19}}