{"type": "Feature", "id": 22484229, "properties": {"woe:id": 22484229, "woe:parent_id": 39101, "woe:name": "Bamber Bridge Railway Station", "woe:placetype": 20, "woe:placetype_name": "POI", "woe:lang": "ENG", "iso:country": "GB", "meta:provider": ["geoplanet:7.3.1", "geoplanet:7.3.2", "geoplanet:7.4.0", "geoplanet:7.4.1", "geoplanet:7.5.1", "geoplanet:7.5.2", "geoplanet:7.6.0", "geoplanet:7.8.1", "geoplanet:7.9.0", "geoplanet:7.10.0", "geoplanet:8.0.0", "woeplanet:8.0.0"], "meta:indexed": "2020-08-20T19:45:33.175447", "woe:alias_ENG_V": ["Bamber Bridge Station"], "meta:updated": "2020-08-22T02:03:29.469082", "woe:hierarchy": {"continent": 24865675, "country": 23424975, "town": 0, "planet": 1, "county": 12602160, "suburb": 0, "state": 24554868, "region": 0, "localadmin": 12696006}, "woe:timezone_id": 28350903, "woe:hash": "gcw1ekwkz474", "woe:centroid": [-2.66079, 53.726719], "geom:latitude": 53.726719, "geom:longitude": -2.66079, "geom:hash": "gcw1ekwkz474", "woe:latitude": 53.726719, "geom:centroid": [-2.66079, 53.726719], "woe:longitude": -2.66079, "woe:repo": "woeplanet-poi-gb"}, "geometry": {"coordinates": [-2.66079, 53.726719], "type": "Point"}}