{"type": "Feature", "id": 22466530, "properties": {"woe:id": 22466530, "woe:parent_id": 30488, "woe:name": "Howden Railway Station", "woe:placetype": 20, "woe:placetype_name": "POI", "woe:lang": "ENG", "iso:country": "GB", "meta:provider": ["geoplanet:7.3.1", "geoplanet:7.3.2", "geoplanet:7.4.0", "geoplanet:7.4.1", "geoplanet:7.5.1", "geoplanet:7.5.2", "geoplanet:7.6.0", "geoplanet:7.8.1", "geoplanet:7.9.0", "geoplanet:7.10.0", "geoplanet:8.0.0", "woeplanet:8.0.0"], "meta:indexed": "2020-08-20T19:45:31.959536", "woe:alias_ENG_V": ["Howden Station"], "meta:updated": "2020-08-22T02:03:28.883484", "woe:hierarchy": {"continent": 24865675, "country": 23424975, "town": 0, "planet": 1, "county": 12602193, "suburb": 0, "state": 24554868, "region": 0, "localadmin": 12696138}, "woe:timezone_id": 28350903, "woe:hash": "gcx3u7t4dqv4", "woe:centroid": [-0.86095, 53.764809], "geom:latitude": 53.764809, "geom:longitude": -0.86095, "geom:hash": "gcx3u7t4dqv4", "woe:latitude": 53.764809, "geom:centroid": [-0.86095, 53.764809], "woe:longitude": -0.86095, "woe:repo": "woeplanet-poi-gb"}, "geometry": {"coordinates": [-0.86095, 53.764809], "type": "Point"}}