{"type": "Feature", "id": 22458276, "properties": {"woe:id": 22458276, "woe:parent_id": 22795, "woe:name": "Beau Desert Golf Club", "woe:placetype": 20, "woe:placetype_name": "POI", "woe:lang": "ENG", "iso:country": "GB", "meta:provider": ["geoplanet:7.3.1", "geoplanet:7.3.2", "geoplanet:7.4.0", "geoplanet:7.4.1", "geoplanet:7.5.1", "geoplanet:7.5.2", "geoplanet:7.6.0", "geoplanet:7.8.1", "geoplanet:7.9.0", "geoplanet:7.10.0", "geoplanet:8.0.0", "woeplanet:8.0.0"], "meta:indexed": "2020-08-20T19:45:31.419662", "meta:updated": "2020-08-22T02:03:28.639127", "woe:alias_ENG_V": ["Beau Desert Golf Course"], "woe:hierarchy": {"continent": 24865675, "country": 23424975, "town": 0, "planet": 1, "county": 12602189, "suburb": 0, "state": 24554868, "region": 0, "localadmin": 12696072}, "woe:timezone_id": 28350903, "woe:hash": "gcqegmmey51d", "woe:centroid": [-1.95874, 52.719929], "geom:latitude": 52.719929, "geom:longitude": -1.95874, "geom:hash": "gcqegmmey51d", "woe:latitude": 52.719929, "geom:centroid": [-1.95874, 52.719929], "woe:longitude": -1.95874, "woe:repo": "woeplanet-poi-gb"}, "geometry": {"coordinates": [-1.95874, 52.719929], "type": "Point"}}