{"type": "Feature", "id": 56068859, "properties": {"woe:id": 56068859, "woe:parent_id": 12695811, "woe:name": "London College of English", "woe:placetype": 20, "woe:placetype_name": "POI", "woe:lang": "ENG", "iso:country": "GB", "meta:provider": ["geoplanet:7.3.1", "geoplanet:7.3.2", "geoplanet:7.4.0", "geoplanet:7.4.1", "geoplanet:7.5.1", "geoplanet:7.5.2", "geoplanet:7.6.0", "geoplanet:7.8.1", "geoplanet:7.9.0", "geoplanet:7.10.0", "geoplanet:8.0.0", "woeplanet:8.0.0"], "meta:indexed": "2020-08-20T19:45:34.372796", "meta:updated": "2020-08-22T02:03:29.976359", "woe:hierarchy": {"continent": 24865675, "country": 23424975, "town": 0, "planet": 1, "county": 23416974, "suburb": 0, "state": 24554868, "region": 0, "localadmin": 12695811}, "woe:timezone_id": 28350903, "woe:hash": "gcpvjsp3314y", "woe:centroid": [-0.09986, 51.5261], "geom:latitude": 51.5261, "geom:longitude": -0.09986, "geom:hash": "gcpvjsp3314y", "woe:latitude": 51.5261, "geom:centroid": [-0.09986, 51.5261], "woe:longitude": -0.09986, "woe:repo": "woeplanet-poi-gb"}, "geometry": {"coordinates": [-0.09986, 51.5261], "type": "Point"}}