{"type": "Feature", "id": 22491594, "geometry": {"type": "Point", "coordinates": [-0.09992, 51.398621]}, "properties": {"woe:id": 22491594, "woe:parent_id": 37370, "woe:name": "Thornton Heath Railway Station", "woe:placetype": 20, "woe:placetype_name": "POI", "woe:lang": "ENG", "iso:country": "GB", "meta:provider": ["geoplanet:7.3.1", "geoplanet:7.3.2", "geoplanet:7.4.0", "geoplanet:7.4.1", "geoplanet:7.5.1", "geoplanet:7.5.2", "geoplanet:7.6.0", "geoplanet:7.8.1", "geoplanet:7.9.0", "geoplanet:7.10.0", "geoplanet:8.0.0", "woeplanet:8.0.0"], "meta:indexed": "2020-08-20T19:45:33.581411", "woe:alias_ENG_V": ["Thornton Heath Station"], "meta:updated": "2020-10-14T11:22:09.532604", "woe:hierarchy": {"continent": 24865675, "country": 23424975, "town": 0, "planet": 1, "county": 23416974, "suburb": 0, "state": 24554868, "region": 0, "localadmin": 12695825}, "woe:timezone_id": 28350903, "woe:hash": "gcpumsz4xtqj", "woe:centroid": [-0.09992, 51.398621], "geom:latitude": 51.398621, "geom:longitude": -0.09992, "geom:hash": "gcpumsz4xtqj", "woe:latitude": 51.398621, "geom:centroid": [-0.09992, 51.398621], "woe:longitude": -0.09992, "woe:repo": "woeplanet-poi-gb", "geom:area": 0.0, "woe:scale": 19}}