{"type": "Feature", "id": 22485457, "geometry": {"type": "Point", "coordinates": [0.1292, 51.567799]}, "properties": {"woe:id": 22485457, "woe:parent_id": 12695835, "woe:name": "Chadwell Heath Railway Station", "woe:placetype": 20, "woe:placetype_name": "POI", "woe:lang": "ENG", "iso:country": "GB", "meta:provider": ["geoplanet:7.4.0", "geoplanet:7.4.1", "geoplanet:7.5.1", "geoplanet:7.5.2", "geoplanet:7.6.0", "geoplanet:7.8.1", "geoplanet:7.9.0", "geoplanet:7.10.0", "geoplanet:8.0.0", "woeplanet:8.0.0"], "meta:indexed": "2020-08-20T23:16:07.659130", "meta:updated": "2020-10-14T11:22:07.860809", "woe:alias_ENG_V": ["Chadwell Heath Station"], "woe:hierarchy": {"continent": 24865675, "country": 23424975, "town": 0, "planet": 1, "county": 23416974, "suburb": 0, "state": 24554868, "region": 0, "localadmin": 12695835}, "woe:timezone_id": 28350903, "woe:hash": "u10j6gwh4w6x", "woe:centroid": [0.1292, 51.567799], "geom:latitude": 51.567799, "geom:longitude": 0.1292, "geom:hash": "u10j6gwh4w6x", "woe:latitude": 51.567799, "geom:centroid": [0.1292, 51.567799], "woe:longitude": 0.1292, "woe:repo": "woeplanet-poi-gb", "geom:area": 0.0, "woe:scale": 19}}