{"type": "Feature", "id": 22456515, "properties": {"woe:id": 22456515, "woe:parent_id": 13911, "woe:name": "Brighton Racecourse", "woe:placetype": 20, "woe:placetype_name": "POI", "woe:lang": "ENG", "iso:country": "GB", "meta:provider": ["geoplanet:7.3.2", "geoplanet:7.4.0", "geoplanet:7.4.1", "geoplanet:7.5.1", "geoplanet:7.5.2", "geoplanet:7.6.0", "geoplanet:7.8.1", "geoplanet:7.9.0", "geoplanet:7.10.0", "geoplanet:8.0.0", "woeplanet:8.0.0"], "meta:indexed": "2020-08-20T21:24:43.312761", "meta:updated": "2020-08-22T02:03:58.002575", "woe:hierarchy": {"continent": 24865675, "country": 23424975, "town": 0, "planet": 1, "county": 12602167, "suburb": 0, "state": 24554868, "region": 0, "localadmin": 12696151}, "woe:timezone_id": 28350903, "woe:hash": "gcpcjmq7zwe2", "woe:centroid": [-0.11194, 50.830299], "geom:latitude": 50.830299, "geom:longitude": -0.11194, "geom:hash": "gcpcjmq7zwe2", "woe:latitude": 50.830299, "geom:centroid": [-0.11194, 50.830299], "woe:longitude": -0.11194, "woe:repo": "woeplanet-poi-gb"}, "geometry": {"coordinates": [-0.11194, 50.830299], "type": "Point"}}