{"type": "Feature", "id": 22457582, "properties": {"woe:id": 22457582, "woe:parent_id": 14653, "woe:name": "Pembrey and Burry Port Railway Station", "woe:placetype": 20, "woe:placetype_name": "POI", "woe:lang": "ENG", "iso:country": "GB", "meta:provider": ["geoplanet:7.3.1", "geoplanet:7.3.2", "geoplanet:7.4.0", "geoplanet:7.4.1", "geoplanet:7.5.1", "geoplanet:7.5.2", "geoplanet:7.6.0", "geoplanet:7.8.1", "geoplanet:7.9.0", "geoplanet:7.10.0", "geoplanet:8.0.0", "woeplanet:8.0.0"], "meta:indexed": "2020-08-20T19:45:31.387647", "woe:alias_ENG_V": ["Pembrey & Burry Port Railway Station", "Pembrey and Burry Port Station", "Pembrey & Burry Port Station"], "meta:updated": "2020-08-22T02:03:28.625715", "woe:hierarchy": {"continent": 24865675, "country": 23424975, "town": 0, "planet": 1, "county": 12602216, "suburb": 0, "state": 12578049, "region": 0, "localadmin": 12696118}, "woe:timezone_id": 28350903, "woe:hash": "gchyp2cc2yft", "woe:centroid": [-4.24927, 51.684059], "geom:latitude": 51.684059, "geom:longitude": -4.24927, "geom:hash": "gchyp2cc2yft", "woe:latitude": 51.684059, "geom:centroid": [-4.24927, 51.684059], "woe:longitude": -4.24927, "woe:repo": "woeplanet-poi-gb"}, "geometry": {"coordinates": [-4.24927, 51.684059], "type": "Point"}}