{"type": "Feature", "id": 22486707, "properties": {"woe:id": 22486707, "woe:parent_id": 34107, "woe:name": "Sawbridgeworth Railway Station", "woe:placetype": 20, "woe:placetype_name": "POI", "woe:lang": "ENG", "iso:country": "GB", "meta:provider": ["geoplanet:7.3.1", "geoplanet:7.3.2", "geoplanet:7.4.0", "geoplanet:7.4.1", "geoplanet:7.5.1", "geoplanet:7.5.2", "geoplanet:7.6.0", "geoplanet:7.8.1", "geoplanet:7.9.0", "geoplanet:7.10.0", "geoplanet:8.0.0", "woeplanet:8.0.0"], "meta:indexed": "2020-08-20T19:45:33.327677", "woe:alias_ENG_V": ["Sawbridgeworth Station"], "meta:updated": "2020-08-22T02:03:29.539777", "woe:hierarchy": {"continent": 24865675, "country": 23424975, "town": 0, "planet": 1, "county": 12602170, "suburb": 0, "state": 24554868, "region": 0, "localadmin": 12695977}, "woe:timezone_id": 28350903, "woe:hash": "u10ng8s1wwnc", "woe:centroid": [0.15959, 51.81456], "geom:latitude": 51.81456, "geom:longitude": 0.15959, "geom:hash": "u10ng8s1wwnc", "woe:latitude": 51.81456, "geom:centroid": [0.15959, 51.81456], "woe:longitude": 0.15959, "woe:repo": "woeplanet-poi-gb"}, "geometry": {"coordinates": [0.15959, 51.81456], "type": "Point"}}