{"type": "Feature", "id": 22467901, "geometry": {"type": "Point", "coordinates": [-0.21558, 51.763779]}, "properties": {"woe:id": 22467901, "woe:parent_id": 22630, "woe:name": "Hatfield Railway Station", "woe:placetype": 20, "woe:placetype_name": "POI", "woe:lang": "ENG", "iso:country": "GB", "meta:provider": ["geoplanet:7.3.1", "geoplanet:7.3.2", "geoplanet:7.4.0", "geoplanet:7.4.1", "geoplanet:7.5.1", "geoplanet:7.5.2", "geoplanet:7.6.0", "geoplanet:7.8.1", "geoplanet:7.9.0", "geoplanet:7.10.0", "geoplanet:8.0.0", "woeplanet:8.0.0"], "meta:indexed": "2020-08-20T19:45:32.046604", "woe:alias_ENG_V": ["Hatfield Station"], "meta:updated": "2020-10-14T11:22:08.748643", "woe:hierarchy": {"continent": 24865675, "country": 23424975, "town": 0, "planet": 1, "county": 12602170, "suburb": 0, "state": 24554868, "region": 0, "localadmin": 12695984}, "woe:timezone_id": 28350903, "woe:hash": "gcpy7p71begc", "woe:centroid": [-0.21558, 51.763779], "geom:latitude": 51.763779, "geom:longitude": -0.21558, "geom:hash": "gcpy7p71begc", "woe:latitude": 51.763779, "geom:centroid": [-0.21558, 51.763779], "woe:longitude": -0.21558, "woe:repo": "woeplanet-poi-gb", "geom:area": 0.0, "woe:scale": 19}}