{"type": "Feature", "id": 23702152, "geometry": {"type": "Point", "coordinates": [0.11797, 52.20578]}, "properties": {"woe:id": 23702152, "woe:parent_id": 43984, "woe:name": "Gonville and Caius College", "woe:placetype": 20, "woe:placetype_name": "POI", "woe:lang": "ENG", "iso:country": "GB", "meta:provider": ["geoplanet:7.3.1", "geoplanet:7.3.2", "geoplanet:7.4.0", "geoplanet:7.4.1", "geoplanet:7.5.1", "geoplanet:7.5.2", "geoplanet:7.6.0", "geoplanet:7.8.1", "geoplanet:7.9.0", "geoplanet:7.10.0", "geoplanet:8.0.0", "woeplanet:8.0.0"], "meta:indexed": "2020-08-20T19:45:34.167589", "woe:alias_ENG_V": ["Gonville & Caius College"], "meta:updated": "2020-10-14T11:21:47.780786", "woe:hierarchy": {"continent": 24865675, "country": 23424975, "town": 0, "planet": 1, "county": 12602140, "suburb": 0, "state": 24554868, "region": 0, "localadmin": 12695882}, "woe:timezone_id": 28350903, "woe:hash": "u120fxvbsyub", "woe:centroid": [0.11797, 52.20578], "geom:latitude": 52.20578, "geom:longitude": 0.11797, "geom:hash": "u120fxvbsyub", "woe:latitude": 52.20578, "geom:centroid": [0.11797, 52.20578], "woe:longitude": 0.11797, "woe:repo": "woeplanet-poi-gb", "geom:area": 0.0, "woe:scale": 19}}