{"type": "Feature", "id": 56068885, "properties": {"woe:id": 56068885, "woe:parent_id": 20094333, "woe:name": "Regal International College", "woe:placetype": 20, "woe:placetype_name": "POI", "woe:lang": "ENG", "iso:country": "GB", "meta:provider": ["geoplanet:7.3.1", "geoplanet:7.3.2", "geoplanet:7.4.0", "geoplanet:7.4.1", "geoplanet:7.5.1", "geoplanet:7.5.2", "geoplanet:7.6.0", "geoplanet:7.8.1", "geoplanet:7.9.0", "geoplanet:7.10.0", "geoplanet:8.0.0", "woeplanet:8.0.0"], "meta:indexed": "2020-08-20T19:45:34.389816", "meta:updated": "2020-08-22T02:03:57.836436", "woe:hierarchy": {"continent": 24865675, "country": 23424975, "town": 0, "planet": 1, "county": 23416974, "suburb": 0, "state": 24554868, "region": 0, "localadmin": 12695815}, "woe:timezone_id": 28350903, "woe:hash": "u10j30y4r8d7", "woe:centroid": [0.05251, 51.552361], "geom:latitude": 51.552361, "geom:longitude": 0.05251, "geom:hash": "u10j30y4r8d7", "woe:latitude": 51.552361, "geom:centroid": [0.05251, 51.552361], "woe:longitude": 0.05251, "woe:repo": "woeplanet-poi-gb"}, "geometry": {"coordinates": [0.05251, 51.552361], "type": "Point"}}