{"type": "Feature", "id": 22473555, "properties": {"woe:id": 22473555, "woe:parent_id": 18287, "woe:name": "Dolau Railway Station", "woe:placetype": 20, "woe:placetype_name": "POI", "woe:lang": "ENG", "iso:country": "GB", "meta:provider": ["geoplanet:7.3.1", "geoplanet:7.3.2", "geoplanet:7.4.0", "geoplanet:7.4.1", "geoplanet:7.5.1", "geoplanet:7.5.2", "geoplanet:7.6.0", "geoplanet:7.8.1", "geoplanet:7.9.0", "geoplanet:7.10.0", "geoplanet:8.0.0", "woeplanet:8.0.0"], "meta:indexed": "2020-08-20T19:45:32.346964", "woe:alias_ENG_V": ["Dolau Station"], "meta:updated": "2020-08-22T02:03:29.074512", "woe:hierarchy": {"continent": 24865675, "country": 23424975, "town": 0, "planet": 1, "county": 12602227, "suburb": 0, "state": 12578049, "region": 0, "localadmin": 12696134}, "woe:timezone_id": 28350903, "woe:hash": "gcm9mzbq6nzx", "woe:centroid": [-3.2625, 52.294659], "geom:latitude": 52.294659, "geom:longitude": -3.2625, "geom:hash": "gcm9mzbq6nzx", "woe:latitude": 52.294659, "geom:centroid": [-3.2625, 52.294659], "woe:longitude": -3.2625, "woe:repo": "woeplanet-poi-gb"}, "geometry": {"coordinates": [-3.2625, 52.294659], "type": "Point"}}