{"type": "Feature", "id": 22468539, "geometry": {"type": "Point", "coordinates": [1.11808, 51.364792]}, "properties": {"woe:id": 22468539, "woe:parent_id": 23078, "woe:name": "Herne Bay Railway Station", "woe:placetype": 20, "woe:placetype_name": "POI", "woe:lang": "ENG", "iso:country": "GB", "meta:provider": ["geoplanet:7.3.1", "geoplanet:7.3.2", "geoplanet:7.4.0", "geoplanet:7.4.1", "geoplanet:7.5.1", "geoplanet:7.5.2", "geoplanet:7.6.0", "geoplanet:7.8.1", "geoplanet:7.9.0", "geoplanet:7.10.0", "geoplanet:8.0.0", "woeplanet:8.0.0"], "meta:indexed": "2020-08-20T19:45:32.084246", "woe:alias_ENG_V": ["Herne Bay Station"], "meta:updated": "2020-10-14T11:22:08.521083", "woe:hierarchy": {"continent": 24865675, "country": 23424975, "town": 0, "planet": 1, "county": 12602173, "suburb": 0, "state": 24554868, "region": 0, "localadmin": 12695986}, "woe:timezone_id": 28350903, "woe:hash": "u10u1qwjt5hz", "woe:centroid": [1.11808, 51.364792], "geom:latitude": 51.364792, "geom:longitude": 1.11808, "geom:hash": "u10u1qwjt5hz", "woe:latitude": 51.364792, "geom:centroid": [1.11808, 51.364792], "woe:longitude": 1.11808, "woe:repo": "woeplanet-poi-gb", "geom:area": 0.0, "woe:scale": 19}}