{"type": "Feature", "id": 22455813, "geometry": {"type": "Point", "coordinates": [-1.76905, 53.819832]}, "properties": {"woe:id": 22455813, "woe:parent_id": 34649, "woe:name": "Frizinghall Railway Station", "woe:placetype": 20, "woe:placetype_name": "POI", "woe:lang": "ENG", "iso:country": "GB", "meta:provider": ["geoplanet:7.3.1", "geoplanet:7.3.2", "geoplanet:7.4.0", "geoplanet:7.4.1", "geoplanet:7.5.1", "geoplanet:7.5.2", "geoplanet:7.6.0", "geoplanet:7.8.1", "geoplanet:7.9.0", "geoplanet:7.10.0", "geoplanet:8.0.0", "woeplanet:8.0.0"], "meta:indexed": "2020-08-20T19:45:31.282248", "woe:alias_ENG_V": ["Frizinghall Station"], "meta:updated": "2020-10-14T11:22:07.708098", "woe:hierarchy": {"continent": 24865675, "country": 23424975, "town": 0, "planet": 1, "county": 12602197, "suburb": 0, "state": 24554868, "region": 0, "localadmin": 12695870}, "woe:timezone_id": 28350903, "woe:hash": "gcwdptxg4pue", "woe:centroid": [-1.76905, 53.819832], "geom:latitude": 53.819832, "geom:longitude": -1.76905, "geom:hash": "gcwdptxg4pue", "woe:latitude": 53.819832, "geom:centroid": [-1.76905, 53.819832], "woe:longitude": -1.76905, "woe:repo": "woeplanet-poi-gb", "geom:area": 0.0, "woe:scale": 19}}