{"type": "Feature", "id": 22482739, "properties": {"woe:id": 22482739, "woe:parent_id": 31342, "woe:name": "Paisley Saint James Railway Station", "woe:placetype": 20, "woe:placetype_name": "POI", "woe:lang": "ENG", "iso:country": "GB", "meta:provider": ["geoplanet:7.3.1", "geoplanet:7.3.2", "geoplanet:7.4.0", "geoplanet:7.4.1", "geoplanet:7.5.1", "geoplanet:7.5.2", "geoplanet:7.6.0", "geoplanet:7.8.1", "geoplanet:7.9.0", "geoplanet:7.10.0", "geoplanet:8.0.0", "woeplanet:8.0.0"], "meta:indexed": "2020-08-20T19:45:33.097979", "woe:alias_ENG_V": ["Paisley St James Railway Station", "Paisley St James Station", "Paisley Saint James Station"], "meta:updated": "2020-08-22T02:03:29.431927", "woe:hierarchy": {"continent": 24865675, "country": 23424975, "town": 0, "planet": 1, "county": 12602207, "suburb": 0, "state": 12578048, "region": 0, "localadmin": 12696207}, "woe:timezone_id": 28350903, "woe:hash": "gcuvdzsfgbnx", "woe:centroid": [-4.44277, 55.852219], "geom:latitude": 55.852219, "geom:longitude": -4.44277, "geom:hash": "gcuvdzsfgbnx", "woe:latitude": 55.852219, "geom:centroid": [-4.44277, 55.852219], "woe:longitude": -4.44277, "woe:repo": "woeplanet-poi-gb"}, "geometry": {"coordinates": [-4.44277, 55.852219], "type": "Point"}}