{"type": "Feature", "id": 22461010, "properties": {"woe:id": 22461010, "woe:parent_id": 17064, "woe:name": "Central Park", "woe:placetype": 20, "woe:placetype_name": "POI", "woe:lang": "ENG", "iso:country": "GB", "meta:provider": ["geoplanet:7.3.1", "geoplanet:7.3.2", "geoplanet:7.4.0", "geoplanet:7.4.1", "geoplanet:7.5.1", "geoplanet:7.5.2", "geoplanet:7.6.0", "geoplanet:7.8.1", "geoplanet:7.9.0", "geoplanet:7.10.0", "geoplanet:8.0.0", "woeplanet:8.0.0"], "meta:indexed": "2020-08-20T19:45:31.574529", "meta:updated": "2020-08-22T02:03:28.710847", "woe:alias_ENG_V": ["Cowdenbeath Football Club"], "woe:hierarchy": {"continent": 24865675, "country": 23424975, "town": 0, "planet": 1, "county": 12602201, "suburb": 0, "state": 12578048, "region": 0, "localadmin": 12696197}, "woe:timezone_id": 28350903, "woe:hash": "gcvx5y68ygv2", "woe:centroid": [-3.3471, 56.1087], "geom:latitude": 56.1087, "geom:longitude": -3.3471, "geom:hash": "gcvx5y68ygv2", "woe:latitude": 56.1087, "geom:centroid": [-3.3471, 56.1087], "woe:longitude": -3.3471, "woe:repo": "woeplanet-poi-gb"}, "geometry": {"coordinates": [-3.3471, 56.1087], "type": "Point"}}