{"type": "Feature", "id": 22460701, "geometry": {"type": "Point", "coordinates": [-3.8299, 53.281101]}, "properties": {"woe:id": 22460701, "woe:parent_id": 16785, "woe:name": "Plas Mawr", "woe:placetype": 20, "woe:placetype_name": "POI", "woe:lang": "ENG", "iso:country": "GB", "meta:provider": ["geoplanet:7.3.1", "geoplanet:7.3.2", "geoplanet:7.4.0", "geoplanet:7.4.1", "geoplanet:7.5.1", "geoplanet:7.5.2", "geoplanet:7.6.0", "geoplanet:7.8.1", "geoplanet:7.9.0", "geoplanet:7.10.0", "geoplanet:8.0.0", "woeplanet:8.0.0"], "meta:indexed": "2020-08-20T19:45:31.564781", "meta:updated": "2020-10-14T11:22:08.721640", "woe:hierarchy": {"continent": 24865675, "country": 23424975, "town": 0, "planet": 1, "county": 12602218, "suburb": 0, "state": 12578049, "region": 0, "localadmin": 12696128}, "woe:timezone_id": 28350903, "woe:hash": "gcmr0ge0uv5e", "woe:centroid": [-3.8299, 53.281101], "geom:latitude": 53.281101, "geom:longitude": -3.8299, "geom:hash": "gcmr0ge0uv5e", "woe:latitude": 53.281101, "geom:centroid": [-3.8299, 53.281101], "woe:longitude": -3.8299, "woe:repo": "woeplanet-poi-gb", "geom:area": 0.0, "woe:scale": 19}}