{"type": "Feature", "id": 23702315, "properties": {"woe:id": 23702315, "woe:parent_id": 20094233, "woe:name": "University of Wales-Institute", "woe:placetype": 20, "woe:placetype_name": "POI", "woe:lang": "ENG", "iso:country": "GB", "meta:provider": ["geoplanet:7.3.1", "geoplanet:7.3.2", "geoplanet:7.4.0", "geoplanet:7.4.1", "geoplanet:7.5.1", "geoplanet:7.5.2", "geoplanet:7.6.0", "geoplanet:7.8.1", "geoplanet:7.9.0", "geoplanet:7.10.0", "geoplanet:8.0.0", "woeplanet:8.0.0"], "meta:indexed": "2020-08-20T19:45:34.324175", "woe:alias_ENG_V": ["University of Wales Institute", "UWIC", "University of Wales Institute, Cardiff"], "meta:updated": "2020-08-22T02:03:29.956774", "woe:hierarchy": {"continent": 24865675, "country": 23424975, "town": 0, "planet": 1, "county": 12602215, "suburb": 0, "state": 12578049, "region": 0, "localadmin": 12696132}, "woe:timezone_id": 28350903, "woe:hash": "gcjsyymjbgsj", "woe:centroid": [-3.21209, 51.4953], "geom:latitude": 51.4953, "geom:longitude": -3.21209, "geom:hash": "gcjsyymjbgsj", "woe:latitude": 51.4953, "geom:centroid": [-3.21209, 51.4953], "woe:longitude": -3.21209, "woe:repo": "woeplanet-poi-gb"}, "geometry": {"coordinates": [-3.21209, 51.4953], "type": "Point"}}