{"type": "Feature", "id": 23367986, "geometry": {"type": "Point", "coordinates": [-3.30987, 57.64901]}, "properties": {"woe:id": 23367986, "woe:parent_id": 19450, "woe:name": "Elgin Museum", "woe:placetype": 20, "woe:placetype_name": "POI", "woe:lang": "ENG", "iso:country": "GB", "meta:provider": ["geoplanet:7.3.1", "geoplanet:7.3.2", "geoplanet:7.4.0", "geoplanet:7.4.1", "geoplanet:7.5.1", "geoplanet:7.5.2", "geoplanet:7.6.0", "geoplanet:7.8.1", "geoplanet:7.9.0", "geoplanet:7.10.0", "geoplanet:8.0.0", "woeplanet:8.0.0"], "meta:indexed": "2020-08-20T19:45:33.852071", "meta:updated": "2020-10-14T11:21:47.654739", "woe:hierarchy": {"continent": 24865675, "country": 23424975, "town": 0, "planet": 1, "county": 12602202, "suburb": 0, "state": 12578048, "region": 0, "localadmin": 12696202}, "woe:timezone_id": 28350903, "woe:hash": "gfjxuwtvf6q5", "woe:centroid": [-3.30987, 57.64901], "geom:latitude": 57.64901, "geom:longitude": -3.30987, "geom:hash": "gfjxuwtvf6q5", "woe:latitude": 57.64901, "geom:centroid": [-3.30987, 57.64901], "woe:longitude": -3.30987, "woe:repo": "woeplanet-poi-gb", "geom:area": 0.0, "woe:scale": 19}}