{"type": "Feature", "id": 56069036, "geometry": {"type": "Point", "coordinates": [-1.86919, 50.732231]}, "properties": {"woe:id": 56069036, "woe:parent_id": 28276336, "woe:name": "Gate College", "woe:placetype": 20, "woe:placetype_name": "POI", "woe:lang": "ENG", "iso:country": "GB", "meta:provider": ["geoplanet:7.3.1", "geoplanet:7.3.2", "geoplanet:7.4.0", "geoplanet:7.4.1", "geoplanet:7.5.1", "geoplanet:7.5.2", "geoplanet:7.6.0", "geoplanet:7.8.1", "geoplanet:7.9.0", "geoplanet:7.10.0", "geoplanet:8.0.0", "woeplanet:8.0.0"], "meta:indexed": "2020-08-20T19:45:34.505102", "meta:updated": "2020-10-14T11:22:10.233114", "woe:hierarchy": {"continent": 24865675, "country": 23424975, "town": 0, "planet": 1, "county": 12602183, "suburb": 0, "state": 24554868, "region": 0, "localadmin": 12696150}, "woe:timezone_id": 28350903, "woe:hash": "gcn8t7wbstqc", "woe:centroid": [-1.86919, 50.732231], "geom:latitude": 50.732231, "geom:longitude": -1.86919, "geom:hash": "gcn8t7wbstqc", "woe:latitude": 50.732231, "geom:centroid": [-1.86919, 50.732231], "woe:longitude": -1.86919, "woe:repo": "woeplanet-poi-gb", "geom:area": 0.0, "woe:scale": 19}}