{"type": "Feature", "id": 22495513, "geometry": {"type": "Point", "coordinates": [-0.24516, 51.381229]}, "properties": {"woe:id": 22495513, "woe:parent_id": 20089316, "woe:name": "Worcester Park Railway Station", "woe:placetype": 20, "woe:placetype_name": "POI", "woe:lang": "ENG", "iso:country": "GB", "meta:provider": ["geoplanet:7.3.1", "geoplanet:7.3.2", "geoplanet:7.4.0", "geoplanet:7.4.1", "geoplanet:7.5.1", "geoplanet:7.5.2", "geoplanet:7.6.0", "geoplanet:7.8.1", "geoplanet:7.9.0", "geoplanet:7.10.0", "geoplanet:8.0.0", "woeplanet:8.0.0"], "meta:indexed": "2020-08-20T19:45:33.799444", "woe:alias_ENG_V": ["Worcester Park Station"], "meta:updated": "2020-10-14T11:22:08.791318", "woe:hierarchy": {"continent": 24865675, "country": 23424975, "town": 0, "planet": 1, "county": 23416974, "suburb": 0, "state": 24554868, "region": 0, "localadmin": 12695833}, "woe:timezone_id": 28350903, "woe:hash": "gcpu63tmr773", "woe:centroid": [-0.24516, 51.381229], "geom:latitude": 51.381229, "geom:longitude": -0.24516, "geom:hash": "gcpu63tmr773", "woe:latitude": 51.381229, "geom:centroid": [-0.24516, 51.381229], "woe:longitude": -0.24516, "woe:repo": "woeplanet-poi-gb", "geom:area": 0.0, "woe:scale": 19}}