{"type": "Feature", "id": 22493986, "geometry": {"type": "Point", "coordinates": [-1.36444, 53.933899]}, "properties": {"woe:id": 22493986, "woe:parent_id": 24409, "woe:name": "Wetherby Racecourse", "woe:placetype": 20, "woe:placetype_name": "POI", "woe:lang": "ENG", "iso:country": "GB", "meta:provider": ["geoplanet:7.3.2", "geoplanet:7.4.0", "geoplanet:7.4.1", "geoplanet:7.5.1", "geoplanet:7.5.2", "geoplanet:7.6.0", "geoplanet:7.8.1", "geoplanet:7.9.0", "geoplanet:7.10.0", "geoplanet:8.0.0", "woeplanet:8.0.0"], "meta:indexed": "2020-08-20T21:24:46.052917", "meta:updated": "2020-10-14T11:22:09.130630", "woe:hierarchy": {"continent": 24865675, "country": 23424975, "town": 0, "planet": 1, "county": 12602197, "suburb": 0, "state": 24554868, "region": 0, "localadmin": 12695873}, "woe:timezone_id": 28350903, "woe:hash": "gcx4bfq7wprz", "woe:centroid": [-1.36444, 53.933899], "geom:latitude": 53.933899, "geom:longitude": -1.36444, "geom:hash": "gcx4bfq7wprz", "woe:latitude": 53.933899, "geom:centroid": [-1.36444, 53.933899], "woe:longitude": -1.36444, "woe:repo": "woeplanet-poi-gb", "geom:area": 0.0, "woe:scale": 19}}