{"type": "Feature", "id": 23380397, "geometry": {"type": "Point", "coordinates": [-0.13306, 51.523602]}, "properties": {"woe:id": 23380397, "woe:parent_id": 43265, "woe:name": "Petrie Museum of Egyptian Archaeology", "woe:placetype": 20, "woe:placetype_name": "POI", "woe:lang": "ENG", "iso:country": "GB", "meta:provider": ["geoplanet:7.3.1", "geoplanet:7.3.2", "geoplanet:7.4.0", "geoplanet:7.4.1", "geoplanet:7.5.1", "geoplanet:7.5.2", "geoplanet:7.6.0", "geoplanet:7.8.1", "geoplanet:7.9.0", "geoplanet:7.10.0", "geoplanet:8.0.0", "woeplanet:8.0.0"], "meta:indexed": "2020-08-20T19:45:33.874009", "meta:updated": "2020-10-14T11:21:47.634279", "woe:alias_ENG_V": ["Petrie Egyptian Archaeology Museum"], "woe:hierarchy": {"continent": 24865675, "country": 23424975, "town": 0, "planet": 1, "county": 23416974, "suburb": 0, "state": 24554868, "region": 0, "localadmin": 12695807}, "woe:timezone_id": 28350903, "woe:hash": "gcpvhgx4erx3", "woe:centroid": [-0.13306, 51.523602], "geom:latitude": 51.523602, "geom:longitude": -0.13306, "geom:hash": "gcpvhgx4erx3", "woe:latitude": 51.523602, "geom:centroid": [-0.13306, 51.523602], "woe:longitude": -0.13306, "woe:repo": "woeplanet-poi-gb", "geom:area": 0.0, "woe:scale": 19}}