{"type": "Feature", "id": 22450813, "geometry": {"type": "Point", "coordinates": [-3.42999, 51.716999]}, "properties": {"woe:id": 22450813, "woe:parent_id": 10216, "woe:name": "Aberdare Golf Course", "woe:placetype": 20, "woe:placetype_name": "POI", "woe:lang": "ENG", "iso:country": "GB", "meta:provider": ["geoplanet:7.3.1", "geoplanet:7.3.2", "geoplanet:7.4.0", "geoplanet:7.4.1", "geoplanet:7.5.1", "geoplanet:7.5.2", "geoplanet:7.6.0", "geoplanet:7.8.1", "geoplanet:7.9.0", "geoplanet:7.10.0", "geoplanet:8.0.0", "woeplanet:8.0.0"], "meta:indexed": "2020-08-20T19:45:30.935790", "meta:updated": "2020-10-14T11:22:08.412321", "woe:hierarchy": {"continent": 24865675, "country": 23424975, "town": 0, "planet": 1, "county": 12602228, "suburb": 0, "state": 12578049, "region": 0, "localadmin": 12696115}, "woe:timezone_id": 28350903, "woe:hash": "gcjw1yy377q5", "woe:centroid": [-3.42999, 51.716999], "geom:latitude": 51.716999, "geom:longitude": -3.42999, "geom:hash": "gcjw1yy377q5", "woe:latitude": 51.716999, "geom:centroid": [-3.42999, 51.716999], "woe:longitude": -3.42999, "woe:repo": "woeplanet-poi-gb", "geom:area": 0.0, "woe:scale": 19}}