{"type": "Feature", "id": 56069052, "properties": {"woe:id": 56069052, "woe:parent_id": 19245, "woe:name": "City College", "woe:placetype": 20, "woe:placetype_name": "POI", "woe:lang": "ENG", "iso:country": "GB", "meta:provider": ["geoplanet:7.3.1", "geoplanet:7.3.2", "geoplanet:7.4.0", "geoplanet:7.4.1", "geoplanet:7.5.1", "geoplanet:7.5.2", "geoplanet:7.6.0", "geoplanet:7.8.1", "geoplanet:7.9.0", "geoplanet:7.10.0", "geoplanet:8.0.0", "woeplanet:8.0.0"], "meta:indexed": "2020-08-20T19:45:34.517508", "meta:updated": "2020-08-22T02:03:57.908402", "woe:hierarchy": {"continent": 24865675, "country": 23424975, "town": 0, "planet": 1, "county": 12602141, "suburb": 0, "state": 24554868, "region": 0, "localadmin": 12696028}, "woe:timezone_id": 28350903, "woe:hash": "u12gm4x77k05", "woe:centroid": [1.28451, 52.616852], "geom:latitude": 52.616852, "geom:longitude": 1.28451, "geom:hash": "u12gm4x77k05", "woe:latitude": 52.616852, "geom:centroid": [1.28451, 52.616852], "woe:longitude": 1.28451, "woe:repo": "woeplanet-poi-gb"}, "geometry": {"coordinates": [1.28451, 52.616852], "type": "Point"}}