{"type": "Feature", "id": 23702143, "geometry": {"type": "Point", "coordinates": [0.10312, 52.212891]}, "properties": {"woe:id": 23702143, "woe:parent_id": 43984, "woe:name": "Churchill College", "woe:placetype": 20, "woe:placetype_name": "POI", "woe:lang": "ENG", "iso:country": "GB", "meta:provider": ["geoplanet:7.3.1", "geoplanet:7.3.2", "geoplanet:7.4.0", "geoplanet:7.4.1", "geoplanet:7.5.1", "geoplanet:7.5.2", "geoplanet:7.6.0", "geoplanet:7.8.1", "geoplanet:7.9.0", "geoplanet:7.10.0", "geoplanet:8.0.0", "woeplanet:8.0.0"], "meta:indexed": "2020-08-20T19:45:34.162239", "meta:updated": "2020-10-14T11:21:47.822086", "woe:hierarchy": {"continent": 24865675, "country": 23424975, "town": 0, "planet": 1, "county": 12602140, "suburb": 0, "state": 24554868, "region": 0, "localadmin": 12695882}, "woe:timezone_id": 28350903, "woe:hash": "u12143544u7f", "woe:centroid": [0.10312, 52.212891], "geom:latitude": 52.212891, "geom:longitude": 0.10312, "geom:hash": "u12143544u7f", "woe:latitude": 52.212891, "geom:centroid": [0.10312, 52.212891], "woe:longitude": 0.10312, "woe:repo": "woeplanet-poi-gb", "geom:area": 0.0, "woe:scale": 19}}