{"type": "Feature", "id": 22452083, "geometry": {"type": "Point", "coordinates": [1.02246, 52.514889]}, "properties": {"woe:id": 22452083, "woe:parent_id": 11362, "woe:name": "Attleborough Railway Station", "woe:placetype": 20, "woe:placetype_name": "POI", "woe:lang": "ENG", "iso:country": "GB", "meta:provider": ["geoplanet:7.3.1", "geoplanet:7.3.2", "geoplanet:7.4.0", "geoplanet:7.4.1", "geoplanet:7.5.1", "geoplanet:7.5.2", "geoplanet:7.6.0", "geoplanet:7.8.1", "geoplanet:7.9.0", "geoplanet:7.10.0", "geoplanet:8.0.0", "woeplanet:8.0.0"], "meta:indexed": "2020-08-20T19:45:31.039769", "woe:alias_ENG_V": ["Attleborough Station"], "meta:updated": "2020-10-14T11:22:09.187266", "woe:hierarchy": {"continent": 24865675, "country": 23424975, "town": 0, "planet": 1, "county": 12602141, "suburb": 0, "state": 24554868, "region": 0, "localadmin": 12696023}, "woe:timezone_id": 28350903, "woe:hash": "u12dz2093hc7", "woe:centroid": [1.02246, 52.514889], "geom:latitude": 52.514889, "geom:longitude": 1.02246, "geom:hash": "u12dz2093hc7", "woe:latitude": 52.514889, "geom:centroid": [1.02246, 52.514889], "woe:longitude": 1.02246, "woe:repo": "woeplanet-poi-gb", "geom:area": 0.0, "woe:scale": 19}}