{"type": "Feature", "id": 22457015, "properties": {"woe:id": 22457015, "woe:parent_id": 12696146, "woe:name": "University of the West of England", "woe:placetype": 20, "woe:placetype_name": "POI", "woe:lang": "ENG", "iso:country": "GB", "meta:provider": ["geoplanet:7.3.1", "geoplanet:7.3.2", "geoplanet:7.4.0", "geoplanet:7.4.1", "geoplanet:7.5.1", "geoplanet:7.5.2", "geoplanet:7.6.0", "geoplanet:7.8.1", "geoplanet:7.9.0", "geoplanet:7.10.0", "geoplanet:8.0.0", "woeplanet:8.0.0"], "meta:indexed": "2020-08-20T19:45:34.257167", "woe:alias_ENG_V": ["Univ West England Frenchay Campus", "UWE", "the West of England University"], "meta:updated": "2020-08-22T02:03:29.924035", "woe:hierarchy": {"continent": 24865675, "country": 23424975, "town": 0, "planet": 1, "county": 12602184, "suburb": 0, "state": 24554868, "region": 0, "localadmin": 12696146}, "woe:timezone_id": 28350903, "woe:hash": "gcnhyp6pwkdq", "woe:centroid": [-2.54581, 51.501099], "geom:latitude": 51.501099, "geom:longitude": -2.54581, "geom:hash": "gcnhyp6pwkdq", "woe:latitude": 51.501099, "geom:centroid": [-2.54581, 51.501099], "woe:longitude": -2.54581, "woe:repo": "woeplanet-poi-gb"}, "geometry": {"coordinates": [-2.54581, 51.501099], "type": "Point"}}