{"type": "Feature", "id": 22482820, "geometry": {"type": "Point", "coordinates": [-3.18077, 51.440109]}, "properties": {"woe:id": 22482820, "woe:parent_id": 31623, "woe:name": "Dingle Road Railway Station", "woe:placetype": 20, "woe:placetype_name": "POI", "woe:lang": "ENG", "iso:country": "GB", "meta:provider": ["geoplanet:7.3.1", "geoplanet:7.3.2", "geoplanet:7.4.0", "geoplanet:7.4.1", "geoplanet:7.5.1", "geoplanet:7.5.2", "geoplanet:7.6.0", "geoplanet:7.8.1", "geoplanet:7.9.0", "geoplanet:7.10.0", "geoplanet:8.0.0", "woeplanet:8.0.0"], "meta:indexed": "2020-08-20T19:45:33.102492", "woe:alias_ENG_V": ["Dingle Road Station"], "meta:updated": "2020-10-14T11:22:08.717550", "woe:alias_UNK_Q": ["Heol Dingle"], "woe:hierarchy": {"continent": 24865675, "country": 23424975, "town": 0, "planet": 1, "county": 12602231, "suburb": 0, "state": 12578049, "region": 0, "localadmin": 12696121}, "woe:timezone_id": 28350903, "woe:hash": "gcjsxs7u6emf", "woe:centroid": [-3.18077, 51.440109], "geom:latitude": 51.440109, "geom:longitude": -3.18077, "geom:hash": "gcjsxs7u6emf", "woe:latitude": 51.440109, "geom:centroid": [-3.18077, 51.440109], "woe:longitude": -3.18077, "woe:repo": "woeplanet-poi-gb", "geom:area": 0.0, "woe:scale": 19}}