{"type": "Feature", "id": 22453555, "properties": {"woe:id": 22453555, "woe:parent_id": 24761, "woe:name": "Kempston Hardwick Railway Station", "woe:placetype": 20, "woe:placetype_name": "POI", "woe:lang": "ENG", "iso:country": "GB", "meta:provider": ["geoplanet:7.3.1", "geoplanet:7.3.2", "geoplanet:7.4.0", "geoplanet:7.4.1", "geoplanet:7.5.1", "geoplanet:7.5.2", "geoplanet:7.6.0", "geoplanet:7.8.1", "geoplanet:7.9.0", "geoplanet:7.10.0", "geoplanet:8.0.0", "woeplanet:8.0.0"], "meta:indexed": "2020-08-20T19:45:31.147073", "woe:alias_ENG_V": ["Kempston Hardwick Station"], "meta:updated": "2020-08-22T02:03:28.533168", "woe:hierarchy": {"continent": 24865675, "country": 23424975, "town": 0, "planet": 1, "county": 12602163, "suburb": 0, "state": 24554868, "region": 0, "localadmin": 12695876}, "woe:timezone_id": 28350903, "woe:hash": "gcr8ke1hs5ue", "woe:centroid": [-0.50382, 52.092468], "geom:latitude": 52.092468, "geom:longitude": -0.50382, "geom:hash": "gcr8ke1hs5ue", "woe:latitude": 52.092468, "geom:centroid": [-0.50382, 52.092468], "woe:longitude": -0.50382, "woe:repo": "woeplanet-poi-gb"}, "geometry": {"coordinates": [-0.50382, 52.092468], "type": "Point"}}