{"type": "Feature", "id": 22465916, "geometry": {"type": "Point", "coordinates": [-4.32452, 55.813351]}, "properties": {"woe:id": 22465916, "woe:parent_id": 31510, "woe:name": "Kennishead Railway Station", "woe:placetype": 20, "woe:placetype_name": "POI", "woe:lang": "ENG", "iso:country": "GB", "meta:provider": ["geoplanet:7.3.1", "geoplanet:7.3.2", "geoplanet:7.4.0", "geoplanet:7.4.1", "geoplanet:7.5.1", "geoplanet:7.5.2", "geoplanet:7.6.0", "geoplanet:7.8.1", "geoplanet:7.9.0", "geoplanet:7.10.0", "geoplanet:8.0.0", "woeplanet:8.0.0"], "meta:indexed": "2020-08-20T19:45:31.903918", "woe:alias_ENG_V": ["Kennishead Station"], "meta:updated": "2020-10-14T11:22:09.593591", "woe:hierarchy": {"continent": 24865675, "country": 23424975, "town": 0, "planet": 1, "county": 12602207, "suburb": 0, "state": 12578048, "region": 0, "localadmin": 12696198}, "woe:timezone_id": 28350903, "woe:hash": "gcuvt8dbr6sp", "woe:centroid": [-4.32452, 55.813351], "geom:latitude": 55.813351, "geom:longitude": -4.32452, "geom:hash": "gcuvt8dbr6sp", "woe:latitude": 55.813351, "geom:centroid": [-4.32452, 55.813351], "woe:longitude": -4.32452, "woe:repo": "woeplanet-poi-gb", "geom:area": 0.0, "woe:scale": 19}}