{"type": "Feature", "id": 23377402, "geometry": {"type": "Point", "coordinates": [-1.20146, 53.27927]}, "properties": {"woe:id": 23377402, "woe:parent_id": 40369, "woe:name": "Whitwel Railway Station", "woe:placetype": 20, "woe:placetype_name": "POI", "woe:lang": "ENG", "iso:country": "GB", "meta:provider": ["geoplanet:7.3.1", "geoplanet:7.3.2", "geoplanet:7.4.0", "geoplanet:7.4.1", "geoplanet:7.5.1", "geoplanet:7.5.2", "geoplanet:7.6.0", "geoplanet:7.8.1", "geoplanet:7.9.0", "geoplanet:7.10.0", "geoplanet:8.0.0", "woeplanet:8.0.0"], "meta:indexed": "2020-08-20T19:45:33.869902", "woe:alias_ENG_V": ["Whitwell Railway Station", "Whitwell Station", "Whitwel Station"], "meta:updated": "2020-10-14T11:21:47.657111", "woe:hierarchy": {"continent": 24865675, "country": 23424975, "town": 0, "planet": 1, "county": 12602143, "suburb": 0, "state": 24554868, "region": 0, "localadmin": 12695907}, "woe:timezone_id": 28350903, "woe:hash": "gcrphejn5zy3", "woe:centroid": [-1.20146, 53.27927], "geom:latitude": 53.27927, "geom:longitude": -1.20146, "geom:hash": "gcrphejn5zy3", "woe:latitude": 53.27927, "geom:centroid": [-1.20146, 53.27927], "woe:longitude": -1.20146, "woe:repo": "woeplanet-poi-gb", "geom:area": 0.0, "woe:scale": 19}}