{"type": "Feature", "id": 22453879, "geometry": {"type": "Point", "coordinates": [0.15982, 51.465]}, "properties": {"woe:id": 22453879, "woe:parent_id": 11898, "woe:name": "Barnehurst Railway Station", "woe:placetype": 20, "woe:placetype_name": "POI", "woe:lang": "ENG", "iso:country": "GB", "meta:provider": ["geoplanet:7.3.1", "geoplanet:7.3.2", "geoplanet:7.4.0", "geoplanet:7.4.1", "geoplanet:7.5.1", "geoplanet:7.5.2", "geoplanet:7.6.0", "geoplanet:7.8.1", "geoplanet:7.9.0", "geoplanet:7.10.0", "geoplanet:8.0.0", "woeplanet:8.0.0"], "meta:indexed": "2020-08-20T19:45:31.174989", "woe:alias_ENG_V": ["Barnehurst Station"], "meta:updated": "2020-10-14T11:22:07.736621", "woe:hierarchy": {"continent": 24865675, "country": 23424975, "town": 0, "planet": 1, "county": 23416974, "suburb": 0, "state": 24554868, "region": 0, "localadmin": 12695822}, "woe:timezone_id": 28350903, "woe:hash": "u10hg8umk567", "woe:centroid": [0.15982, 51.465], "geom:latitude": 51.465, "geom:longitude": 0.15982, "geom:hash": "u10hg8umk567", "woe:latitude": 51.465, "geom:centroid": [0.15982, 51.465], "woe:longitude": 0.15982, "woe:repo": "woeplanet-poi-gb", "geom:area": 0.0, "woe:scale": 19}}