{"type": "Feature", "id": 23366930, "properties": {"woe:id": 23366930, "woe:parent_id": 37829, "woe:name": "Marischal Museum", "woe:placetype": 20, "woe:placetype_name": "POI", "woe:lang": "ENG", "iso:country": "GB", "meta:provider": ["geoplanet:7.3.1", "geoplanet:7.3.2", "geoplanet:7.4.0", "geoplanet:7.4.1", "geoplanet:7.5.1", "geoplanet:7.5.2", "geoplanet:7.6.0", "geoplanet:7.8.1", "geoplanet:7.9.0", "geoplanet:7.10.0", "geoplanet:8.0.0", "woeplanet:8.0.0"], "meta:indexed": "2020-08-20T19:45:33.836328", "meta:updated": "2020-08-22T02:03:29.784054", "woe:hierarchy": {"continent": 24865675, "country": 23424975, "town": 0, "planet": 1, "county": 12602202, "suburb": 0, "state": 12578048, "region": 0, "localadmin": 12696182}, "woe:timezone_id": 28350903, "woe:hash": "gfnt07959e0u", "woe:centroid": [-2.09695, 57.14875], "geom:latitude": 57.14875, "geom:longitude": -2.09695, "geom:hash": "gfnt07959e0u", "woe:latitude": 57.14875, "geom:centroid": [-2.09695, 57.14875], "woe:longitude": -2.09695, "woe:repo": "woeplanet-poi-gb"}, "geometry": {"coordinates": [-2.09695, 57.14875], "type": "Point"}}