{"type": "Feature", "id": 22454703, "properties": {"woe:id": 22454703, "woe:parent_id": 12723, "woe:name": "University Railway Station", "woe:placetype": 20, "woe:placetype_name": "POI", "woe:lang": "ENG", "iso:country": "GB", "meta:provider": ["geoplanet:7.3.1", "geoplanet:7.3.2", "geoplanet:7.4.0", "geoplanet:7.4.1", "geoplanet:7.5.1", "geoplanet:7.5.2", "geoplanet:7.6.0", "geoplanet:7.8.1", "geoplanet:7.9.0", "geoplanet:7.10.0", "geoplanet:8.0.0", "woeplanet:8.0.0"], "meta:indexed": "2020-08-20T19:45:31.227653", "woe:alias_ENG_V": ["University Station"], "meta:updated": "2020-08-22T02:03:28.566335", "woe:hierarchy": {"continent": 24865675, "country": 23424975, "town": 0, "planet": 1, "county": 12602191, "suburb": 0, "state": 24554868, "region": 0, "localadmin": 12695863}, "woe:timezone_id": 28350903, "woe:hash": "gcqd7umqjufs", "woe:centroid": [-1.93712, 52.45116], "geom:latitude": 52.45116, "geom:longitude": -1.93712, "geom:hash": "gcqd7umqjufs", "woe:latitude": 52.45116, "geom:centroid": [-1.93712, 52.45116], "woe:longitude": -1.93712, "woe:repo": "woeplanet-poi-gb"}, "geometry": {"coordinates": [-1.93712, 52.45116], "type": "Point"}}