{"type": "Feature", "id": 23689629, "properties": {"woe:id": 23689629, "woe:parent_id": 12695819, "woe:name": "Charing Cross Road", "woe:placetype": 20, "woe:placetype_name": "POI", "woe:lang": "ENG", "iso:country": "GB", "meta:provider": ["geoplanet:7.3.1", "geoplanet:7.3.2", "geoplanet:7.4.0", "geoplanet:7.4.1", "geoplanet:7.5.1", "geoplanet:7.5.2", "geoplanet:7.6.0", "geoplanet:7.8.1", "geoplanet:7.9.0", "geoplanet:7.10.0", "geoplanet:8.0.0", "woeplanet:8.0.0"], "meta:indexed": "2020-08-20T19:45:33.905424", "woe:alias_ENG_V": ["Charingcrossroad"], "meta:updated": "2020-08-22T02:03:29.807542", "woe:hierarchy": {"continent": 24865675, "country": 23424975, "town": 0, "planet": 1, "county": 23416974, "suburb": 0, "state": 24554868, "region": 0, "localadmin": 12695819}, "woe:timezone_id": 28350903, "woe:hash": "gcpvj1dhf3d5", "woe:centroid": [-0.12899, 51.51297], "geom:latitude": 51.51297, "geom:longitude": -0.12899, "geom:hash": "gcpvj1dhf3d5", "woe:latitude": 51.51297, "geom:centroid": [-0.12899, 51.51297], "woe:longitude": -0.12899, "woe:repo": "woeplanet-poi-gb"}, "geometry": {"coordinates": [-0.12899, 51.51297], "type": "Point"}}