{"type": "Feature", "id": 22490001, "geometry": {"type": "Point", "coordinates": [-1.723, 52.181]}, "properties": {"woe:id": 22490001, "woe:parent_id": 28949, "woe:name": "Stratford-on-Avon Racecourse", "woe:placetype": 20, "woe:placetype_name": "POI", "woe:lang": "ENG", "iso:country": "GB", "meta:provider": ["geoplanet:7.3.2", "geoplanet:7.4.0", "geoplanet:7.4.1", "geoplanet:7.5.1", "geoplanet:7.5.2", "geoplanet:7.6.0", "geoplanet:7.8.1", "geoplanet:7.9.0", "geoplanet:7.10.0", "geoplanet:8.0.0", "woeplanet:8.0.0"], "meta:indexed": "2020-08-20T21:24:45.806557", "meta:updated": "2020-10-14T11:22:07.600834", "woe:hierarchy": {"continent": 24865675, "country": 23424975, "town": 0, "planet": 1, "county": 12602190, "suburb": 0, "state": 24554868, "region": 0, "localadmin": 12696101}, "woe:timezone_id": 28350903, "woe:hash": "gcqbbg3275qj", "woe:centroid": [-1.723, 52.181], "geom:latitude": 52.181, "geom:longitude": -1.723, "geom:hash": "gcqbbg3275qj", "woe:latitude": 52.181, "geom:centroid": [-1.723, 52.181], "woe:longitude": -1.723, "woe:repo": "woeplanet-poi-gb", "geom:area": 0.0, "woe:scale": 19}}