{"type": "Feature", "id": 22471164, "geometry": {"type": "Point", "coordinates": [-3.16834, 56.0998]}, "properties": {"woe:id": 22471164, "woe:parent_id": 25380, "woe:name": "Stark's Park", "woe:placetype": 20, "woe:placetype_name": "POI", "woe:lang": "ENG", "iso:country": "GB", "meta:provider": ["geoplanet:7.3.1", "geoplanet:7.3.2", "geoplanet:7.4.0", "geoplanet:7.4.1", "geoplanet:7.5.1", "geoplanet:7.5.2", "geoplanet:7.6.0", "geoplanet:7.8.1", "geoplanet:7.9.0", "geoplanet:7.10.0", "geoplanet:8.0.0", "woeplanet:8.0.0"], "meta:indexed": "2020-08-20T19:45:32.220491", "woe:alias_ENG_V": ["Raith Rovers Football Club", "Starks Park"], "meta:updated": "2020-10-14T11:22:08.558509", "woe:hierarchy": {"continent": 24865675, "country": 23424975, "town": 0, "planet": 1, "county": 12602201, "suburb": 0, "state": 12578048, "region": 0, "localadmin": 12696197}, "woe:timezone_id": 28350903, "woe:hash": "gcvxpusvh2dq", "woe:centroid": [-3.16834, 56.0998], "geom:latitude": 56.0998, "geom:longitude": -3.16834, "geom:hash": "gcvxpusvh2dq", "woe:latitude": 56.0998, "geom:centroid": [-3.16834, 56.0998], "woe:longitude": -3.16834, "woe:repo": "woeplanet-poi-gb", "geom:area": 0.0, "woe:scale": 19}}