{"type": "Feature", "id": 22466155, "properties": {"woe:id": 22466155, "woe:parent_id": 28994, "woe:name": "Stepps Railway Station", "woe:placetype": 20, "woe:placetype_name": "POI", "woe:lang": "ENG", "iso:country": "GB", "meta:provider": ["geoplanet:7.3.1", "geoplanet:7.3.2", "geoplanet:7.4.0", "geoplanet:7.4.1", "geoplanet:7.5.1", "geoplanet:7.5.2", "geoplanet:7.6.0", "geoplanet:7.8.1", "geoplanet:7.9.0", "geoplanet:7.10.0", "geoplanet:8.0.0", "woeplanet:8.0.0"], "meta:indexed": "2020-08-20T19:45:31.935008", "woe:alias_ENG_V": ["Stepps Station"], "meta:updated": "2020-08-22T02:03:28.871894", "woe:hierarchy": {"continent": 24865675, "country": 23424975, "town": 0, "planet": 1, "county": 12602207, "suburb": 0, "state": 12578048, "region": 0, "localadmin": 12696204}, "woe:timezone_id": 28350903, "woe:hash": "gcvjcy8bj6pg", "woe:centroid": [-4.14058, 55.890209], "geom:latitude": 55.890209, "geom:longitude": -4.14058, "geom:hash": "gcvjcy8bj6pg", "woe:latitude": 55.890209, "geom:centroid": [-4.14058, 55.890209], "woe:longitude": -4.14058, "woe:repo": "woeplanet-poi-gb"}, "geometry": {"coordinates": [-4.14058, 55.890209], "type": "Point"}}