{"type": "Feature", "id": 22463878, "properties": {"woe:id": 22463878, "woe:parent_id": 43670, "woe:name": "Slateford Railway Station", "woe:placetype": 20, "woe:placetype_name": "POI", "woe:lang": "ENG", "iso:country": "GB", "meta:provider": ["geoplanet:7.3.1", "geoplanet:7.3.2", "geoplanet:7.4.0", "geoplanet:7.4.1", "geoplanet:7.5.1", "geoplanet:7.5.2", "geoplanet:7.6.0", "geoplanet:7.8.1", "geoplanet:7.9.0", "geoplanet:7.10.0", "geoplanet:8.0.0", "woeplanet:8.0.0"], "meta:indexed": "2020-08-20T19:45:31.735498", "woe:alias_ENG_V": ["Slateford Station"], "meta:updated": "2020-08-22T02:03:28.781943", "woe:hierarchy": {"continent": 24865675, "country": 23424975, "town": 0, "planet": 1, "county": 12602204, "suburb": 0, "state": 12578048, "region": 0, "localadmin": 12696195}, "woe:timezone_id": 28350903, "woe:hash": "gcvwnjnqw3c6", "woe:centroid": [-3.2431, 55.927029], "geom:latitude": 55.927029, "geom:longitude": -3.2431, "geom:hash": "gcvwnjnqw3c6", "woe:latitude": 55.927029, "geom:centroid": [-3.2431, 55.927029], "woe:longitude": -3.2431, "woe:repo": "woeplanet-poi-gb"}, "geometry": {"coordinates": [-3.2431, 55.927029], "type": "Point"}}