{"type": "Feature", "id": 56072235, "geometry": {"type": "Point", "coordinates": [-3.22423, 52.55542]}, "properties": {"woe:id": 56072235, "woe:parent_id": 10278, "woe:name": "Green Lane", "woe:placetype": 20, "woe:placetype_name": "POI", "woe:lang": "ENG", "iso:country": "GB", "meta:provider": ["geoplanet:7.4.0", "geoplanet:7.4.1", "geoplanet:7.5.1", "geoplanet:7.5.2", "geoplanet:7.6.0", "geoplanet:7.8.1", "geoplanet:7.9.0", "geoplanet:7.10.0", "geoplanet:8.0.0", "woeplanet:8.0.0"], "meta:indexed": "2020-08-20T23:16:09.511233", "meta:updated": "2020-10-14T11:22:10.191180", "woe:hierarchy": {"continent": 24865675, "country": 23424975, "town": 0, "planet": 1, "county": 12602227, "suburb": 0, "state": 12578049, "region": 0, "localadmin": 0}, "woe:timezone_id": 28350903, "woe:hash": "gcmdyxkjtbrg", "woe:centroid": [-3.22423, 52.55542], "geom:latitude": 52.55542, "geom:longitude": -3.22423, "geom:hash": "gcmdyxkjtbrg", "woe:latitude": 52.55542, "geom:centroid": [-3.22423, 52.55542], "woe:longitude": -3.22423, "woe:repo": "woeplanet-poi-gb", "geom:area": 0.0, "woe:scale": 19}}