{"type": "Feature", "id": 28350048, "properties": {"woe:id": 28350048, "woe:parent_id": 11663, "woe:name": "Balham Underground Station", "woe:placetype": 20, "woe:placetype_name": "POI", "woe:lang": "ENG", "iso:country": "GB", "meta:provider": ["geoplanet:7.3.1", "geoplanet:7.3.2", "geoplanet:7.4.0", "geoplanet:7.4.1", "geoplanet:7.5.1", "geoplanet:7.5.2", "geoplanet:7.6.0", "geoplanet:7.8.1", "geoplanet:7.9.0", "geoplanet:7.10.0", "geoplanet:8.0.0", "woeplanet:8.0.0"], "meta:indexed": "2020-08-20T19:45:34.083041", "woe:alias_ENG_V": ["Balham Tube", "Balham Underground", "Balham Tube Station"], "meta:updated": "2020-08-22T02:03:29.856785", "woe:hierarchy": {"continent": 24865675, "country": 23424975, "town": 0, "planet": 1, "county": 23416974, "suburb": 0, "state": 24554868, "region": 0, "localadmin": 12695818}, "woe:timezone_id": 28350903, "woe:hash": "gcpusscjf8vu", "woe:centroid": [-0.15232, 51.4431], "geom:latitude": 51.4431, "geom:longitude": -0.15232, "geom:hash": "gcpusscjf8vu", "woe:latitude": 51.4431, "geom:centroid": [-0.15232, 51.4431], "woe:longitude": -0.15232, "woe:repo": "woeplanet-poi-gb"}, "geometry": {"coordinates": [-0.15232, 51.4431], "type": "Point"}}