{"type": "Feature", "id": 56069001, "geometry": {"type": "Point", "coordinates": [-0.2049, 51.595291]}, "properties": {"woe:id": 56069001, "woe:parent_id": 43333, "woe:name": "Kensit Memorial College", "woe:placetype": 20, "woe:placetype_name": "POI", "woe:lang": "ENG", "iso:country": "GB", "meta:provider": ["geoplanet:7.3.1", "geoplanet:7.3.2", "geoplanet:7.4.0", "geoplanet:7.4.1", "geoplanet:7.5.1", "geoplanet:7.5.2", "geoplanet:7.6.0", "geoplanet:7.8.1", "geoplanet:7.9.0", "geoplanet:7.10.0", "geoplanet:8.0.0", "woeplanet:8.0.0"], "meta:indexed": "2020-08-20T19:45:34.476668", "meta:updated": "2020-10-14T11:22:10.248722", "woe:hierarchy": {"continent": 24865675, "country": 23424975, "town": 0, "planet": 1, "county": 23416974, "suburb": 0, "state": 24554868, "region": 0, "localadmin": 12695821}, "woe:timezone_id": 28350903, "woe:hash": "gcpve2du37r7", "woe:centroid": [-0.2049, 51.595291], "geom:latitude": 51.595291, "geom:longitude": -0.2049, "geom:hash": "gcpve2du37r7", "woe:latitude": 51.595291, "geom:centroid": [-0.2049, 51.595291], "woe:longitude": -0.2049, "woe:repo": "woeplanet-poi-gb", "geom:area": 0.0, "woe:scale": 19}}