{"type": "Feature", "id": 56069021, "properties": {"woe:id": 56069021, "woe:parent_id": 18483, "woe:name": "Strathmore College", "woe:placetype": 20, "woe:placetype_name": "POI", "woe:lang": "ENG", "iso:country": "GB", "meta:provider": ["geoplanet:7.3.1", "geoplanet:7.3.2", "geoplanet:7.4.0", "geoplanet:7.4.1", "geoplanet:7.5.1", "geoplanet:7.5.2", "geoplanet:7.6.0", "geoplanet:7.8.1", "geoplanet:7.9.0", "geoplanet:7.10.0", "geoplanet:8.0.0", "woeplanet:8.0.0"], "meta:indexed": "2020-08-20T19:45:34.492803", "meta:updated": "2020-08-22T02:03:57.894079", "woe:hierarchy": {"continent": 24865675, "country": 23424975, "town": 0, "planet": 1, "county": 12602189, "suburb": 0, "state": 24554868, "region": 0, "localadmin": 12696161}, "woe:timezone_id": 28350903, "woe:hash": "gcqmrke2532f", "woe:centroid": [-2.13773, 52.978828], "geom:latitude": 52.978828, "geom:longitude": -2.13773, "geom:hash": "gcqmrke2532f", "woe:latitude": 52.978828, "geom:centroid": [-2.13773, 52.978828], "woe:longitude": -2.13773, "woe:repo": "woeplanet-poi-gb"}, "geometry": {"coordinates": [-2.13773, 52.978828], "type": "Point"}}