{"type": "Feature", "id": 22458928, "geometry": {"type": "Point", "coordinates": [-2.72002, 56.498009]}, "properties": {"woe:id": 22458928, "woe:parent_id": 15251, "woe:name": "Golf Street Railway Station", "woe:placetype": 20, "woe:placetype_name": "POI", "woe:lang": "ENG", "iso:country": "GB", "meta:provider": ["geoplanet:7.3.1", "geoplanet:7.3.2", "geoplanet:7.4.0", "geoplanet:7.4.1", "geoplanet:7.5.1", "geoplanet:7.5.2", "geoplanet:7.6.0", "geoplanet:7.8.1", "geoplanet:7.9.0", "geoplanet:7.10.0", "geoplanet:8.0.0", "woeplanet:8.0.0"], "meta:indexed": "2020-08-20T19:45:31.461539", "woe:alias_ENG_V": ["Golf St Railway Station", "Golf St Station", "Golf Street Station"], "meta:updated": "2020-10-14T11:22:08.652311", "woe:hierarchy": {"continent": 24865675, "country": 23424975, "town": 0, "planet": 1, "county": 12602208, "suburb": 0, "state": 12578048, "region": 0, "localadmin": 12696184}, "woe:timezone_id": 28350903, "woe:hash": "gfn16j5kfbnp", "woe:centroid": [-2.72002, 56.498009], "geom:latitude": 56.498009, "geom:longitude": -2.72002, "geom:hash": "gfn16j5kfbnp", "woe:latitude": 56.498009, "geom:centroid": [-2.72002, 56.498009], "woe:longitude": -2.72002, "woe:repo": "woeplanet-poi-gb", "geom:area": 0.0, "woe:scale": 19}}