{"type": "Feature", "id": 22474050, "properties": {"woe:id": 22474050, "woe:parent_id": 39699, "woe:name": "Barons Court Underground Station", "woe:placetype": 20, "woe:placetype_name": "POI", "woe:lang": "ENG", "iso:country": "GB", "meta:provider": ["geoplanet:7.3.1", "geoplanet:7.3.2", "geoplanet:7.4.0", "geoplanet:7.4.1", "geoplanet:7.5.1", "geoplanet:7.5.2", "geoplanet:7.6.0", "geoplanet:7.8.1", "geoplanet:7.9.0", "geoplanet:7.10.0", "geoplanet:8.0.0", "woeplanet:8.0.0"], "meta:indexed": "2020-08-20T19:45:32.393734", "woe:alias_ENG_V": ["Barons Court Tube", "Barons Court Underground", "Barons Court Station", "Barons Court Tube Station"], "meta:updated": "2020-08-22T02:03:29.099039", "woe:hierarchy": {"continent": 24865675, "country": 23424975, "town": 0, "planet": 1, "county": 23416974, "suburb": 0, "state": 24554868, "region": 0, "localadmin": 12695809}, "woe:timezone_id": 28350903, "woe:hash": "gcpugjs8m098", "woe:centroid": [-0.21333, 51.490219], "geom:latitude": 51.490219, "geom:longitude": -0.21333, "geom:hash": "gcpugjs8m098", "woe:latitude": 51.490219, "geom:centroid": [-0.21333, 51.490219], "woe:longitude": -0.21333, "woe:repo": "woeplanet-poi-gb"}, "geometry": {"coordinates": [-0.21333, 51.490219], "type": "Point"}}