{"type": "Feature", "id": 22472879, "geometry": {"type": "Point", "coordinates": [-0.19269, 53.101349]}, "properties": {"woe:id": 22472879, "woe:parent_id": 37018, "woe:name": "Tattershall Castle", "woe:placetype": 20, "woe:placetype_name": "POI", "woe:lang": "ENG", "iso:country": "GB", "meta:provider": ["geoplanet:7.3.1", "geoplanet:7.3.2", "geoplanet:7.4.0", "geoplanet:7.4.1", "geoplanet:7.5.1", "geoplanet:7.5.2", "geoplanet:7.6.0", "geoplanet:7.8.1", "geoplanet:7.9.0", "geoplanet:7.10.0", "geoplanet:8.0.0", "woeplanet:8.0.0"], "meta:indexed": "2020-08-20T19:45:32.299154", "meta:updated": "2020-10-14T11:22:10.037742", "woe:hierarchy": {"continent": 24865675, "country": 23424975, "town": 0, "planet": 1, "county": 12602145, "suburb": 0, "state": 24554868, "region": 0, "localadmin": 12696017}, "woe:timezone_id": 28350903, "woe:hash": "gcry5dg9vbzv", "woe:centroid": [-0.19269, 53.101349], "geom:latitude": 53.101349, "geom:longitude": -0.19269, "geom:hash": "gcry5dg9vbzv", "woe:latitude": 53.101349, "geom:centroid": [-0.19269, 53.101349], "woe:longitude": -0.19269, "woe:repo": "woeplanet-poi-gb", "geom:area": 0.0, "woe:scale": 19}}