{"type": "Feature", "id": 56069147, "geometry": {"type": "Point", "coordinates": [-4.23003, 55.879959]}, "properties": {"woe:id": 56069147, "woe:parent_id": 35527, "woe:name": "North Glasgow College", "woe:placetype": 20, "woe:placetype_name": "POI", "woe:lang": "ENG", "iso:country": "GB", "meta:provider": ["geoplanet:7.3.1", "geoplanet:7.3.2", "geoplanet:7.4.0", "geoplanet:7.4.1", "geoplanet:7.5.1", "geoplanet:7.5.2", "geoplanet:7.6.0", "geoplanet:7.8.1", "geoplanet:7.9.0", "geoplanet:7.10.0", "geoplanet:8.0.0", "woeplanet:8.0.0"], "meta:indexed": "2020-08-20T19:45:34.589361", "meta:updated": "2020-10-14T11:22:10.300755", "woe:hierarchy": {"continent": 24865675, "country": 23424975, "town": 0, "planet": 1, "county": 12602207, "suburb": 0, "state": 12578048, "region": 0, "localadmin": 12696198}, "woe:timezone_id": 28350903, "woe:hash": "gcuvzsxu35m5", "woe:centroid": [-4.23003, 55.879959], "geom:latitude": 55.879959, "geom:longitude": -4.23003, "geom:hash": "gcuvzsxu35m5", "woe:latitude": 55.879959, "geom:centroid": [-4.23003, 55.879959], "woe:longitude": -4.23003, "woe:repo": "woeplanet-poi-gb", "geom:area": 0.0, "woe:scale": 19}}