{"type": "Feature", "id": 22488502, "properties": {"woe:id": 22488502, "woe:parent_id": 22913, "woe:name": "Hedge End Railway Station", "woe:placetype": 20, "woe:placetype_name": "POI", "woe:lang": "ENG", "iso:country": "GB", "meta:provider": ["geoplanet:7.3.1", "geoplanet:7.3.2", "geoplanet:7.4.0", "geoplanet:7.4.1", "geoplanet:7.5.1", "geoplanet:7.5.2", "geoplanet:7.6.0", "geoplanet:7.8.1", "geoplanet:7.9.0", "geoplanet:7.10.0", "geoplanet:8.0.0", "woeplanet:8.0.0"], "meta:indexed": "2020-08-20T19:45:33.433788", "woe:alias_ENG_V": ["Hedge End Station"], "meta:updated": "2020-08-22T02:03:29.589904", "woe:hierarchy": {"continent": 24865675, "country": 23424975, "town": 0, "planet": 1, "county": 12602169, "suburb": 0, "state": 24554868, "region": 0, "localadmin": 12695960}, "woe:timezone_id": 28350903, "woe:hash": "gcp1dxbz956c", "woe:centroid": [-1.29531, 50.932549], "geom:latitude": 50.932549, "geom:longitude": -1.29531, "geom:hash": "gcp1dxbz956c", "woe:latitude": 50.932549, "geom:centroid": [-1.29531, 50.932549], "woe:longitude": -1.29531, "woe:repo": "woeplanet-poi-gb"}, "geometry": {"coordinates": [-1.29531, 50.932549], "type": "Point"}}