{"type": "Feature", "id": 22492946, "geometry": {"type": "Point", "coordinates": [-0.024, 51.702999]}, "properties": {"woe:id": 22492946, "woe:parent_id": 15824, "woe:name": "Cheshunt Railway Station", "woe:placetype": 20, "woe:placetype_name": "POI", "woe:lang": "ENG", "iso:country": "GB", "meta:provider": ["geoplanet:7.4.0", "geoplanet:7.4.1", "geoplanet:7.5.1", "geoplanet:7.5.2", "geoplanet:7.6.0", "geoplanet:7.8.1", "geoplanet:7.9.0", "geoplanet:7.10.0", "geoplanet:8.0.0", "woeplanet:8.0.0"], "meta:indexed": "2020-08-20T23:16:08.093883", "meta:updated": "2020-10-14T11:22:08.186737", "woe:alias_ENG_V": ["Cheshunt Station"], "woe:hierarchy": {"continent": 24865675, "country": 23424975, "town": 0, "planet": 1, "county": 12602170, "suburb": 0, "state": 24554868, "region": 0, "localadmin": 12695975}, "woe:timezone_id": 28350903, "woe:hash": "gcpypknxbc86", "woe:centroid": [-0.024, 51.702999], "geom:latitude": 51.702999, "geom:longitude": -0.024, "geom:hash": "gcpypknxbc86", "woe:latitude": 51.702999, "geom:centroid": [-0.024, 51.702999], "woe:longitude": -0.024, "woe:repo": "woeplanet-poi-gb", "geom:area": 0.0, "woe:scale": 19}}