{"type": "Feature", "id": 22485442, "properties": {"woe:id": 22485442, "woe:parent_id": 20089936, "woe:name": "Rogart Railway Station", "woe:placetype": 20, "woe:placetype_name": "POI", "woe:lang": "ENG", "iso:country": "GB", "meta:provider": ["geoplanet:7.3.1", "geoplanet:7.3.2", "geoplanet:7.4.0", "geoplanet:7.4.1", "geoplanet:7.5.1", "geoplanet:7.5.2", "geoplanet:7.6.0", "geoplanet:7.8.1", "geoplanet:7.9.0", "geoplanet:7.10.0", "geoplanet:8.0.0", "woeplanet:8.0.0"], "meta:indexed": "2020-08-20T19:45:33.253956", "woe:alias_ENG_V": ["Rogart Station"], "meta:updated": "2020-08-22T02:03:29.505133", "woe:hierarchy": {"continent": 24865675, "country": 23424975, "town": 0, "planet": 1, "county": 12602203, "suburb": 0, "state": 12578048, "region": 0, "localadmin": 12696199}, "woe:timezone_id": 28350903, "woe:hash": "gfm1ck7xpkbs", "woe:centroid": [-4.1587, 57.988441], "geom:latitude": 57.988441, "geom:longitude": -4.1587, "geom:hash": "gfm1ck7xpkbs", "woe:latitude": 57.988441, "geom:centroid": [-4.1587, 57.988441], "woe:longitude": -4.1587, "woe:repo": "woeplanet-poi-gb"}, "geometry": {"coordinates": [-4.1587, 57.988441], "type": "Point"}}