{"type": "Feature", "id": 22483094, "properties": {"woe:id": 22483094, "woe:parent_id": 29980, "woe:name": "Murrayshall Golf Club", "woe:placetype": 20, "woe:placetype_name": "POI", "woe:lang": "ENG", "iso:country": "GB", "meta:provider": ["geoplanet:7.3.1", "geoplanet:7.3.2", "geoplanet:7.4.0", "geoplanet:7.4.1", "geoplanet:7.5.1", "geoplanet:7.5.2", "geoplanet:7.6.0", "geoplanet:7.8.1", "geoplanet:7.9.0", "geoplanet:7.10.0", "geoplanet:8.0.0", "woeplanet:8.0.0"], "meta:indexed": "2020-08-20T19:45:33.116132", "meta:updated": "2020-08-22T02:03:29.440602", "woe:alias_ENG_V": ["Murrayshall Golf Course"], "woe:hierarchy": {"continent": 24865675, "country": 23424975, "town": 0, "planet": 1, "county": 12602208, "suburb": 0, "state": 12578048, "region": 0, "localadmin": 12696206}, "woe:timezone_id": 28350903, "woe:hash": "gfj8gr7brhcc", "woe:centroid": [-3.36735, 56.42173], "geom:latitude": 56.42173, "geom:longitude": -3.36735, "geom:hash": "gfj8gr7brhcc", "woe:latitude": 56.42173, "geom:centroid": [-3.36735, 56.42173], "woe:longitude": -3.36735, "woe:repo": "woeplanet-poi-gb"}, "geometry": {"coordinates": [-3.36735, 56.42173], "type": "Point"}}