{"type": "Feature", "id": 28350007, "properties": {"woe:id": 28350007, "woe:parent_id": 10411, "woe:name": "Lloyd Park Tram Stop", "woe:placetype": 20, "woe:placetype_name": "POI", "woe:lang": "ENG", "iso:country": "GB", "meta:provider": ["geoplanet:7.3.1", "geoplanet:7.3.2", "geoplanet:7.4.0", "geoplanet:7.4.1", "geoplanet:7.5.1", "geoplanet:7.5.2", "geoplanet:7.6.0", "geoplanet:7.8.1", "geoplanet:7.9.0", "geoplanet:7.10.0", "geoplanet:8.0.0", "woeplanet:8.0.0"], "meta:indexed": "2020-08-20T19:45:34.057234", "meta:updated": "2020-08-22T02:03:29.843070", "woe:hierarchy": {"continent": 24865675, "country": 23424975, "town": 0, "planet": 1, "county": 23416974, "suburb": 0, "state": 24554868, "region": 0, "localadmin": 12695825}, "woe:timezone_id": 28350903, "woe:hash": "gcpunnt49r82", "woe:centroid": [-0.08097, 51.3643], "geom:latitude": 51.3643, "geom:longitude": -0.08097, "geom:hash": "gcpunnt49r82", "woe:latitude": 51.3643, "geom:centroid": [-0.08097, 51.3643], "woe:longitude": -0.08097, "woe:repo": "woeplanet-poi-gb"}, "geometry": {"coordinates": [-0.08097, 51.3643], "type": "Point"}}