{"type": "Feature", "id": 22459929, "geometry": {"type": "Point", "coordinates": [-1.5628, 51.866829]}, "properties": {"woe:id": 22459929, "woe:parent_id": 11091, "woe:name": "Ascott-under-Wychwood Railway Station", "woe:placetype": 20, "woe:placetype_name": "POI", "woe:lang": "ENG", "iso:country": "GB", "meta:provider": ["geoplanet:7.3.1", "geoplanet:7.3.2", "geoplanet:7.4.0", "geoplanet:7.4.1", "geoplanet:7.5.1", "geoplanet:7.5.2", "geoplanet:7.6.0", "geoplanet:7.8.1", "geoplanet:7.9.0", "geoplanet:7.10.0", "geoplanet:8.0.0", "woeplanet:8.0.0"], "meta:indexed": "2020-08-20T19:45:31.516629", "woe:alias_ENG_V": ["Ascott-under-Wychwood Station"], "meta:updated": "2020-10-14T11:22:08.228920", "woe:hierarchy": {"continent": 24865675, "country": 23424975, "town": 0, "planet": 1, "county": 12602175, "suburb": 0, "state": 24554868, "region": 0, "localadmin": 12696061}, "woe:timezone_id": 28350903, "woe:hash": "gcnzh6n40jey", "woe:centroid": [-1.5628, 51.866829], "geom:latitude": 51.866829, "geom:longitude": -1.5628, "geom:hash": "gcnzh6n40jey", "woe:latitude": 51.866829, "geom:centroid": [-1.5628, 51.866829], "woe:longitude": -1.5628, "woe:repo": "woeplanet-poi-gb", "geom:area": 0.0, "woe:scale": 19}}