{"type": "Feature", "id": 22475547, "geometry": {"type": "Point", "coordinates": [-0.09625, 51.517559]}, "properties": {"woe:id": 22475547, "woe:parent_id": 20094307, "woe:name": "Museum of London", "woe:placetype": 20, "woe:placetype_name": "POI", "woe:lang": "ENG", "iso:country": "GB", "meta:provider": ["geoplanet:7.3.1", "geoplanet:7.3.2", "geoplanet:7.4.0", "geoplanet:7.4.1", "geoplanet:7.5.1", "geoplanet:7.5.2", "geoplanet:7.6.0", "geoplanet:7.8.1", "geoplanet:7.9.0", "geoplanet:7.10.0", "geoplanet:8.0.0", "woeplanet:8.0.0"], "meta:indexed": "2020-08-20T19:45:32.591365", "woe:alias_ENG_V": ["Museumoflondon"], "meta:updated": "2020-10-14T11:22:08.482854", "woe:hierarchy": {"continent": 24865675, "country": 23424975, "town": 0, "planet": 1, "county": 23416974, "suburb": 0, "state": 24554868, "region": 0, "localadmin": 12695806}, "woe:timezone_id": 28350903, "woe:hash": "gcpvjf3zt1nc", "woe:centroid": [-0.09625, 51.517559], "geom:latitude": 51.517559, "geom:longitude": -0.09625, "geom:hash": "gcpvjf3zt1nc", "woe:latitude": 51.517559, "geom:centroid": [-0.09625, 51.517559], "woe:longitude": -0.09625, "woe:repo": "woeplanet-poi-gb", "geom:area": 0.0, "woe:scale": 19}}