{"type": "Feature", "id": 23702206, "properties": {"woe:id": 23702206, "woe:parent_id": 44080, "woe:name": "St Stephen's House", "woe:placetype": 20, "woe:placetype_name": "POI", "woe:lang": "ENG", "iso:country": "GB", "meta:provider": ["geoplanet:7.3.1", "geoplanet:7.3.2", "geoplanet:7.4.0", "geoplanet:7.4.1", "geoplanet:7.5.1", "geoplanet:7.5.2", "geoplanet:7.6.0", "geoplanet:7.8.1", "geoplanet:7.9.0", "geoplanet:7.10.0", "geoplanet:8.0.0", "woeplanet:8.0.0"], "meta:indexed": "2020-08-20T19:45:34.207416", "woe:alias_ENG_V": ["St Stephens House"], "meta:updated": "2020-08-22T02:03:29.902170", "woe:hierarchy": {"continent": 24865675, "country": 23424975, "town": 0, "planet": 1, "county": 12602175, "suburb": 0, "state": 24554868, "region": 0, "localadmin": 12696058}, "woe:timezone_id": 28350903, "woe:hash": "gcpn7u38h241", "woe:centroid": [-1.23921, 51.746979], "geom:latitude": 51.746979, "geom:longitude": -1.23921, "geom:hash": "gcpn7u38h241", "woe:latitude": 51.746979, "geom:centroid": [-1.23921, 51.746979], "woe:longitude": -1.23921, "woe:repo": "woeplanet-poi-gb"}, "geometry": {"coordinates": [-1.23921, 51.746979], "type": "Point"}}