{"type": "Feature", "id": 22477639, "geometry": {"type": "Point", "coordinates": [-5.82255, 56.969318]}, "properties": {"woe:id": 22477639, "woe:parent_id": 29299, "woe:name": "Morar Railway Station", "woe:placetype": 20, "woe:placetype_name": "POI", "woe:lang": "ENG", "iso:country": "GB", "meta:provider": ["geoplanet:7.3.1", "geoplanet:7.3.2", "geoplanet:7.4.0", "geoplanet:7.4.1", "geoplanet:7.5.1", "geoplanet:7.5.2", "geoplanet:7.6.0", "geoplanet:7.8.1", "geoplanet:7.9.0", "geoplanet:7.10.0", "geoplanet:8.0.0", "woeplanet:8.0.0"], "meta:indexed": "2020-08-20T19:45:32.817822", "woe:alias_ENG_V": ["Morar Station"], "meta:updated": "2020-10-14T11:22:09.272091", "woe:hierarchy": {"continent": 24865675, "country": 23424975, "town": 0, "planet": 1, "county": 12602203, "suburb": 0, "state": 12578048, "region": 0, "localadmin": 12696199}, "woe:timezone_id": 28350903, "woe:hash": "gf5u5dbnkf85", "woe:centroid": [-5.82255, 56.969318], "geom:latitude": 56.969318, "geom:longitude": -5.82255, "geom:hash": "gf5u5dbnkf85", "woe:latitude": 56.969318, "geom:centroid": [-5.82255, 56.969318], "woe:longitude": -5.82255, "woe:repo": "woeplanet-poi-gb", "geom:area": 0.0, "woe:scale": 19}}