{"type": "Feature", "id": 22458923, "geometry": {"type": "Point", "coordinates": [-2.70553, 56.50098]}, "properties": {"woe:id": 22458923, "woe:parent_id": 39936, "woe:name": "Carnoustie Railway Station", "woe:placetype": 20, "woe:placetype_name": "POI", "woe:lang": "ENG", "iso:country": "GB", "meta:provider": ["geoplanet:7.3.1", "geoplanet:7.3.2", "geoplanet:7.4.0", "geoplanet:7.4.1", "geoplanet:7.5.1", "geoplanet:7.5.2", "geoplanet:7.6.0", "geoplanet:7.8.1", "geoplanet:7.9.0", "geoplanet:7.10.0", "geoplanet:8.0.0", "woeplanet:8.0.0"], "meta:indexed": "2020-08-20T19:45:31.460429", "woe:alias_ENG_V": ["Carnoustie Station"], "meta:updated": "2020-10-14T11:22:08.649574", "woe:hierarchy": {"continent": 24865675, "country": 23424975, "town": 0, "planet": 1, "county": 12602208, "suburb": 0, "state": 12578048, "region": 0, "localadmin": 12696184}, "woe:timezone_id": 28350903, "woe:hash": "gfn16mtyhd4d", "woe:centroid": [-2.70553, 56.50098], "geom:latitude": 56.50098, "geom:longitude": -2.70553, "geom:hash": "gfn16mtyhd4d", "woe:latitude": 56.50098, "geom:centroid": [-2.70553, 56.50098], "woe:longitude": -2.70553, "woe:repo": "woeplanet-poi-gb", "geom:area": 0.0, "woe:scale": 19}}