{"type": "Feature", "id": 22468133, "properties": {"woe:id": 22468133, "woe:parent_id": 38568, "woe:name": "Lelant Saltings Railway Station", "woe:placetype": 20, "woe:placetype_name": "POI", "woe:lang": "ENG", "iso:country": "GB", "meta:provider": ["geoplanet:7.3.1", "geoplanet:7.3.2", "geoplanet:7.4.0", "geoplanet:7.4.1", "geoplanet:7.5.1", "geoplanet:7.5.2", "geoplanet:7.6.0", "geoplanet:7.8.1", "geoplanet:7.9.0", "geoplanet:7.10.0", "geoplanet:8.0.0", "woeplanet:8.0.0"], "meta:indexed": "2020-08-20T19:45:32.059691", "woe:alias_ENG_V": ["Lelant Saltings Station"], "meta:updated": "2020-08-22T02:03:28.934859", "woe:hierarchy": {"continent": 24865675, "country": 23424975, "town": 0, "planet": 1, "county": 12602181, "suburb": 0, "state": 24554868, "region": 0, "localadmin": 12695897}, "woe:timezone_id": 28350903, "woe:hash": "gbujkntjcymr", "woe:centroid": [-5.44227, 50.178329], "geom:latitude": 50.178329, "geom:longitude": -5.44227, "geom:hash": "gbujkntjcymr", "woe:latitude": 50.178329, "geom:centroid": [-5.44227, 50.178329], "woe:longitude": -5.44227, "woe:repo": "woeplanet-poi-gb"}, "geometry": {"coordinates": [-5.44227, 50.178329], "type": "Point"}}