{"type": "Feature", "id": 22490760, "geometry": {"type": "Point", "coordinates": [-3.9788, 51.60788]}, "properties": {"woe:id": 22490760, "woe:parent_id": 14349, "woe:name": "University of Wales-Swansea", "woe:placetype": 20, "woe:placetype_name": "POI", "woe:lang": "ENG", "iso:country": "GB", "meta:provider": ["geoplanet:7.3.1", "geoplanet:7.3.2", "geoplanet:7.4.0", "geoplanet:7.4.1", "geoplanet:7.5.1", "geoplanet:7.5.2", "geoplanet:7.6.0", "geoplanet:7.8.1", "geoplanet:7.9.0", "geoplanet:7.10.0", "geoplanet:8.0.0", "woeplanet:8.0.0"], "meta:indexed": "2020-08-20T19:45:34.258893", "woe:alias_ENG_V": ["University of Wales Swansea", "UWS", "Swansea University"], "meta:updated": "2020-10-14T11:22:07.831459", "woe:hierarchy": {"continent": 24865675, "country": 23424975, "town": 0, "planet": 1, "county": 12602229, "suburb": 0, "state": 12578049, "region": 0, "localadmin": 12696131}, "woe:timezone_id": 28350903, "woe:hash": "gcjjt6ytxnpe", "woe:centroid": [-3.9788, 51.60788], "geom:latitude": 51.60788, "geom:longitude": -3.9788, "geom:hash": "gcjjt6ytxnpe", "woe:latitude": 51.60788, "geom:centroid": [-3.9788, 51.60788], "woe:longitude": -3.9788, "woe:repo": "woeplanet-poi-gb", "geom:area": 0.0, "woe:scale": 19}}