{"type": "Feature", "id": 22476499, "geometry": {"type": "Point", "coordinates": [-0.07596, 51.509739]}, "properties": {"woe:id": 22476499, "woe:parent_id": 20094363, "woe:name": "Tower Hill Underground Station", "woe:placetype": 20, "woe:placetype_name": "POI", "woe:lang": "ENG", "iso:country": "GB", "meta:provider": ["geoplanet:7.3.1", "geoplanet:7.3.2", "geoplanet:7.4.0", "geoplanet:7.4.1", "geoplanet:7.5.1", "geoplanet:7.5.2", "geoplanet:7.6.0", "geoplanet:7.8.1", "geoplanet:7.9.0", "geoplanet:7.10.0", "geoplanet:8.0.0", "woeplanet:8.0.0"], "meta:indexed": "2020-08-20T19:45:32.715366", "woe:alias_ENG_V": ["Tower Hill Tube", "Tower Hill Underground", "Tower Hill Station", "Tower Hill Tube Station"], "meta:updated": "2020-10-14T11:22:08.594144", "woe:hierarchy": {"continent": 24865675, "country": 23424975, "town": 0, "planet": 1, "county": 23416974, "suburb": 0, "state": 24554868, "region": 0, "localadmin": 12695817}, "woe:timezone_id": 28350903, "woe:hash": "gcpvn309yp21", "woe:centroid": [-0.07596, 51.509739], "geom:latitude": 51.509739, "geom:longitude": -0.07596, "geom:hash": "gcpvn309yp21", "woe:latitude": 51.509739, "geom:centroid": [-0.07596, 51.509739], "woe:longitude": -0.07596, "woe:repo": "woeplanet-poi-gb", "geom:area": 0.0, "woe:scale": 19}}