{"type": "Feature", "id": 22464068, "geometry": {"type": "Point", "coordinates": [0.31664, 52.4622]}, "properties": {"woe:id": 22464068, "woe:parent_id": 26706, "woe:name": "Littleport Railway Station", "woe:placetype": 20, "woe:placetype_name": "POI", "woe:lang": "ENG", "iso:country": "GB", "meta:provider": ["geoplanet:7.3.1", "geoplanet:7.3.2", "geoplanet:7.4.0", "geoplanet:7.4.1", "geoplanet:7.5.1", "geoplanet:7.5.2", "geoplanet:7.6.0", "geoplanet:7.8.1", "geoplanet:7.9.0", "geoplanet:7.10.0", "geoplanet:8.0.0", "woeplanet:8.0.0"], "meta:indexed": "2020-08-20T19:45:31.747561", "woe:alias_ENG_V": ["Littleport Station"], "meta:updated": "2020-10-14T11:22:08.266045", "woe:hierarchy": {"continent": 24865675, "country": 23424975, "town": 0, "planet": 1, "county": 12602140, "suburb": 0, "state": 24554868, "region": 0, "localadmin": 12695883}, "woe:timezone_id": 28350903, "woe:hash": "u124rnqw6nzu", "woe:centroid": [0.31664, 52.4622], "geom:latitude": 52.4622, "geom:longitude": 0.31664, "geom:hash": "u124rnqw6nzu", "woe:latitude": 52.4622, "geom:centroid": [0.31664, 52.4622], "woe:longitude": 0.31664, "woe:repo": "woeplanet-poi-gb", "geom:area": 0.0, "woe:scale": 19}}