{"type": "Feature", "id": 22476660, "geometry": {"type": "Point", "coordinates": [-0.28105, 51.51783]}, "properties": {"woe:id": 22476660, "woe:parent_id": 20089545, "woe:name": "West Acton Underground Station", "woe:placetype": 20, "woe:placetype_name": "POI", "woe:lang": "ENG", "iso:country": "GB", "meta:provider": ["geoplanet:7.3.1", "geoplanet:7.3.2", "geoplanet:7.4.0", "geoplanet:7.4.1", "geoplanet:7.5.1", "geoplanet:7.5.2", "geoplanet:7.6.0", "geoplanet:7.8.1", "geoplanet:7.9.0", "geoplanet:7.10.0", "geoplanet:8.0.0", "woeplanet:8.0.0"], "meta:indexed": "2020-08-20T19:45:32.735834", "woe:alias_ENG_V": ["W Acton Underground Station", "West Acton Station", "West Acton Tube Station", "W Acton Station", "W Acton Tube", "West Acton Tube", "West Acton Underground", "W Acton Underground", "W Acton Tube Station"], "meta:updated": "2020-10-14T11:22:07.847243", "woe:hierarchy": {"continent": 24865675, "country": 23424975, "town": 0, "planet": 1, "county": 23416974, "suburb": 0, "state": 24554868, "region": 0, "localadmin": 12695826}, "woe:timezone_id": 28350903, "woe:hash": "gcpv1de3559f", "woe:centroid": [-0.28105, 51.51783], "geom:latitude": 51.51783, "geom:longitude": -0.28105, "geom:hash": "gcpv1de3559f", "woe:latitude": 51.51783, "geom:centroid": [-0.28105, 51.51783], "woe:longitude": -0.28105, "woe:repo": "woeplanet-poi-gb", "geom:area": 0.0, "woe:scale": 19}}