{"type": "Feature", "id": 22491884, "geometry": {"type": "Point", "coordinates": [-3.54361, 50.461712]}, "properties": {"woe:id": 22491884, "woe:parent_id": 37818, "woe:name": "Torquay Railway Station", "woe:placetype": 20, "woe:placetype_name": "POI", "woe:lang": "ENG", "iso:country": "GB", "meta:provider": ["geoplanet:7.3.1", "geoplanet:7.3.2", "geoplanet:7.4.0", "geoplanet:7.4.1", "geoplanet:7.5.1", "geoplanet:7.5.2", "geoplanet:7.6.0", "geoplanet:7.8.1", "geoplanet:7.9.0", "geoplanet:7.10.0", "geoplanet:8.0.0", "woeplanet:8.0.0"], "meta:indexed": "2020-08-20T19:45:33.598568", "woe:alias_ENG_V": ["Torquay Station"], "meta:updated": "2020-10-14T11:22:08.982284", "woe:hierarchy": {"continent": 24865675, "country": 23424975, "town": 0, "planet": 1, "county": 12602182, "suburb": 0, "state": 24554868, "region": 0, "localadmin": 12696174}, "woe:timezone_id": 28350903, "woe:hash": "gbvrp678gbuv", "woe:centroid": [-3.54361, 50.461712], "geom:latitude": 50.461712, "geom:longitude": -3.54361, "geom:hash": "gbvrp678gbuv", "woe:latitude": 50.461712, "geom:centroid": [-3.54361, 50.461712], "woe:longitude": -3.54361, "woe:repo": "woeplanet-poi-gb", "geom:area": 0.0, "woe:scale": 19}}