{"type": "Feature", "id": 22472930, "properties": {"woe:id": 22472930, "woe:parent_id": 26347, "woe:name": "Liphook Golf Course", "woe:placetype": 20, "woe:placetype_name": "POI", "woe:lang": "ENG", "iso:country": "GB", "meta:provider": ["geoplanet:7.3.1", "geoplanet:7.3.2", "geoplanet:7.4.0", "geoplanet:7.4.1", "geoplanet:7.5.1", "geoplanet:7.5.2", "geoplanet:7.6.0", "geoplanet:7.8.1", "geoplanet:7.9.0", "geoplanet:7.10.0", "geoplanet:8.0.0", "woeplanet:8.0.0"], "meta:indexed": "2020-08-20T19:45:32.302639", "meta:updated": "2020-08-22T02:03:29.050716", "woe:hierarchy": {"continent": 24865675, "country": 23424975, "town": 0, "planet": 1, "county": 12602177, "suburb": 0, "state": 24554868, "region": 0, "localadmin": 12696105}, "woe:timezone_id": 28350903, "woe:hash": "gcp6mx41urny", "woe:centroid": [-0.81005, 51.059299], "geom:latitude": 51.059299, "geom:longitude": -0.81005, "geom:hash": "gcp6mx41urny", "woe:latitude": 51.059299, "geom:centroid": [-0.81005, 51.059299], "woe:longitude": -0.81005, "woe:repo": "woeplanet-poi-gb"}, "geometry": {"coordinates": [-0.81005, 51.059299], "type": "Point"}}