{"type": "Feature", "id": 22452186, "geometry": {"type": "Point", "coordinates": [-1.09557, 51.823311]}, "properties": {"woe:id": 22452186, "woe:parent_id": 13108, "woe:name": "Boarstall Tower", "woe:placetype": 20, "woe:placetype_name": "POI", "woe:lang": "ENG", "iso:country": "GB", "meta:provider": ["geoplanet:7.3.1", "geoplanet:7.3.2", "geoplanet:7.4.0", "geoplanet:7.4.1", "geoplanet:7.5.1", "geoplanet:7.5.2", "geoplanet:7.6.0", "geoplanet:7.8.1", "geoplanet:7.9.0", "geoplanet:7.10.0", "geoplanet:8.0.0", "woeplanet:8.0.0"], "meta:indexed": "2020-08-20T19:45:31.047036", "meta:updated": "2020-10-14T11:22:09.314769", "woe:hierarchy": {"continent": 24865675, "country": 23424975, "town": 0, "planet": 1, "county": 12602166, "suburb": 0, "state": 24554868, "region": 0, "localadmin": 12695878}, "woe:timezone_id": 28350903, "woe:hash": "gcpnz44hxm7g", "woe:centroid": [-1.09557, 51.823311], "geom:latitude": 51.823311, "geom:longitude": -1.09557, "geom:hash": "gcpnz44hxm7g", "woe:latitude": 51.823311, "geom:centroid": [-1.09557, 51.823311], "woe:longitude": -1.09557, "woe:repo": "woeplanet-poi-gb", "geom:area": 0.0, "woe:scale": 19}}