{"type": "Feature", "id": 22470338, "geometry": {"type": "Point", "coordinates": [-1.9025, 53.875301]}, "properties": {"woe:id": 22470338, "woe:parent_id": 24688, "woe:name": "Cougar Park", "woe:placetype": 20, "woe:placetype_name": "POI", "woe:lang": "ENG", "iso:country": "GB", "meta:provider": ["geoplanet:7.3.1", "geoplanet:7.3.2", "geoplanet:7.4.0", "geoplanet:7.4.1", "geoplanet:7.5.1", "geoplanet:7.5.2", "geoplanet:7.6.0", "geoplanet:7.8.1", "geoplanet:7.9.0", "geoplanet:7.10.0", "geoplanet:8.0.0", "woeplanet:8.0.0"], "meta:indexed": "2020-08-20T19:45:32.179198", "meta:updated": "2020-10-14T11:22:08.939788", "woe:hierarchy": {"continent": 24865675, "country": 23424975, "town": 0, "planet": 1, "county": 12602197, "suburb": 0, "state": 24554868, "region": 0, "localadmin": 12695870}, "woe:timezone_id": 28350903, "woe:hash": "gcwdkxwwks10", "woe:centroid": [-1.9025, 53.875301], "geom:latitude": 53.875301, "geom:longitude": -1.9025, "geom:hash": "gcwdkxwwks10", "woe:latitude": 53.875301, "geom:centroid": [-1.9025, 53.875301], "woe:longitude": -1.9025, "woe:repo": "woeplanet-poi-gb", "geom:area": 0.0, "woe:scale": 19}}