{"type": "Feature", "id": 22467028, "properties": {"woe:id": 22467028, "woe:parent_id": 21824, "woe:name": "Cartsdyke Railway Station", "woe:placetype": 20, "woe:placetype_name": "POI", "woe:lang": "ENG", "iso:country": "GB", "meta:provider": ["geoplanet:7.3.1", "geoplanet:7.3.2", "geoplanet:7.4.0", "geoplanet:7.4.1", "geoplanet:7.5.1", "geoplanet:7.5.2", "geoplanet:7.6.0", "geoplanet:7.8.1", "geoplanet:7.9.0", "geoplanet:7.10.0", "geoplanet:8.0.0", "woeplanet:8.0.0"], "meta:indexed": "2020-08-20T19:45:31.986718", "woe:alias_ENG_V": ["Cartsdyke Station"], "meta:updated": "2020-08-22T02:03:28.900258", "woe:hierarchy": {"continent": 24865675, "country": 23424975, "town": 0, "planet": 1, "county": 12602207, "suburb": 0, "state": 12578048, "region": 0, "localadmin": 12696200}, "woe:timezone_id": 28350903, "woe:hash": "gcuwhrfm9wf2", "woe:centroid": [-4.73195, 55.94199], "geom:latitude": 55.94199, "geom:longitude": -4.73195, "geom:hash": "gcuwhrfm9wf2", "woe:latitude": 55.94199, "geom:centroid": [-4.73195, 55.94199], "woe:longitude": -4.73195, "woe:repo": "woeplanet-poi-gb"}, "geometry": {"coordinates": [-4.73195, 55.94199], "type": "Point"}}