{"type": "Feature", "id": 22465015, "geometry": {"type": "Point", "coordinates": [-3.04287, 53.917252]}, "properties": {"woe:id": 22465015, "woe:parent_id": 20299, "woe:name": "Fleetwood Golf Course", "woe:placetype": 20, "woe:placetype_name": "POI", "woe:lang": "ENG", "iso:country": "GB", "meta:provider": ["geoplanet:7.3.1", "geoplanet:7.3.2", "geoplanet:7.4.0", "geoplanet:7.4.1", "geoplanet:7.5.1", "geoplanet:7.5.2", "geoplanet:7.6.0", "geoplanet:7.8.1", "geoplanet:7.9.0", "geoplanet:7.10.0", "geoplanet:8.0.0", "woeplanet:8.0.0"], "meta:indexed": "2020-08-20T19:45:31.819638", "meta:updated": "2020-10-14T11:22:08.666308", "woe:hierarchy": {"continent": 24865675, "country": 23424975, "town": 0, "planet": 1, "county": 12602160, "suburb": 0, "state": 24554868, "region": 0, "localadmin": 12696008}, "woe:timezone_id": 28350903, "woe:hash": "gctfdz24zbr8", "woe:centroid": [-3.04287, 53.917252], "geom:latitude": 53.917252, "geom:longitude": -3.04287, "geom:hash": "gctfdz24zbr8", "woe:latitude": 53.917252, "geom:centroid": [-3.04287, 53.917252], "woe:longitude": -3.04287, "woe:repo": "woeplanet-poi-gb", "geom:area": 0.0, "woe:scale": 19}}