{"type": "Feature", "id": 22491903, "geometry": {"type": "Point", "coordinates": [-3.63662, 50.449001]}, "properties": {"woe:id": 22491903, "woe:parent_id": 12429, "woe:name": "Berry Pomeroy Castle", "woe:placetype": 20, "woe:placetype_name": "POI", "woe:lang": "ENG", "iso:country": "GB", "meta:provider": ["geoplanet:7.3.1", "geoplanet:7.3.2", "geoplanet:7.4.0", "geoplanet:7.4.1", "geoplanet:7.5.1", "geoplanet:7.5.2", "geoplanet:7.6.0", "geoplanet:7.8.1", "geoplanet:7.9.0", "geoplanet:7.10.0", "geoplanet:8.0.0", "woeplanet:8.0.0"], "meta:indexed": "2020-08-20T19:45:33.600203", "meta:updated": "2020-10-14T11:22:09.152725", "woe:hierarchy": {"continent": 24865675, "country": 23424975, "town": 0, "planet": 1, "county": 12602182, "suburb": 0, "state": 24554868, "region": 0, "localadmin": 12695918}, "woe:timezone_id": 28350903, "woe:hash": "gbvqvpzysx7t", "woe:centroid": [-3.63662, 50.449001], "geom:latitude": 50.449001, "geom:longitude": -3.63662, "geom:hash": "gbvqvpzysx7t", "woe:latitude": 50.449001, "geom:centroid": [-3.63662, 50.449001], "woe:longitude": -3.63662, "woe:repo": "woeplanet-poi-gb", "geom:area": 0.0, "woe:scale": 19}}