{"type": "Feature", "id": 22461699, "geometry": {"type": "Point", "coordinates": [-4.98393, 56.400829]}, "properties": {"woe:id": 22461699, "woe:parent_id": 17860, "woe:name": "Dalmally Railway Station", "woe:placetype": 20, "woe:placetype_name": "POI", "woe:lang": "ENG", "iso:country": "GB", "meta:provider": ["geoplanet:7.3.1", "geoplanet:7.3.2", "geoplanet:7.4.0", "geoplanet:7.4.1", "geoplanet:7.5.1", "geoplanet:7.5.2", "geoplanet:7.6.0", "geoplanet:7.8.1", "geoplanet:7.9.0", "geoplanet:7.10.0", "geoplanet:8.0.0", "woeplanet:8.0.0"], "meta:indexed": "2020-08-20T19:45:31.615374", "woe:alias_ENG_V": ["Dalmally Station"], "meta:updated": "2020-10-14T11:22:07.819801", "woe:hierarchy": {"continent": 24865675, "country": 23424975, "town": 0, "planet": 1, "county": 12602207, "suburb": 0, "state": 12578048, "region": 0, "localadmin": 12696185}, "woe:timezone_id": 28350903, "woe:hash": "gfh2ye6ydh86", "woe:centroid": [-4.98393, 56.400829], "geom:latitude": 56.400829, "geom:longitude": -4.98393, "geom:hash": "gfh2ye6ydh86", "woe:latitude": 56.400829, "geom:centroid": [-4.98393, 56.400829], "woe:longitude": -4.98393, "woe:repo": "woeplanet-poi-gb", "geom:area": 0.0, "woe:scale": 19}}