{"type": "Feature", "id": 22452441, "properties": {"woe:id": 22452441, "woe:parent_id": 18885, "woe:name": "Banbury Golf Course", "woe:placetype": 20, "woe:placetype_name": "POI", "woe:lang": "ENG", "iso:country": "GB", "meta:provider": ["geoplanet:7.3.1", "geoplanet:7.3.2", "geoplanet:7.4.0", "geoplanet:7.4.1", "geoplanet:7.5.1", "geoplanet:7.5.2", "geoplanet:7.6.0", "geoplanet:7.8.1", "geoplanet:7.9.0", "geoplanet:7.10.0", "geoplanet:8.0.0", "woeplanet:8.0.0"], "meta:indexed": "2020-08-20T19:45:31.063341", "meta:updated": "2020-08-22T02:03:28.499506", "woe:hierarchy": {"continent": 24865675, "country": 23424975, "town": 0, "planet": 1, "county": 12602175, "suburb": 0, "state": 24554868, "region": 0, "localadmin": 12696057}, "woe:timezone_id": 28350903, "woe:hash": "gcppfe7knt52", "woe:centroid": [-1.29164, 52.005871], "geom:latitude": 52.005871, "geom:longitude": -1.29164, "geom:hash": "gcppfe7knt52", "woe:latitude": 52.005871, "geom:centroid": [-1.29164, 52.005871], "woe:longitude": -1.29164, "woe:repo": "woeplanet-poi-gb"}, "geometry": {"coordinates": [-1.29164, 52.005871], "type": "Point"}}