{"type": "Feature", "id": 22494367, "geometry": {"type": "Point", "coordinates": [-2.70905, 53.530102]}, "properties": {"woe:id": 22494367, "woe:parent_id": 31093, "woe:name": "Orrell Railway Station", "woe:placetype": 20, "woe:placetype_name": "POI", "woe:lang": "ENG", "iso:country": "GB", "meta:provider": ["geoplanet:7.3.1", "geoplanet:7.3.2", "geoplanet:7.4.0", "geoplanet:7.4.1", "geoplanet:7.5.1", "geoplanet:7.5.2", "geoplanet:7.6.0", "geoplanet:7.8.1", "geoplanet:7.9.0", "geoplanet:7.10.0", "geoplanet:8.0.0", "woeplanet:8.0.0"], "meta:indexed": "2020-08-20T19:45:33.742720", "woe:alias_ENG_V": ["Orrell Station"], "meta:updated": "2020-10-14T11:22:09.505936", "woe:hierarchy": {"continent": 24865675, "country": 23424975, "town": 0, "planet": 1, "county": 12602158, "suburb": 0, "state": 24554868, "region": 0, "localadmin": 12695848}, "woe:timezone_id": 28350903, "woe:hash": "gcw0d2g76w3b", "woe:centroid": [-2.70905, 53.530102], "geom:latitude": 53.530102, "geom:longitude": -2.70905, "geom:hash": "gcw0d2g76w3b", "woe:latitude": 53.530102, "geom:centroid": [-2.70905, 53.530102], "woe:longitude": -2.70905, "woe:repo": "woeplanet-poi-gb", "geom:area": 0.0, "woe:scale": 19}}