{"type": "Feature", "id": 22463603, "properties": {"woe:id": 22463603, "woe:parent_id": 28339, "woe:name": "Cowden Railway Station", "woe:placetype": 20, "woe:placetype_name": "POI", "woe:lang": "ENG", "iso:country": "GB", "meta:provider": ["geoplanet:7.3.1", "geoplanet:7.3.2", "geoplanet:7.4.0", "geoplanet:7.4.1", "geoplanet:7.5.1", "geoplanet:7.5.2", "geoplanet:7.6.0", "geoplanet:7.8.1", "geoplanet:7.9.0", "geoplanet:7.10.0", "geoplanet:8.0.0", "woeplanet:8.0.0"], "meta:indexed": "2020-08-20T19:45:31.722371", "woe:alias_ENG_V": ["Cowden Station"], "meta:updated": "2020-08-22T02:03:28.775561", "woe:hierarchy": {"continent": 24865675, "country": 23424975, "town": 0, "planet": 1, "county": 12602173, "suburb": 0, "state": 24554868, "region": 0, "localadmin": 12695991}, "woe:timezone_id": 28350903, "woe:hash": "u1054884d3z8", "woe:centroid": [0.10997, 51.155529], "geom:latitude": 51.155529, "geom:longitude": 0.10997, "geom:hash": "u1054884d3z8", "woe:latitude": 51.155529, "geom:centroid": [0.10997, 51.155529], "woe:longitude": 0.10997, "woe:repo": "woeplanet-poi-gb"}, "geometry": {"coordinates": [0.10997, 51.155529], "type": "Point"}}