{"type": "Feature", "id": 22459630, "geometry": {"type": "Point", "coordinates": [-1.57828, 54.855019]}, "properties": {"woe:id": 22459630, "woe:parent_id": 15832, "woe:name": "Chester-le-Street Railway Station", "woe:placetype": 20, "woe:placetype_name": "POI", "woe:lang": "ENG", "iso:country": "GB", "meta:provider": ["geoplanet:7.3.1", "geoplanet:7.3.2", "geoplanet:7.4.0", "geoplanet:7.4.1", "geoplanet:7.5.1", "geoplanet:7.5.2", "geoplanet:7.6.0", "geoplanet:7.8.1", "geoplanet:7.9.0", "geoplanet:7.10.0", "geoplanet:8.0.0", "woeplanet:8.0.0"], "meta:indexed": "2020-08-20T19:45:31.502578", "woe:alias_ENG_V": ["Chester le Street Railway Station", "Chester le Street Station", "Chester-le-Street Station"], "meta:updated": "2020-10-14T11:22:08.583765", "woe:hierarchy": {"continent": 24865675, "country": 23424975, "town": 0, "planet": 1, "county": 12602150, "suburb": 0, "state": 24554868, "region": 0, "localadmin": 12695928}, "woe:timezone_id": 28350903, "woe:hash": "gcybh449xktn", "woe:centroid": [-1.57828, 54.855019], "geom:latitude": 54.855019, "geom:longitude": -1.57828, "geom:hash": "gcybh449xktn", "woe:latitude": 54.855019, "geom:centroid": [-1.57828, 54.855019], "woe:longitude": -1.57828, "woe:repo": "woeplanet-poi-gb", "geom:area": 0.0, "woe:scale": 19}}