{"type": "Feature", "id": 22485473, "properties": {"woe:id": 22485473, "woe:parent_id": 20089462, "woe:name": "Gidea Park Railway Station", "woe:placetype": 20, "woe:placetype_name": "POI", "woe:lang": "ENG", "iso:country": "GB", "meta:provider": ["geoplanet:7.3.1", "geoplanet:7.3.2", "geoplanet:7.4.0", "geoplanet:7.4.1", "geoplanet:7.5.1", "geoplanet:7.5.2", "geoplanet:7.6.0", "geoplanet:7.8.1", "geoplanet:7.9.0", "geoplanet:7.10.0", "geoplanet:8.0.0", "woeplanet:8.0.0"], "meta:indexed": "2020-08-20T19:45:33.254680", "woe:alias_ENG_V": ["Gidea Park Station"], "meta:updated": "2020-08-22T02:03:29.505843", "woe:hierarchy": {"continent": 24865675, "country": 23424975, "town": 0, "planet": 1, "county": 23416974, "suburb": 0, "state": 24554868, "region": 0, "localadmin": 12695830}, "woe:timezone_id": 28350903, "woe:hash": "u10jkwjse945", "woe:centroid": [0.20546, 51.581589], "geom:latitude": 51.581589, "geom:longitude": 0.20546, "geom:hash": "u10jkwjse945", "woe:latitude": 51.581589, "geom:centroid": [0.20546, 51.581589], "woe:longitude": 0.20546, "woe:repo": "woeplanet-poi-gb"}, "geometry": {"coordinates": [0.20546, 51.581589], "type": "Point"}}