{"type": "Feature", "id": 22463085, "geometry": {"type": "Point", "coordinates": [-2.96896, 56.474701]}, "properties": {"woe:id": 22463085, "woe:parent_id": 18637, "woe:name": "Tannadice Park", "woe:placetype": 20, "woe:placetype_name": "POI", "woe:lang": "ENG", "iso:country": "GB", "meta:provider": ["geoplanet:7.3.1", "geoplanet:7.3.2", "geoplanet:7.4.0", "geoplanet:7.4.1", "geoplanet:7.5.1", "geoplanet:7.5.2", "geoplanet:7.6.0", "geoplanet:7.8.1", "geoplanet:7.9.0", "geoplanet:7.10.0", "geoplanet:8.0.0", "woeplanet:8.0.0"], "meta:indexed": "2020-08-20T19:45:31.699897", "meta:updated": "2020-10-14T11:22:09.921382", "woe:alias_ENG_V": ["Dundee United Football Club"], "woe:hierarchy": {"continent": 24865675, "country": 23424975, "town": 0, "planet": 1, "county": 12602208, "suburb": 0, "state": 12578048, "region": 0, "localadmin": 12696190}, "woe:timezone_id": 28350903, "woe:hash": "gfjck2yhfpqc", "woe:centroid": [-2.96896, 56.474701], "geom:latitude": 56.474701, "geom:longitude": -2.96896, "geom:hash": "gfjck2yhfpqc", "woe:latitude": 56.474701, "geom:centroid": [-2.96896, 56.474701], "woe:longitude": -2.96896, "woe:repo": "woeplanet-poi-gb", "geom:area": 0.0, "woe:scale": 19}}