{"type": "Feature", "id": 22459068, "geometry": {"type": "Point", "coordinates": [-0.58734, 51.62656]}, "properties": {"woe:id": 22459068, "woe:parent_id": 15580, "woe:name": "Chalfont Park Golf Club", "woe:placetype": 20, "woe:placetype_name": "POI", "woe:lang": "ENG", "iso:country": "GB", "meta:provider": ["geoplanet:7.3.1", "geoplanet:7.3.2", "geoplanet:7.4.0", "geoplanet:7.4.1", "geoplanet:7.5.1", "geoplanet:7.5.2", "geoplanet:7.6.0", "geoplanet:7.8.1", "geoplanet:7.9.0", "geoplanet:7.10.0", "geoplanet:8.0.0", "woeplanet:8.0.0"], "meta:indexed": "2020-08-20T19:45:31.469625", "meta:updated": "2020-10-14T11:22:09.687627", "woe:hierarchy": {"continent": 24865675, "country": 23424975, "town": 0, "planet": 1, "county": 12602166, "suburb": 0, "state": 24554868, "region": 0, "localadmin": 12695879}, "woe:timezone_id": 28350903, "woe:hash": "gcptdwk69brd", "woe:centroid": [-0.58734, 51.62656], "geom:latitude": 51.62656, "geom:longitude": -0.58734, "geom:hash": "gcptdwk69brd", "woe:latitude": 51.62656, "geom:centroid": [-0.58734, 51.62656], "woe:longitude": -0.58734, "woe:repo": "woeplanet-poi-gb", "geom:area": 0.0, "woe:scale": 19}}