{"type": "Feature", "id": 22474212, "geometry": {"type": "Point", "coordinates": [-0.03752, 51.464298]}, "properties": {"woe:id": 22474212, "woe:parent_id": 20089486, "woe:name": "Brockley Railway Station", "woe:placetype": 20, "woe:placetype_name": "POI", "woe:lang": "ENG", "iso:country": "GB", "meta:provider": ["geoplanet:7.3.1", "geoplanet:7.3.2", "geoplanet:7.4.0", "geoplanet:7.4.1", "geoplanet:7.5.1", "geoplanet:7.5.2", "geoplanet:7.6.0", "geoplanet:7.8.1", "geoplanet:7.9.0", "geoplanet:7.10.0", "geoplanet:8.0.0", "woeplanet:8.0.0"], "meta:indexed": "2020-08-20T19:45:32.415844", "woe:alias_ENG_V": ["Brockley Station"], "meta:updated": "2020-10-14T11:22:07.661951", "woe:hierarchy": {"continent": 24865675, "country": 23424975, "town": 0, "planet": 1, "county": 23416974, "suburb": 0, "state": 24554868, "region": 0, "localadmin": 12695814}, "woe:timezone_id": 28350903, "woe:hash": "gcpuz0u9m8rp", "woe:centroid": [-0.03752, 51.464298], "geom:latitude": 51.464298, "geom:longitude": -0.03752, "geom:hash": "gcpuz0u9m8rp", "woe:latitude": 51.464298, "geom:centroid": [-0.03752, 51.464298], "woe:longitude": -0.03752, "woe:repo": "woeplanet-poi-gb", "geom:area": 0.0, "woe:scale": 19}}