{"type": "Feature", "id": 22473726, "geometry": {"type": "Point", "coordinates": [-3.5557, 52.113682]}, "properties": {"woe:id": 22473726, "woe:parent_id": 26956, "woe:name": "Llangammarch Railway Station", "woe:placetype": 20, "woe:placetype_name": "POI", "woe:lang": "ENG", "iso:country": "GB", "meta:provider": ["geoplanet:7.3.1", "geoplanet:7.3.2", "geoplanet:7.4.0", "geoplanet:7.4.1", "geoplanet:7.5.1", "geoplanet:7.5.2", "geoplanet:7.6.0", "geoplanet:7.8.1", "geoplanet:7.9.0", "geoplanet:7.10.0", "geoplanet:8.0.0", "woeplanet:8.0.0"], "meta:indexed": "2020-08-20T19:45:32.356401", "woe:alias_ENG_V": ["Llangammarch Station"], "meta:updated": "2020-10-14T11:22:08.211001", "woe:hierarchy": {"continent": 24865675, "country": 23424975, "town": 0, "planet": 1, "county": 12602227, "suburb": 0, "state": 12578049, "region": 0, "localadmin": 12696134}, "woe:timezone_id": 28350903, "woe:hash": "gcm2rp4b4nmy", "woe:centroid": [-3.5557, 52.113682], "geom:latitude": 52.113682, "geom:longitude": -3.5557, "geom:hash": "gcm2rp4b4nmy", "woe:latitude": 52.113682, "geom:centroid": [-3.5557, 52.113682], "woe:longitude": -3.5557, "woe:repo": "woeplanet-poi-gb", "geom:area": 0.0, "woe:scale": 19}}