{"type": "Feature", "id": 22459875, "geometry": {"type": "Point", "coordinates": [-2.1149, 51.46244]}, "properties": {"woe:id": 22459875, "woe:parent_id": 15952, "woe:name": "Chippenham Railway Station", "woe:placetype": 20, "woe:placetype_name": "POI", "woe:lang": "ENG", "iso:country": "GB", "meta:provider": ["geoplanet:7.3.1", "geoplanet:7.3.2", "geoplanet:7.4.0", "geoplanet:7.4.1", "geoplanet:7.5.1", "geoplanet:7.5.2", "geoplanet:7.6.0", "geoplanet:7.8.1", "geoplanet:7.9.0", "geoplanet:7.10.0", "geoplanet:8.0.0", "woeplanet:8.0.0"], "meta:indexed": "2020-08-20T19:45:31.514278", "woe:alias_ENG_V": ["Chippenham Station"], "meta:updated": "2020-10-14T11:22:09.862021", "woe:hierarchy": {"continent": 24865675, "country": 23424975, "town": 0, "planet": 1, "county": 12602186, "suburb": 0, "state": 24554868, "region": 0, "localadmin": 12696111}, "woe:timezone_id": 28350903, "woe:hash": "gcnkzb7yrq0k", "woe:centroid": [-2.1149, 51.46244], "geom:latitude": 51.46244, "geom:longitude": -2.1149, "geom:hash": "gcnkzb7yrq0k", "woe:latitude": 51.46244, "geom:centroid": [-2.1149, 51.46244], "woe:longitude": -2.1149, "woe:repo": "woeplanet-poi-gb", "geom:area": 0.0, "woe:scale": 19}}