{"type": "Feature", "id": 22473920, "properties": {"woe:id": 22473920, "woe:parent_id": 43323, "woe:name": "Acton Town Underground Station", "woe:placetype": 20, "woe:placetype_name": "POI", "woe:lang": "ENG", "iso:country": "GB", "meta:provider": ["geoplanet:7.3.1", "geoplanet:7.3.2", "geoplanet:7.4.0", "geoplanet:7.4.1", "geoplanet:7.5.1", "geoplanet:7.5.2", "geoplanet:7.6.0", "geoplanet:7.8.1", "geoplanet:7.9.0", "geoplanet:7.10.0", "geoplanet:8.0.0", "woeplanet:8.0.0"], "meta:indexed": "2020-08-20T19:45:32.372077", "woe:alias_ENG_V": ["Acton Town Tube", "Acton Town Underground", "Acton Town Station", "Acton Town Tube Station"], "meta:updated": "2020-08-22T02:03:29.085665", "woe:hierarchy": {"continent": 24865675, "country": 23424975, "town": 0, "planet": 1, "county": 23416974, "suburb": 0, "state": 24554868, "region": 0, "localadmin": 12695826}, "woe:timezone_id": 28350903, "woe:hash": "gcpucxgg0h73", "woe:centroid": [-0.28049, 51.503071], "geom:latitude": 51.503071, "geom:longitude": -0.28049, "geom:hash": "gcpucxgg0h73", "woe:latitude": 51.503071, "geom:centroid": [-0.28049, 51.503071], "woe:longitude": -0.28049, "woe:repo": "woeplanet-poi-gb"}, "geometry": {"coordinates": [-0.28049, 51.503071], "type": "Point"}}