{"type": "Feature", "id": 22485147, "geometry": {"type": "Point", "coordinates": [-0.28843, 51.465221]}, "properties": {"woe:id": 22485147, "woe:parent_id": 20089531, "woe:name": "North Sheen Railway Station", "woe:placetype": 20, "woe:placetype_name": "POI", "woe:lang": "ENG", "iso:country": "GB", "meta:provider": ["geoplanet:7.3.1", "geoplanet:7.3.2", "geoplanet:7.4.0", "geoplanet:7.4.1", "geoplanet:7.5.1", "geoplanet:7.5.2", "geoplanet:7.6.0", "geoplanet:7.8.1", "geoplanet:7.9.0", "geoplanet:7.10.0", "geoplanet:8.0.0", "woeplanet:8.0.0"], "meta:indexed": "2020-08-20T19:45:33.234037", "woe:alias_ENG_V": ["N Sheen Station", "North Sheen Station"], "meta:updated": "2020-10-14T11:22:09.542181", "woe:hierarchy": {"continent": 24865675, "country": 23424975, "town": 0, "planet": 1, "county": 23416974, "suburb": 0, "state": 24554868, "region": 0, "localadmin": 12695836}, "woe:timezone_id": 28350903, "woe:hash": "gcpuc2vyxhe1", "woe:centroid": [-0.28843, 51.465221], "geom:latitude": 51.465221, "geom:longitude": -0.28843, "geom:hash": "gcpuc2vyxhe1", "woe:latitude": 51.465221, "geom:centroid": [-0.28843, 51.465221], "woe:longitude": -0.28843, "woe:repo": "woeplanet-poi-gb", "geom:area": 0.0, "woe:scale": 19}}