{"type": "Feature", "id": 22485099, "geometry": {"type": "Point", "coordinates": [-4.50663, 53.234539]}, "properties": {"woe:id": 22485099, "woe:parent_id": 26892, "woe:name": "Rhosneigr Railway Station", "woe:placetype": 20, "woe:placetype_name": "POI", "woe:lang": "ENG", "iso:country": "GB", "meta:provider": ["geoplanet:7.3.1", "geoplanet:7.3.2", "geoplanet:7.4.0", "geoplanet:7.4.1", "geoplanet:7.5.1", "geoplanet:7.5.2", "geoplanet:7.6.0", "geoplanet:7.8.1", "geoplanet:7.9.0", "geoplanet:7.10.0", "geoplanet:8.0.0", "woeplanet:8.0.0"], "meta:indexed": "2020-08-20T19:45:33.229012", "woe:alias_ENG_V": ["Rhosneigr Station"], "meta:updated": "2020-10-14T11:22:07.946093", "woe:hierarchy": {"continent": 24865675, "country": 23424975, "town": 0, "planet": 1, "county": 12602211, "suburb": 0, "state": 12578049, "region": 0, "localadmin": 12696117}, "woe:timezone_id": 28350903, "woe:hash": "gckyc7n3evm4", "woe:centroid": [-4.50663, 53.234539], "geom:latitude": 53.234539, "geom:longitude": -4.50663, "geom:hash": "gckyc7n3evm4", "woe:latitude": 53.234539, "geom:centroid": [-4.50663, 53.234539], "woe:longitude": -4.50663, "woe:repo": "woeplanet-poi-gb", "geom:area": 0.0, "woe:scale": 19}}