{"type": "Feature", "id": 22481545, "properties": {"woe:id": 22481545, "woe:parent_id": 13024, "woe:name": "Bleasby Railway Station", "woe:placetype": 20, "woe:placetype_name": "POI", "woe:lang": "ENG", "iso:country": "GB", "meta:provider": ["geoplanet:7.3.1", "geoplanet:7.3.2", "geoplanet:7.4.0", "geoplanet:7.4.1", "geoplanet:7.5.1", "geoplanet:7.5.2", "geoplanet:7.6.0", "geoplanet:7.8.1", "geoplanet:7.9.0", "geoplanet:7.10.0", "geoplanet:8.0.0", "woeplanet:8.0.0"], "meta:indexed": "2020-08-20T19:45:33.032146", "woe:alias_ENG_V": ["Bleasby Station"], "meta:updated": "2020-08-22T02:03:29.407145", "woe:hierarchy": {"continent": 24865675, "country": 23424975, "town": 0, "planet": 1, "county": 12602147, "suburb": 0, "state": 24554868, "region": 0, "localadmin": 12696055}, "woe:timezone_id": 28350903, "woe:hash": "gcrmdrzgnn25", "woe:centroid": [-0.94491, 53.041168], "geom:latitude": 53.041168, "geom:longitude": -0.94491, "geom:hash": "gcrmdrzgnn25", "woe:latitude": 53.041168, "geom:centroid": [-0.94491, 53.041168], "woe:longitude": -0.94491, "woe:repo": "woeplanet-poi-gb"}, "geometry": {"coordinates": [-0.94491, 53.041168], "type": "Point"}}