{"type": "Feature", "id": 22473545, "geometry": {"type": "Point", "coordinates": [-3.80266, 51.995411]}, "properties": {"woe:id": 22473545, "woe:parent_id": 26843, "woe:name": "Llandovery Railway Station", "woe:placetype": 20, "woe:placetype_name": "POI", "woe:lang": "ENG", "iso:country": "GB", "meta:provider": ["geoplanet:7.3.1", "geoplanet:7.3.2", "geoplanet:7.4.0", "geoplanet:7.4.1", "geoplanet:7.5.1", "geoplanet:7.5.2", "geoplanet:7.6.0", "geoplanet:7.8.1", "geoplanet:7.9.0", "geoplanet:7.10.0", "geoplanet:8.0.0", "woeplanet:8.0.0"], "meta:indexed": "2020-08-20T19:45:32.346149", "woe:alias_ENG_V": ["Llandovery Station"], "meta:updated": "2020-10-14T11:22:08.303770", "woe:hierarchy": {"continent": 24865675, "country": 23424975, "town": 0, "planet": 1, "county": 12602216, "suburb": 0, "state": 12578049, "region": 0, "localadmin": 12696118}, "woe:timezone_id": 28350903, "woe:hash": "gcjrc3qzpx5h", "woe:centroid": [-3.80266, 51.995411], "geom:latitude": 51.995411, "geom:longitude": -3.80266, "geom:hash": "gcjrc3qzpx5h", "woe:latitude": 51.995411, "geom:centroid": [-3.80266, 51.995411], "woe:longitude": -3.80266, "woe:repo": "woeplanet-poi-gb", "geom:area": 0.0, "woe:scale": 19}}