{"type": "Feature", "id": 22460708, "properties": {"woe:id": 22460708, "woe:parent_id": 16845, "woe:name": "Corbridge Railway Station", "woe:placetype": 20, "woe:placetype_name": "POI", "woe:lang": "ENG", "iso:country": "GB", "meta:provider": ["geoplanet:7.3.1", "geoplanet:7.3.2", "geoplanet:7.4.0", "geoplanet:7.4.1", "geoplanet:7.5.1", "geoplanet:7.5.2", "geoplanet:7.6.0", "geoplanet:7.8.1", "geoplanet:7.9.0", "geoplanet:7.10.0", "geoplanet:8.0.0", "woeplanet:8.0.0"], "meta:indexed": "2020-08-20T19:45:31.566259", "woe:alias_ENG_V": ["Corbridge Station"], "meta:updated": "2020-08-22T02:03:28.704529", "woe:hierarchy": {"continent": 24865675, "country": 23424975, "town": 0, "planet": 1, "county": 12602153, "suburb": 0, "state": 24554868, "region": 0, "localadmin": 12696041}, "woe:timezone_id": 28350903, "woe:hash": "gcy8dnk1769q", "woe:centroid": [-2.01585, 54.966202], "geom:latitude": 54.966202, "geom:longitude": -2.01585, "geom:hash": "gcy8dnk1769q", "woe:latitude": 54.966202, "geom:centroid": [-2.01585, 54.966202], "woe:longitude": -2.01585, "woe:repo": "woeplanet-poi-gb"}, "geometry": {"coordinates": [-2.01585, 54.966202], "type": "Point"}}