{"type": "Feature", "id": 22476661, "geometry": {"type": "Point", "coordinates": [-0.19582, 51.48732]}, "properties": {"woe:id": 22476661, "woe:parent_id": 18851, "woe:name": "West Brompton Railway Station", "woe:placetype": 20, "woe:placetype_name": "POI", "woe:lang": "ENG", "iso:country": "GB", "meta:provider": ["geoplanet:7.3.1", "geoplanet:7.3.2", "geoplanet:7.4.0", "geoplanet:7.4.1", "geoplanet:7.5.1", "geoplanet:7.5.2", "geoplanet:7.6.0", "geoplanet:7.8.1", "geoplanet:7.9.0", "geoplanet:7.10.0", "geoplanet:8.0.0", "woeplanet:8.0.0"], "meta:indexed": "2020-08-20T19:45:32.736629", "woe:alias_ENG_V": ["W Brompton Station", "West Brompton Station"], "meta:updated": "2020-10-14T11:22:07.839033", "woe:hierarchy": {"continent": 24865675, "country": 23424975, "town": 0, "planet": 1, "county": 23416974, "suburb": 0, "state": 24554868, "region": 0, "localadmin": 12695812}, "woe:timezone_id": 28350903, "woe:hash": "gcpugscrmh45", "woe:centroid": [-0.19582, 51.48732], "geom:latitude": 51.48732, "geom:longitude": -0.19582, "geom:hash": "gcpugscrmh45", "woe:latitude": 51.48732, "geom:centroid": [-0.19582, 51.48732], "woe:longitude": -0.19582, "woe:repo": "woeplanet-poi-gb", "geom:area": 0.0, "woe:scale": 19}}