{"type": "Feature", "id": 23702126, "geometry": {"type": "Point", "coordinates": [-2.80845, 56.34079]}, "properties": {"woe:id": 23702126, "woe:parent_id": 35567, "woe:name": "St.Andrews University", "woe:placetype": 20, "woe:placetype_name": "POI", "woe:lang": "ENG", "iso:country": "GB", "meta:provider": ["geoplanet:7.3.1", "geoplanet:7.3.2", "geoplanet:7.4.0", "geoplanet:7.4.1", "geoplanet:7.5.1", "geoplanet:7.5.2", "geoplanet:7.6.0", "geoplanet:7.8.1", "geoplanet:7.9.0", "geoplanet:7.10.0", "geoplanet:8.0.0", "woeplanet:8.0.0"], "meta:indexed": "2020-08-20T19:45:34.296889", "woe:alias_ENG_V": ["University of St Andrews"], "meta:updated": "2020-10-14T11:21:47.815959", "woe:hierarchy": {"continent": 24865675, "country": 23424975, "town": 0, "planet": 1, "county": 12602201, "suburb": 0, "state": 12578048, "region": 0, "localadmin": 12696197}, "woe:timezone_id": 28350903, "woe:hash": "gfn080dbyk7z", "woe:centroid": [-2.80845, 56.34079], "geom:latitude": 56.34079, "geom:longitude": -2.80845, "geom:hash": "gfn080dbyk7z", "woe:latitude": 56.34079, "geom:centroid": [-2.80845, 56.34079], "woe:longitude": -2.80845, "woe:repo": "woeplanet-poi-gb", "geom:area": 0.0, "woe:scale": 19}}