{"type": "Feature", "id": 22474972, "geometry": {"type": "Point", "coordinates": [-0.22369, 51.492279]}, "properties": {"woe:id": 22474972, "woe:parent_id": 43319, "woe:name": "Hammersmith Underground Station Piccadilly and District Line", "woe:placetype": 20, "woe:placetype_name": "POI", "woe:lang": "ENG", "iso:country": "GB", "meta:provider": ["geoplanet:7.3.1", "geoplanet:7.3.2", "geoplanet:7.4.0", "geoplanet:7.4.1", "geoplanet:7.5.1", "geoplanet:7.5.2", "geoplanet:7.6.0", "geoplanet:7.8.1", "geoplanet:7.9.0", "geoplanet:7.10.0", "geoplanet:8.0.0", "woeplanet:8.0.0"], "meta:indexed": "2020-08-20T19:45:32.516273", "woe:alias_ENG_V": ["Hammersmith Underground Station Piccadilly & District Line", "Hammersmith Tube Station", "Hammersmith Tube", "Hammersmith Underground Station", "Hammersmith Underground", "Hammersmith Station Piccadilly & District Line", "Hammersmith Tube Station Piccadilly & District Line", "Hammersmith Station Piccadilly and District Line", "Hammersmith Tube Station Piccadilly and District Line", "Hammersmith Station", "Hammersmith Tube Piccadilly & District Line", "Hammersmith Tube Piccadilly and District Line", "Hammersmith Underground Piccadilly and District Line", "Hammersmith Underground Piccadilly & District Line"], "meta:updated": "2020-10-14T11:22:09.454505", "woe:hierarchy": {"continent": 24865675, "country": 23424975, "town": 0, "planet": 1, "county": 23416974, "suburb": 0, "state": 24554868, "region": 0, "localadmin": 12695809}, "woe:timezone_id": 28350903, "woe:hash": "gcpufvvh78s8", "woe:centroid": [-0.22369, 51.492279], "geom:latitude": 51.492279, "geom:longitude": -0.22369, "geom:hash": "gcpufvvh78s8", "woe:latitude": 51.492279, "geom:centroid": [-0.22369, 51.492279], "woe:longitude": -0.22369, "woe:repo": "woeplanet-poi-gb", "geom:area": 0.0, "woe:scale": 19}}