{"type": "Feature", "id": 22489517, "geometry": {"type": "Point", "coordinates": [-1.46635, 54.6464]}, "properties": {"woe:id": 22489517, "woe:parent_id": 34321, "woe:name": "Sedgefield Racecourse", "woe:placetype": 20, "woe:placetype_name": "POI", "woe:lang": "ENG", "iso:country": "GB", "meta:provider": ["geoplanet:7.3.2", "geoplanet:7.4.0", "geoplanet:7.4.1", "geoplanet:7.5.1", "geoplanet:7.5.2", "geoplanet:7.6.0", "geoplanet:7.8.1", "geoplanet:7.9.0", "geoplanet:7.10.0", "geoplanet:8.0.0", "woeplanet:8.0.0"], "meta:indexed": "2020-08-20T21:24:45.780497", "meta:updated": "2020-10-14T11:22:09.776469", "woe:hierarchy": {"continent": 24865675, "country": 23424975, "town": 0, "planet": 1, "county": 12602150, "suburb": 0, "state": 24554868, "region": 0, "localadmin": 12695932}, "woe:timezone_id": 28350903, "woe:hash": "gcwyysh4re61", "woe:centroid": [-1.46635, 54.6464], "geom:latitude": 54.6464, "geom:longitude": -1.46635, "geom:hash": "gcwyysh4re61", "woe:latitude": 54.6464, "geom:centroid": [-1.46635, 54.6464], "woe:longitude": -1.46635, "woe:repo": "woeplanet-poi-gb", "geom:area": 0.0, "woe:scale": 19}}