{"type": "Feature", "id": 22487707, "geometry": {"type": "Point", "coordinates": [-2.74771, 52.708199]}, "properties": {"woe:id": 22487707, "woe:parent_id": 34757, "woe:name": "Gay Meadow", "woe:placetype": 20, "woe:placetype_name": "POI", "woe:lang": "ENG", "iso:country": "GB", "meta:provider": ["geoplanet:7.3.1", "geoplanet:7.3.2", "geoplanet:7.4.0", "geoplanet:7.4.1", "geoplanet:7.5.1", "geoplanet:7.5.2", "geoplanet:7.6.0", "geoplanet:7.8.1", "geoplanet:7.9.0", "geoplanet:7.10.0", "geoplanet:8.0.0", "woeplanet:8.0.0"], "meta:indexed": "2020-08-20T19:45:33.382688", "meta:updated": "2020-10-14T11:22:09.807383", "woe:hierarchy": {"continent": 24865675, "country": 23424975, "town": 0, "planet": 1, "county": 12602188, "suburb": 0, "state": 24554868, "region": 0, "localadmin": 12696065}, "woe:timezone_id": 28350903, "woe:hash": "gcq5c7ppt8qy", "woe:centroid": [-2.74771, 52.708199], "geom:latitude": 52.708199, "geom:longitude": -2.74771, "geom:hash": "gcq5c7ppt8qy", "woe:latitude": 52.708199, "geom:centroid": [-2.74771, 52.708199], "woe:longitude": -2.74771, "woe:repo": "woeplanet-poi-gb", "geom:area": 0.0, "woe:scale": 19}}