{"type": "Feature", "id": 22485721, "properties": {"woe:id": 22485721, "woe:parent_id": 37522, "woe:name": "Thurnscoe Railway Station", "woe:placetype": 20, "woe:placetype_name": "POI", "woe:lang": "ENG", "iso:country": "GB", "meta:provider": ["geoplanet:7.3.1", "geoplanet:7.3.2", "geoplanet:7.4.0", "geoplanet:7.4.1", "geoplanet:7.5.1", "geoplanet:7.5.2", "geoplanet:7.6.0", "geoplanet:7.8.1", "geoplanet:7.9.0", "geoplanet:7.10.0", "geoplanet:8.0.0", "woeplanet:8.0.0"], "meta:indexed": "2020-08-20T19:45:33.267474", "woe:alias_ENG_V": ["Thurnscoe Station"], "meta:updated": "2020-08-22T02:03:29.510947", "woe:hierarchy": {"continent": 24865675, "country": 23424975, "town": 0, "planet": 1, "county": 12602196, "suburb": 0, "state": 24554868, "region": 0, "localadmin": 12695854}, "woe:timezone_id": 28350903, "woe:hash": "gcx0d5xeyp3s", "woe:centroid": [-1.3078, 53.5453], "geom:latitude": 53.5453, "geom:longitude": -1.3078, "geom:hash": "gcx0d5xeyp3s", "woe:latitude": 53.5453, "geom:centroid": [-1.3078, 53.5453], "woe:longitude": -1.3078, "woe:repo": "woeplanet-poi-gb"}, "geometry": {"coordinates": [-1.3078, 53.5453], "type": "Point"}}