{"type": "Feature", "id": 20089520, "geometry": {"type": "Point", "coordinates": [-0.18896, 51.4254]}, "properties": {"woe:id": 20089520, "woe:parent_id": 43385, "woe:name": "Haydons Road", "woe:placetype": 20, "woe:placetype_name": "POI", "woe:lang": "ENG", "iso:country": "GB", "meta:provider": ["geoplanet:7.3.1", "geoplanet:7.3.2", "geoplanet:7.4.0", "geoplanet:7.4.1", "geoplanet:7.5.1", "geoplanet:7.5.2", "geoplanet:7.6.0", "geoplanet:7.8.1", "geoplanet:7.9.0", "geoplanet:7.10.0", "geoplanet:8.0.0", "woeplanet:8.0.0"], "meta:indexed": "2020-08-20T19:45:30.875822", "meta:updated": "2020-10-14T11:22:10.661723", "woe:hierarchy": {"continent": 24865675, "country": 23424975, "town": 0, "planet": 1, "county": 23416974, "suburb": 0, "state": 24554868, "region": 0, "localadmin": 12695834}, "woe:timezone_id": 28350903, "woe:hash": "gcpue9wqsvm5", "woe:centroid": [-0.18896, 51.4254], "geom:latitude": 51.4254, "geom:longitude": -0.18896, "geom:hash": "gcpue9wqsvm5", "woe:latitude": 51.4254, "geom:centroid": [-0.18896, 51.4254], "woe:longitude": -0.18896, "woe:repo": "woeplanet-poi-gb", "geom:area": 0.0, "woe:scale": 19}}