{"type": "Feature", "id": 22473946, "properties": {"woe:id": 22473946, "woe:parent_id": 20094358, "woe:name": "Aldwych Theatre", "woe:placetype": 20, "woe:placetype_name": "POI", "woe:lang": "ENG", "iso:country": "GB", "meta:provider": ["geoplanet:7.3.1", "geoplanet:7.3.2", "geoplanet:7.4.0", "geoplanet:7.4.1", "geoplanet:7.5.1", "geoplanet:7.5.2", "geoplanet:7.6.0", "geoplanet:7.8.1", "geoplanet:7.9.0", "geoplanet:7.10.0", "geoplanet:8.0.0", "woeplanet:8.0.0"], "meta:indexed": "2020-08-20T19:45:32.376023", "meta:updated": "2020-08-22T02:03:29.088108", "woe:hierarchy": {"continent": 24865675, "country": 23424975, "town": 0, "planet": 1, "county": 23416974, "suburb": 0, "state": 24554868, "region": 0, "localadmin": 12695819}, "woe:timezone_id": 28350903, "woe:hash": "gcpvj39u97f4", "woe:centroid": [-0.11839, 51.512939], "geom:latitude": 51.512939, "geom:longitude": -0.11839, "geom:hash": "gcpvj39u97f4", "woe:latitude": 51.512939, "geom:centroid": [-0.11839, 51.512939], "woe:longitude": -0.11839, "woe:repo": "woeplanet-poi-gb"}, "geometry": {"coordinates": [-0.11839, 51.512939], "type": "Point"}}