{"type": "Feature", "id": 22464745, "properties": {"woe:id": 22464745, "woe:parent_id": 35416, "woe:name": "Southwick Park Golf Club", "woe:placetype": 20, "woe:placetype_name": "POI", "woe:lang": "ENG", "iso:country": "GB", "meta:provider": ["geoplanet:7.3.1", "geoplanet:7.3.2", "geoplanet:7.4.0", "geoplanet:7.4.1", "geoplanet:7.5.1", "geoplanet:7.5.2", "geoplanet:7.6.0", "geoplanet:7.8.1", "geoplanet:7.9.0", "geoplanet:7.10.0", "geoplanet:8.0.0", "woeplanet:8.0.0"], "meta:indexed": "2020-08-20T19:45:31.801344", "meta:updated": "2020-08-22T02:03:28.810095", "woe:alias_ENG_V": ["Southwick Park Golf Course"], "woe:hierarchy": {"continent": 24865675, "country": 23424975, "town": 0, "planet": 1, "county": 12602169, "suburb": 0, "state": 24554868, "region": 0, "localadmin": 12695968}, "woe:timezone_id": 28350903, "woe:hash": "gcp1qvpwh7mr", "woe:centroid": [-1.09913, 50.873241], "geom:latitude": 50.873241, "geom:longitude": -1.09913, "geom:hash": "gcp1qvpwh7mr", "woe:latitude": 50.873241, "geom:centroid": [-1.09913, 50.873241], "woe:longitude": -1.09913, "woe:repo": "woeplanet-poi-gb"}, "geometry": {"coordinates": [-1.09913, 50.873241], "type": "Point"}}