{"type": "Feature", "id": 22459153, "properties": {"woe:id": 22459153, "woe:parent_id": 22829, "woe:name": "Gatley Golf Club", "woe:placetype": 20, "woe:placetype_name": "POI", "woe:lang": "ENG", "iso:country": "GB", "meta:provider": ["geoplanet:7.3.1", "geoplanet:7.3.2", "geoplanet:7.4.0", "geoplanet:7.4.1", "geoplanet:7.5.1", "geoplanet:7.5.2", "geoplanet:7.6.0", "geoplanet:7.8.1", "geoplanet:7.9.0", "geoplanet:7.10.0", "geoplanet:8.0.0", "woeplanet:8.0.0"], "meta:indexed": "2020-08-20T19:45:31.474086", "meta:updated": "2020-08-22T02:03:28.667581", "woe:alias_ENG_V": ["Gatley Golf Course"], "woe:hierarchy": {"continent": 24865675, "country": 23424975, "town": 0, "planet": 1, "county": 12602158, "suburb": 0, "state": 24554868, "region": 0, "localadmin": 12695845}, "woe:timezone_id": 28350903, "woe:hash": "gcqrtjsekrww", "woe:centroid": [-2.23484, 53.380421], "geom:latitude": 53.380421, "geom:longitude": -2.23484, "geom:hash": "gcqrtjsekrww", "woe:latitude": 53.380421, "geom:centroid": [-2.23484, 53.380421], "woe:longitude": -2.23484, "woe:repo": "woeplanet-poi-gb"}, "geometry": {"coordinates": [-2.23484, 53.380421], "type": "Point"}}