{"type": "Feature", "id": 22467863, "properties": {"woe:id": 22467863, "woe:parent_id": 22619, "woe:name": "Ore Railway Station", "woe:placetype": 20, "woe:placetype_name": "POI", "woe:lang": "ENG", "iso:country": "GB", "meta:provider": ["geoplanet:7.3.1", "geoplanet:7.3.2", "geoplanet:7.4.0", "geoplanet:7.4.1", "geoplanet:7.5.1", "geoplanet:7.5.2", "geoplanet:7.6.0", "geoplanet:7.8.1", "geoplanet:7.9.0", "geoplanet:7.10.0", "geoplanet:8.0.0", "woeplanet:8.0.0"], "meta:indexed": "2020-08-20T19:45:32.042566", "woe:alias_ENG_V": ["Ore Station"], "meta:updated": "2020-08-22T02:03:28.926150", "woe:hierarchy": {"continent": 24865675, "country": 23424975, "town": 0, "planet": 1, "county": 12602167, "suburb": 0, "state": 24554868, "region": 0, "localadmin": 12695936}, "woe:timezone_id": 28350903, "woe:hash": "u103m7vnx3tp", "woe:centroid": [0.58946, 50.866451], "geom:latitude": 50.866451, "geom:longitude": 0.58946, "geom:hash": "u103m7vnx3tp", "woe:latitude": 50.866451, "geom:centroid": [0.58946, 50.866451], "woe:longitude": 0.58946, "woe:repo": "woeplanet-poi-gb"}, "geometry": {"coordinates": [0.58946, 50.866451], "type": "Point"}}