{"type": "Feature", "id": 22467039, "geometry": {"type": "Point", "coordinates": [-4.78032, 55.950241]}, "properties": {"woe:id": 22467039, "woe:parent_id": 21824, "woe:name": "Greenock Golf Course", "woe:placetype": 20, "woe:placetype_name": "POI", "woe:lang": "ENG", "iso:country": "GB", "meta:provider": ["geoplanet:7.3.1", "geoplanet:7.3.2", "geoplanet:7.4.0", "geoplanet:7.4.1", "geoplanet:7.5.1", "geoplanet:7.5.2", "geoplanet:7.6.0", "geoplanet:7.8.1", "geoplanet:7.9.0", "geoplanet:7.10.0", "geoplanet:8.0.0", "woeplanet:8.0.0"], "meta:indexed": "2020-08-20T19:45:31.988427", "meta:updated": "2020-10-14T11:22:08.505428", "woe:hierarchy": {"continent": 24865675, "country": 23424975, "town": 0, "planet": 1, "county": 12602207, "suburb": 0, "state": 12578048, "region": 0, "localadmin": 12696200}, "woe:timezone_id": 28350903, "woe:hash": "gcuw71rjf2z5", "woe:centroid": [-4.78032, 55.950241], "geom:latitude": 55.950241, "geom:longitude": -4.78032, "geom:hash": "gcuw71rjf2z5", "woe:latitude": 55.950241, "geom:centroid": [-4.78032, 55.950241], "woe:longitude": -4.78032, "woe:repo": "woeplanet-poi-gb", "geom:area": 0.0, "woe:scale": 19}}