{"type": "Feature", "id": 23702157, "properties": {"woe:id": 23702157, "woe:parent_id": 43984, "woe:name": "Lucy Cavendish College", "woe:placetype": 20, "woe:placetype_name": "POI", "woe:lang": "ENG", "iso:country": "GB", "meta:provider": ["geoplanet:7.3.1", "geoplanet:7.3.2", "geoplanet:7.4.0", "geoplanet:7.4.1", "geoplanet:7.5.1", "geoplanet:7.5.2", "geoplanet:7.6.0", "geoplanet:7.8.1", "geoplanet:7.9.0", "geoplanet:7.10.0", "geoplanet:8.0.0", "woeplanet:8.0.0"], "meta:indexed": "2020-08-20T19:45:34.325901", "woe:alias_ENG_V": ["Lucy Cavendish"], "meta:updated": "2020-08-22T02:03:57.980850", "woe:hierarchy": {"continent": 24865675, "country": 23424975, "town": 0, "planet": 1, "county": 12602140, "suburb": 0, "state": 24554868, "region": 0, "localadmin": 12695882}, "woe:timezone_id": 28350903, "woe:hash": "u12142zg8jrm", "woe:centroid": [0.10953, 52.211781], "geom:latitude": 52.211781, "geom:longitude": 0.10953, "geom:hash": "u12142zg8jrm", "woe:latitude": 52.211781, "geom:centroid": [0.10953, 52.211781], "woe:longitude": 0.10953, "woe:repo": "woeplanet-poi-gb"}, "geometry": {"coordinates": [0.10953, 52.211781], "type": "Point"}}