{"type": "Feature", "id": 22475954, "geometry": {"type": "Point", "coordinates": [-0.14647, 51.523651]}, "properties": {"woe:id": 22475954, "woe:parent_id": 35723, "woe:name": "Regent's Park Underground Station", "woe:placetype": 20, "woe:placetype_name": "POI", "woe:lang": "ENG", "iso:country": "GB", "meta:provider": ["geoplanet:7.3.1", "geoplanet:7.3.2", "geoplanet:7.4.0", "geoplanet:7.4.1", "geoplanet:7.5.1", "geoplanet:7.5.2", "geoplanet:7.6.0", "geoplanet:7.8.1", "geoplanet:7.9.0", "geoplanet:7.10.0", "geoplanet:8.0.0", "woeplanet:8.0.0"], "meta:indexed": "2020-08-20T19:45:32.648149", "woe:alias_ENG_V": ["Regent's Park Tube Station", "Regents Park Station", "Regents Park Tube Station", "Regents Park Underground Station", "Regent's Park Tube", "Regents Park Tube", "Regent's Park Underground", "Regents Park Underground", "Regent's Park Station"], "meta:updated": "2020-10-14T11:22:09.209738", "woe:hierarchy": {"continent": 24865675, "country": 23424975, "town": 0, "planet": 1, "county": 23416974, "suburb": 0, "state": 24554868, "region": 0, "localadmin": 12695819}, "woe:timezone_id": 28350903, "woe:hash": "gcpvhet7508n", "woe:centroid": [-0.14647, 51.523651], "geom:latitude": 51.523651, "geom:longitude": -0.14647, "geom:hash": "gcpvhet7508n", "woe:latitude": 51.523651, "geom:centroid": [-0.14647, 51.523651], "woe:longitude": -0.14647, "woe:repo": "woeplanet-poi-gb", "geom:area": 0.0, "woe:scale": 19}}