{"type": "Feature", "id": 22474786, "properties": {"woe:id": 22474786, "woe:parent_id": 17581, "woe:name": "Old Royal Observatory", "woe:placetype": 20, "woe:placetype_name": "POI", "woe:lang": "ENG", "iso:country": "GB", "meta:provider": ["geoplanet:7.3.1", "geoplanet:7.3.2", "geoplanet:7.4.0", "geoplanet:7.4.1", "geoplanet:7.5.1", "geoplanet:7.5.2", "geoplanet:7.6.0", "geoplanet:7.8.1", "geoplanet:7.9.0", "geoplanet:7.10.0", "geoplanet:8.0.0", "woeplanet:8.0.0"], "meta:indexed": "2020-08-20T19:45:32.493025", "woe:alias_ENG_V": ["Flamsteed House Museum"], "meta:updated": "2020-08-22T02:03:29.149359", "woe:alias_FIN_V": ["Vanha Kuninkaallinen Observatorio"], "woe:alias_DUT_V": ["Koninklijk Observatorium"], "woe:alias_HUN_V": ["Greenwichi Obszervatorium", "Greenwichi Obszervat\u00f3rium"], "woe:alias_POR_V": ["Antigo Observat\u00f3rio Real", "Antigo Observatorio Real"], "woe:alias_SPA_Q": ["Antiguo Observatorio Real"], "woe:alias_GER_V": ["K\u00f6nigl. Observatorium Von Greenwich", "Konigl. Observatorium Von Greenwich"], "woe:alias_FRE_V": ["Observatoire Royal"], "woe:alias_POL_V": ["Krolewskie Obserwatorium", "Kr\u00f3lewskie Obserwatorium"], "woe:alias_ITA_V": ["Museo Old Royal Observatory"], "woe:alias_CZE_V": ["Kr\u00e1lovsk\u00e1 Greenwichsk\u00e1 Observato\u0159", "Kralovska Greenwichska Observator"], "woe:alias_DAN_V": ["Gammel Kongelig Observatory"], "woe:alias_UNK_V": ["\u03a0\u03b1\u03bb\u03b1\u03b9\u03bf \u0392\u03b1\u03c3\u03b9\u03bb\u03b9\u03ba\u03bf \u03a0\u03b1\u03c1\u03b1\u03c4\u03b7\u03c1\u03c4\u03b7\u03c1\u03b9\u03bf"], "woe:alias_SWE_Q": ["Gamla Kungliga Observatoriet"], "woe:alias_UNK_Q": ["Kralovske Observatorium V Greenwich", "\u0421\u0442\u0430\u0440\u0430\u044f \u041a\u043e\u0440\u043e\u043b\u0435\u0432\u0441\u043a\u0430\u044f \u041e\u0431\u0441\u0435\u0440\u0432\u0430\u0442\u043e\u0440\u0438\u044f"], "woe:alias_NOR_V": ["Det Gamle Kongelige Observatorie"], "woe:hierarchy": {"continent": 24865675, "country": 23424975, "town": 0, "planet": 1, "county": 23416974, "suburb": 0, "state": 24554868, "region": 0, "localadmin": 12695828}, "woe:timezone_id": 28350903, "woe:hash": "gcpuzgpxux69", "woe:centroid": [-0.00049, 51.47781], "geom:latitude": 51.47781, "geom:longitude": -0.00049, "geom:hash": "gcpuzgpxux69", "woe:latitude": 51.47781, "geom:centroid": [-0.00049, 51.47781], "woe:longitude": -0.00049, "woe:repo": "woeplanet-poi-gb"}, "geometry": {"coordinates": [-0.00049, 51.47781], "type": "Point"}}