{"type": "Feature", "id": 22468229, "properties": {"woe:id": 22468229, "woe:parent_id": 28924, "woe:name": "Hardcastle Crags", "woe:placetype": 20, "woe:placetype_name": "POI", "woe:lang": "ENG", "iso:country": "GB", "meta:provider": ["geoplanet:7.3.2", "geoplanet:7.4.0", "geoplanet:7.4.1", "geoplanet:7.5.1", "geoplanet:7.5.2", "geoplanet:7.6.0", "geoplanet:7.8.1", "geoplanet:7.9.0", "geoplanet:7.10.0", "geoplanet:8.0.0", "woeplanet:8.0.0"], "meta:indexed": "2020-08-20T21:24:44.084770", "meta:updated": "2020-08-22T02:03:28.937714", "woe:hierarchy": {"continent": 24865675, "country": 23424975, "town": 0, "planet": 1, "county": 12602197, "suburb": 0, "state": 24554868, "region": 0, "localadmin": 12695871}, "woe:timezone_id": 28350903, "woe:hash": "gcw9f43kd5c7", "woe:centroid": [-2.01968, 53.75827], "geom:latitude": 53.75827, "geom:longitude": -2.01968, "geom:hash": "gcw9f43kd5c7", "woe:latitude": 53.75827, "geom:centroid": [-2.01968, 53.75827], "woe:longitude": -2.01968, "woe:repo": "woeplanet-poi-gb"}, "geometry": {"coordinates": [-2.01968, 53.75827], "type": "Point"}}