{"type": "Feature", "id": 22484780, "geometry": {"type": "Point", "coordinates": [-0.93694, 51.4519]}, "properties": {"woe:id": 22484780, "woe:parent_id": 40989, "woe:name": "Palmer Park Stadium", "woe:placetype": 20, "woe:placetype_name": "POI", "woe:lang": "ENG", "iso:country": "GB", "meta:provider": ["geoplanet:7.3.1", "geoplanet:7.3.2", "geoplanet:7.4.0", "geoplanet:7.4.1", "geoplanet:7.5.1", "geoplanet:7.5.2", "geoplanet:7.6.0", "geoplanet:7.8.1", "geoplanet:7.9.0", "geoplanet:7.10.0", "geoplanet:8.0.0", "woeplanet:8.0.0"], "meta:indexed": "2020-08-20T19:45:33.211224", "meta:updated": "2020-10-14T11:22:09.292298", "woe:hierarchy": {"continent": 24865675, "country": 23424975, "town": 0, "planet": 1, "county": 26821262, "suburb": 0, "state": 24554868, "region": 0, "localadmin": 12696166}, "woe:timezone_id": 28350903, "woe:hash": "gcpkdwt9p9qf", "woe:centroid": [-0.93694, 51.4519], "geom:latitude": 51.4519, "geom:longitude": -0.93694, "geom:hash": "gcpkdwt9p9qf", "woe:latitude": 51.4519, "geom:centroid": [-0.93694, 51.4519], "woe:longitude": -0.93694, "woe:repo": "woeplanet-poi-gb", "geom:area": 0.0, "woe:scale": 19}}