{"type": "Feature", "id": 22472983, "geometry": {"type": "Point", "coordinates": [-0.91043, 51.02697]}, "properties": {"woe:id": 22472983, "woe:parent_id": 20311, "woe:name": "Peterfield Golf Club", "woe:placetype": 20, "woe:placetype_name": "POI", "woe:lang": "ENG", "iso:country": "GB", "meta:provider": ["geoplanet:7.3.1", "geoplanet:7.3.2", "geoplanet:7.4.0", "geoplanet:7.4.1", "geoplanet:7.5.1", "geoplanet:7.5.2", "geoplanet:7.6.0", "geoplanet:7.8.1", "geoplanet:7.9.0", "geoplanet:7.10.0", "geoplanet:8.0.0", "woeplanet:8.0.0"], "meta:indexed": "2020-08-20T19:45:32.308326", "meta:updated": "2020-10-14T11:22:08.889714", "woe:alias_ENG_V": ["Petersfield Golf Course (new)", "Petersfield Golf Course"], "woe:hierarchy": {"continent": 24865675, "country": 23424975, "town": 0, "planet": 1, "county": 12602169, "suburb": 0, "state": 24554868, "region": 0, "localadmin": 12695959}, "woe:timezone_id": 28350903, "woe:hash": "gcp6731j9kwh", "woe:centroid": [-0.91043, 51.02697], "geom:latitude": 51.02697, "geom:longitude": -0.91043, "geom:hash": "gcp6731j9kwh", "woe:latitude": 51.02697, "geom:centroid": [-0.91043, 51.02697], "woe:longitude": -0.91043, "woe:repo": "woeplanet-poi-gb", "geom:area": 0.0, "woe:scale": 19}}