{"type": "Feature", "id": 22475985, "geometry": {"type": "Point", "coordinates": [-0.05186, 51.50079]}, "properties": {"woe:id": 22475985, "woe:parent_id": 20089476, "woe:name": "Rotherhithe Underground Station", "woe:placetype": 20, "woe:placetype_name": "POI", "woe:lang": "ENG", "iso:country": "GB", "meta:provider": ["geoplanet:7.3.1", "geoplanet:7.3.2", "geoplanet:7.4.0", "geoplanet:7.4.1", "geoplanet:7.5.1", "geoplanet:7.5.2", "geoplanet:7.6.0", "geoplanet:7.8.1", "geoplanet:7.9.0", "geoplanet:7.10.0", "geoplanet:8.0.0", "woeplanet:8.0.0"], "meta:indexed": "2020-08-20T19:45:32.648917", "woe:alias_ENG_V": ["Rotherhithe Railway Station", "Rotherhithe Tube", "Rotherhithe Underground", "Rotherhithe Station", "Rotherhithe Tube Station"], "meta:updated": "2020-10-14T11:22:09.213598", "woe:hierarchy": {"continent": 24865675, "country": 23424975, "town": 0, "planet": 1, "county": 23416974, "suburb": 0, "state": 24554868, "region": 0, "localadmin": 12695816}, "woe:timezone_id": 28350903, "woe:hash": "gcpuyz6jze46", "woe:centroid": [-0.05186, 51.50079], "geom:latitude": 51.50079, "geom:longitude": -0.05186, "geom:hash": "gcpuyz6jze46", "woe:latitude": 51.50079, "geom:centroid": [-0.05186, 51.50079], "woe:longitude": -0.05186, "woe:repo": "woeplanet-poi-gb", "geom:area": 0.0, "woe:scale": 19}}