{"type": "Feature", "id": 22493119, "geometry": {"type": "Point", "coordinates": [-2.62148, 53.434238]}, "properties": {"woe:id": 22493119, "woe:parent_id": 12696172, "woe:name": "Alder Root Golf Club", "woe:placetype": 20, "woe:placetype_name": "POI", "woe:lang": "ENG", "iso:country": "GB", "meta:provider": ["geoplanet:7.3.1", "geoplanet:7.3.2", "geoplanet:7.4.0", "geoplanet:7.4.1", "geoplanet:7.5.1", "geoplanet:7.5.2", "geoplanet:7.6.0", "geoplanet:7.8.1", "geoplanet:7.9.0", "geoplanet:7.10.0", "geoplanet:8.0.0", "woeplanet:8.0.0"], "meta:indexed": "2020-08-20T19:45:33.669770", "meta:updated": "2020-10-14T11:22:08.071873", "woe:alias_ENG_V": ["Alder Root Golf Course"], "woe:hierarchy": {"continent": 24865675, "country": 23424975, "town": 0, "planet": 1, "county": 12602157, "suburb": 0, "state": 24554868, "region": 0, "localadmin": 12696172}, "woe:timezone_id": 28350903, "woe:hash": "gcqpur7hgpfv", "woe:centroid": [-2.62148, 53.434238], "geom:latitude": 53.434238, "geom:longitude": -2.62148, "geom:hash": "gcqpur7hgpfv", "woe:latitude": 53.434238, "geom:centroid": [-2.62148, 53.434238], "woe:longitude": -2.62148, "woe:repo": "woeplanet-poi-gb", "geom:area": 0.0, "woe:scale": 19}}