{"type": "Feature", "id": 22483794, "properties": {"woe:id": 22483794, "woe:parent_id": 38052, "woe:name": "Trehafod Railway Station", "woe:placetype": 20, "woe:placetype_name": "POI", "woe:lang": "ENG", "iso:country": "GB", "meta:provider": ["geoplanet:7.3.1", "geoplanet:7.3.2", "geoplanet:7.4.0", "geoplanet:7.4.1", "geoplanet:7.5.1", "geoplanet:7.5.2", "geoplanet:7.6.0", "geoplanet:7.8.1", "geoplanet:7.9.0", "geoplanet:7.10.0", "geoplanet:8.0.0", "woeplanet:8.0.0"], "meta:indexed": "2020-08-20T19:45:33.152847", "woe:alias_ENG_V": ["Trehafod Station"], "meta:updated": "2020-08-22T02:03:29.458296", "woe:hierarchy": {"continent": 24865675, "country": 23424975, "town": 0, "planet": 1, "county": 12602228, "suburb": 0, "state": 12578049, "region": 0, "localadmin": 12696115}, "woe:timezone_id": 28350903, "woe:hash": "gcjte562hrvh", "woe:centroid": [-3.38051, 51.609692], "geom:latitude": 51.609692, "geom:longitude": -3.38051, "geom:hash": "gcjte562hrvh", "woe:latitude": 51.609692, "geom:centroid": [-3.38051, 51.609692], "woe:longitude": -3.38051, "woe:repo": "woeplanet-poi-gb"}, "geometry": {"coordinates": [-3.38051, 51.609692], "type": "Point"}}