{"type": "Feature", "id": 22486930, "geometry": {"type": "Point", "coordinates": [-2.36461, 54.28294]}, "properties": {"woe:id": 22486930, "woe:parent_id": 17070, "woe:name": "Dent Railway Station", "woe:placetype": 20, "woe:placetype_name": "POI", "woe:lang": "ENG", "iso:country": "GB", "meta:provider": ["geoplanet:7.3.1", "geoplanet:7.3.2", "geoplanet:7.4.0", "geoplanet:7.4.1", "geoplanet:7.5.1", "geoplanet:7.5.2", "geoplanet:7.6.0", "geoplanet:7.8.1", "geoplanet:7.9.0", "geoplanet:7.10.0", "geoplanet:8.0.0", "woeplanet:8.0.0"], "meta:indexed": "2020-08-20T19:45:33.338838", "woe:alias_ENG_V": ["Dent Station"], "meta:updated": "2020-10-14T11:22:09.956045", "woe:hierarchy": {"continent": 24865675, "country": 23424975, "town": 0, "planet": 1, "county": 12602148, "suburb": 0, "state": 24554868, "region": 0, "localadmin": 12695905}, "woe:timezone_id": 28350903, "woe:hash": "gcwkf1yjh96y", "woe:centroid": [-2.36461, 54.28294], "geom:latitude": 54.28294, "geom:longitude": -2.36461, "geom:hash": "gcwkf1yjh96y", "woe:latitude": 54.28294, "geom:centroid": [-2.36461, 54.28294], "woe:longitude": -2.36461, "woe:repo": "woeplanet-poi-gb", "geom:area": 0.0, "woe:scale": 19}}