{"type": "Feature", "id": 22464785, "geometry": {"type": "Point", "coordinates": [-0.74296, 51.302399]}, "properties": {"woe:id": 22464785, "woe:parent_id": 20646, "woe:name": "Farnborough North Railway Station", "woe:placetype": 20, "woe:placetype_name": "POI", "woe:lang": "ENG", "iso:country": "GB", "meta:provider": ["geoplanet:7.3.1", "geoplanet:7.3.2", "geoplanet:7.4.0", "geoplanet:7.4.1", "geoplanet:7.5.1", "geoplanet:7.5.2", "geoplanet:7.6.0", "geoplanet:7.8.1", "geoplanet:7.9.0", "geoplanet:7.10.0", "geoplanet:8.0.0", "woeplanet:8.0.0"], "meta:indexed": "2020-08-20T19:45:31.806198", "woe:alias_ENG_V": ["Farnborough North Station"], "meta:updated": "2020-10-14T11:22:08.064075", "woe:hierarchy": {"continent": 24865675, "country": 23424975, "town": 0, "planet": 1, "county": 12602169, "suburb": 0, "state": 24554868, "region": 0, "localadmin": 12695966}, "woe:timezone_id": 28350903, "woe:hash": "gcp7z56fpu2f", "woe:centroid": [-0.74296, 51.302399], "geom:latitude": 51.302399, "geom:longitude": -0.74296, "geom:hash": "gcp7z56fpu2f", "woe:latitude": 51.302399, "geom:centroid": [-0.74296, 51.302399], "woe:longitude": -0.74296, "woe:repo": "woeplanet-poi-gb", "geom:area": 0.0, "woe:scale": 19}}