{"type": "Feature", "id": 23367464, "properties": {"woe:id": 23367464, "woe:parent_id": 18612, "woe:name": "Strathclyde Homes Stadium", "woe:placetype": 20, "woe:placetype_name": "POI", "woe:lang": "ENG", "iso:country": "GB", "meta:provider": ["geoplanet:7.3.1", "geoplanet:7.3.2", "geoplanet:7.4.0", "geoplanet:7.4.1", "geoplanet:7.5.1", "geoplanet:7.5.2", "geoplanet:7.6.0", "geoplanet:7.8.1", "geoplanet:7.9.0", "geoplanet:7.10.0", "geoplanet:8.0.0", "woeplanet:8.0.0"], "meta:indexed": "2020-08-20T19:45:33.841699", "meta:updated": "2020-08-22T02:03:58.125834", "woe:alias_ENG_V": ["Dumbarton Football Club"], "woe:hierarchy": {"continent": 24865675, "country": 23424975, "town": 0, "planet": 1, "county": 12602207, "suburb": 0, "state": 12578048, "region": 0, "localadmin": 12696188}, "woe:timezone_id": 28350903, "woe:hash": "gcuy0pq2y9xc", "woe:centroid": [-4.56144, 55.9384], "geom:latitude": 55.9384, "geom:longitude": -4.56144, "geom:hash": "gcuy0pq2y9xc", "woe:latitude": 55.9384, "geom:centroid": [-4.56144, 55.9384], "woe:longitude": -4.56144, "woe:repo": "woeplanet-poi-gb"}, "geometry": {"coordinates": [-4.56144, 55.9384], "type": "Point"}}