{"type": "Feature", "id": 22477857, "geometry": {"type": "Point", "coordinates": [-2.13024, 53.457119]}, "properties": {"woe:id": 22477857, "woe:parent_id": 11413, "woe:name": "Denton Railway Station", "woe:placetype": 20, "woe:placetype_name": "POI", "woe:lang": "ENG", "iso:country": "GB", "meta:provider": ["geoplanet:7.3.1", "geoplanet:7.3.2", "geoplanet:7.4.0", "geoplanet:7.4.1", "geoplanet:7.5.1", "geoplanet:7.5.2", "geoplanet:7.6.0", "geoplanet:7.8.1", "geoplanet:7.9.0", "geoplanet:7.10.0", "geoplanet:8.0.0", "woeplanet:8.0.0"], "meta:indexed": "2020-08-20T19:45:32.829004", "woe:alias_ENG_V": ["Denton Station"], "meta:updated": "2020-10-14T11:22:09.553510", "woe:hierarchy": {"continent": 24865675, "country": 23424975, "town": 0, "planet": 1, "county": 12602158, "suburb": 0, "state": 24554868, "region": 0, "localadmin": 12695846}, "woe:timezone_id": 28350903, "woe:hash": "gcw2pe8f3c1z", "woe:centroid": [-2.13024, 53.457119], "geom:latitude": 53.457119, "geom:longitude": -2.13024, "geom:hash": "gcw2pe8f3c1z", "woe:latitude": 53.457119, "geom:centroid": [-2.13024, 53.457119], "woe:longitude": -2.13024, "woe:repo": "woeplanet-poi-gb", "geom:area": 0.0, "woe:scale": 19}}