{"type": "Feature", "id": 22473149, "geometry": {"type": "Point", "coordinates": [-2.96639, 53.4389]}, "properties": {"woe:id": 22473149, "woe:parent_id": 13250, "woe:name": "Goodison Park", "woe:placetype": 20, "woe:placetype_name": "POI", "woe:lang": "ENG", "iso:country": "GB", "meta:provider": ["geoplanet:7.3.2", "geoplanet:7.4.0", "geoplanet:7.4.1", "geoplanet:7.5.1", "geoplanet:7.5.2", "geoplanet:7.6.0", "geoplanet:7.8.1", "geoplanet:7.9.0", "geoplanet:7.10.0", "geoplanet:8.0.0", "woeplanet:8.0.0"], "meta:indexed": "2020-08-20T21:24:44.376627", "meta:updated": "2020-10-14T11:22:08.156715", "woe:alias_ENG_V": ["Everton Football Club"], "woe:hierarchy": {"continent": 24865675, "country": 23424975, "town": 0, "planet": 1, "county": 12602161, "suburb": 0, "state": 24554868, "region": 0, "localadmin": 12695850}, "woe:timezone_id": 28350903, "woe:hash": "gctbh2rbnhgr", "woe:centroid": [-2.96639, 53.4389], "geom:latitude": 53.4389, "geom:longitude": -2.96639, "geom:hash": "gctbh2rbnhgr", "woe:latitude": 53.4389, "geom:centroid": [-2.96639, 53.4389], "woe:longitude": -2.96639, "woe:repo": "woeplanet-poi-gb", "geom:area": 0.0, "woe:scale": 19}}