{"type": "Feature", "id": 22476322, "geometry": {"type": "Point", "coordinates": [-0.04684, 51.521801]}, "properties": {"woe:id": 22476322, "woe:parent_id": 20089368, "woe:name": "Stepney Green Underground Station", "woe:placetype": 20, "woe:placetype_name": "POI", "woe:lang": "ENG", "iso:country": "GB", "meta:provider": ["geoplanet:7.3.1", "geoplanet:7.3.2", "geoplanet:7.4.0", "geoplanet:7.4.1", "geoplanet:7.5.1", "geoplanet:7.5.2", "geoplanet:7.6.0", "geoplanet:7.8.1", "geoplanet:7.9.0", "geoplanet:7.10.0", "geoplanet:8.0.0", "woeplanet:8.0.0"], "meta:indexed": "2020-08-20T19:45:32.691109", "woe:alias_ENG_V": ["Stepney Green Tube", "Stepney Green Underground", "Stepney Green Station", "Stepney Green Tube Station"], "meta:updated": "2020-10-14T11:22:07.768971", "woe:hierarchy": {"continent": 24865675, "country": 23424975, "town": 0, "planet": 1, "county": 23416974, "suburb": 0, "state": 24554868, "region": 0, "localadmin": 12695817}, "woe:timezone_id": 28350903, "woe:hash": "gcpvngmbhxcd", "woe:centroid": [-0.04684, 51.521801], "geom:latitude": 51.521801, "geom:longitude": -0.04684, "geom:hash": "gcpvngmbhxcd", "woe:latitude": 51.521801, "geom:centroid": [-0.04684, 51.521801], "woe:longitude": -0.04684, "woe:repo": "woeplanet-poi-gb", "geom:area": 0.0, "woe:scale": 19}}