{"type": "Feature", "id": 22458720, "properties": {"woe:id": 22458720, "woe:parent_id": 18756, "woe:name": "Carlisle Racecourse", "woe:placetype": 20, "woe:placetype_name": "POI", "woe:lang": "ENG", "iso:country": "GB", "meta:provider": ["geoplanet:7.3.2", "geoplanet:7.4.0", "geoplanet:7.4.1", "geoplanet:7.5.1", "geoplanet:7.5.2", "geoplanet:7.6.0", "geoplanet:7.8.1", "geoplanet:7.9.0", "geoplanet:7.10.0", "geoplanet:8.0.0", "woeplanet:8.0.0"], "meta:indexed": "2020-08-20T21:24:43.447260", "meta:updated": "2020-08-22T02:03:58.006943", "woe:hierarchy": {"continent": 24865675, "country": 23424975, "town": 0, "planet": 1, "county": 12602148, "suburb": 0, "state": 24554868, "region": 0, "localadmin": 12695902}, "woe:timezone_id": 28350903, "woe:hash": "gcvbj70j06nd", "woe:centroid": [-2.93333, 54.861099], "geom:latitude": 54.861099, "geom:longitude": -2.93333, "geom:hash": "gcvbj70j06nd", "woe:latitude": 54.861099, "geom:centroid": [-2.93333, 54.861099], "woe:longitude": -2.93333, "woe:repo": "woeplanet-poi-gb"}, "geometry": {"coordinates": [-2.93333, 54.861099], "type": "Point"}}