{"type": "Feature", "id": 22453672, "geometry": {"type": "Point", "coordinates": [-1.48235, 53.024101]}, "properties": {"woe:id": 22453672, "woe:parent_id": 12329, "woe:name": "Belper Railway Station", "woe:placetype": 20, "woe:placetype_name": "POI", "woe:lang": "ENG", "iso:country": "GB", "meta:provider": ["geoplanet:7.3.1", "geoplanet:7.3.2", "geoplanet:7.4.0", "geoplanet:7.4.1", "geoplanet:7.5.1", "geoplanet:7.5.2", "geoplanet:7.6.0", "geoplanet:7.8.1", "geoplanet:7.9.0", "geoplanet:7.10.0", "geoplanet:8.0.0", "woeplanet:8.0.0"], "meta:indexed": "2020-08-20T19:45:31.157054", "woe:alias_ENG_V": ["Belper Station"], "meta:updated": "2020-10-14T11:22:08.467618", "woe:hierarchy": {"continent": 24865675, "country": 23424975, "town": 0, "planet": 1, "county": 12602143, "suburb": 0, "state": 24554868, "region": 0, "localadmin": 12695906}, "woe:timezone_id": 28350903, "woe:hash": "gcqvwk8xf8zd", "woe:centroid": [-1.48235, 53.024101], "geom:latitude": 53.024101, "geom:longitude": -1.48235, "geom:hash": "gcqvwk8xf8zd", "woe:latitude": 53.024101, "geom:centroid": [-1.48235, 53.024101], "woe:longitude": -1.48235, "woe:repo": "woeplanet-poi-gb", "geom:area": 0.0, "woe:scale": 19}}