{"type": "Feature", "id": 22473786, "properties": {"woe:id": 22473786, "woe:parent_id": 27130, "woe:name": "Llanwrda Railway Station", "woe:placetype": 20, "woe:placetype_name": "POI", "woe:lang": "UNK", "iso:country": "GB", "meta:provider": ["geoplanet:7.3.1", "geoplanet:7.3.2", "geoplanet:7.4.0", "geoplanet:7.4.1", "geoplanet:7.5.1", "geoplanet:7.5.2", "geoplanet:7.6.0", "geoplanet:7.8.1", "geoplanet:7.9.0", "geoplanet:7.10.0", "geoplanet:8.0.0", "woeplanet:8.0.0"], "meta:indexed": "2020-08-20T19:45:32.360482", "woe:alias_UNK_V": ["Llanwrda Station"], "meta:updated": "2020-08-22T02:03:29.080756", "woe:hierarchy": {"continent": 24865675, "country": 23424975, "town": 0, "planet": 1, "county": 12602216, "suburb": 0, "state": 12578049, "region": 0, "localadmin": 12696118}, "woe:timezone_id": 28350903, "woe:hash": "gcjpxgkrscdx", "woe:centroid": [-3.87213, 51.962509], "geom:latitude": 51.962509, "geom:longitude": -3.87213, "geom:hash": "gcjpxgkrscdx", "woe:latitude": 51.962509, "geom:centroid": [-3.87213, 51.962509], "woe:longitude": -3.87213, "woe:repo": "woeplanet-poi-gb"}, "geometry": {"coordinates": [-3.87213, 51.962509], "type": "Point"}}