{"type": "Feature", "id": 22463587, "properties": {"woe:id": 22463587, "woe:parent_id": 30291, "woe:name": "Eugene Cross Park", "woe:placetype": 20, "woe:placetype_name": "POI", "woe:lang": "ENG", "iso:country": "GB", "meta:provider": ["geoplanet:7.3.2", "geoplanet:7.4.0", "geoplanet:7.4.1", "geoplanet:7.5.1", "geoplanet:7.5.2", "geoplanet:7.6.0", "geoplanet:7.8.1", "geoplanet:7.9.0", "geoplanet:7.10.0", "geoplanet:8.0.0", "woeplanet:8.0.0"], "meta:indexed": "2020-08-20T21:24:43.745117", "meta:updated": "2020-08-22T02:03:58.031474", "woe:hierarchy": {"continent": 24865675, "country": 23424975, "town": 0, "planet": 1, "county": 12602212, "suburb": 0, "state": 12578049, "region": 0, "localadmin": 12696120}, "woe:timezone_id": 28350903, "woe:hash": "gcjwx51pjxy3", "woe:centroid": [-3.20639, 51.785301], "geom:latitude": 51.785301, "geom:longitude": -3.20639, "geom:hash": "gcjwx51pjxy3", "woe:latitude": 51.785301, "geom:centroid": [-3.20639, 51.785301], "woe:longitude": -3.20639, "woe:repo": "woeplanet-poi-gb"}, "geometry": {"coordinates": [-3.20639, 51.785301], "type": "Point"}}