{"type": "Feature", "id": 22486609, "geometry": {"type": "Point", "coordinates": [-4.78424, 55.633678]}, "properties": {"woe:id": 22486609, "woe:parent_id": 33909, "woe:name": "Saltcoats Railway Station", "woe:placetype": 20, "woe:placetype_name": "POI", "woe:lang": "ENG", "iso:country": "GB", "meta:provider": ["geoplanet:7.3.1", "geoplanet:7.3.2", "geoplanet:7.4.0", "geoplanet:7.4.1", "geoplanet:7.5.1", "geoplanet:7.5.2", "geoplanet:7.6.0", "geoplanet:7.8.1", "geoplanet:7.9.0", "geoplanet:7.10.0", "geoplanet:8.0.0", "woeplanet:8.0.0"], "meta:indexed": "2020-08-20T19:45:33.319331", "woe:alias_ENG_V": ["Saltcoats Station"], "meta:updated": "2020-10-14T11:22:08.866742", "woe:hierarchy": {"continent": 24865675, "country": 23424975, "town": 0, "planet": 1, "county": 12602207, "suburb": 0, "state": 12578048, "region": 0, "localadmin": 12696203}, "woe:timezone_id": 28350903, "woe:hash": "gcus7pu1xjk0", "woe:centroid": [-4.78424, 55.633678], "geom:latitude": 55.633678, "geom:longitude": -4.78424, "geom:hash": "gcus7pu1xjk0", "woe:latitude": 55.633678, "geom:centroid": [-4.78424, 55.633678], "woe:longitude": -4.78424, "woe:repo": "woeplanet-poi-gb", "geom:area": 0.0, "woe:scale": 19}}