{"type": "Feature", "id": 22477182, "geometry": {"type": "Point", "coordinates": [-2.64063, 51.737911]}, "properties": {"woe:id": 22477182, "woe:parent_id": 35589, "woe:name": "St Briavel's Castle", "woe:placetype": 20, "woe:placetype_name": "POI", "woe:lang": "ENG", "iso:country": "GB", "meta:provider": ["geoplanet:7.3.1", "geoplanet:7.3.2", "geoplanet:7.4.0", "geoplanet:7.4.1", "geoplanet:7.5.1", "geoplanet:7.5.2", "geoplanet:7.6.0", "geoplanet:7.8.1", "geoplanet:7.9.0", "geoplanet:7.10.0", "geoplanet:8.0.0", "woeplanet:8.0.0"], "meta:indexed": "2020-08-20T19:45:32.788098", "woe:alias_ENG_V": ["St Briavels Castle"], "meta:updated": "2020-10-14T11:22:08.416699", "woe:hierarchy": {"continent": 24865675, "country": 23424975, "town": 0, "planet": 1, "county": 12602184, "suburb": 0, "state": 24554868, "region": 0, "localadmin": 12695954}, "woe:timezone_id": 28350903, "woe:hash": "gcnn7ft5hves", "woe:centroid": [-2.64063, 51.737911], "geom:latitude": 51.737911, "geom:longitude": -2.64063, "geom:hash": "gcnn7ft5hves", "woe:latitude": 51.737911, "geom:centroid": [-2.64063, 51.737911], "woe:longitude": -2.64063, "woe:repo": "woeplanet-poi-gb", "geom:area": 0.0, "woe:scale": 19}}