{"type": "Feature", "id": 22462720, "properties": {"woe:id": 22462720, "woe:parent_id": 18382, "woe:name": "Dover Western Docks Railway Station", "woe:placetype": 20, "woe:placetype_name": "POI", "woe:lang": "ENG", "iso:country": "GB", "meta:provider": ["geoplanet:7.3.1", "geoplanet:7.3.2", "geoplanet:7.4.0", "geoplanet:7.4.1", "geoplanet:7.5.1", "geoplanet:7.5.2", "geoplanet:7.6.0", "geoplanet:7.8.1", "geoplanet:7.9.0", "geoplanet:7.10.0", "geoplanet:8.0.0", "woeplanet:8.0.0"], "meta:indexed": "2020-08-20T19:45:31.673992", "woe:alias_ENG_V": ["Dover Western Docks Station"], "meta:updated": "2020-08-22T02:03:28.754700", "woe:hierarchy": {"continent": 24865675, "country": 23424975, "town": 0, "planet": 1, "county": 12602173, "suburb": 0, "state": 24554868, "region": 0, "localadmin": 12695988}, "woe:timezone_id": 28350903, "woe:hash": "u10fvc5y1r4t", "woe:centroid": [1.31258, 51.11496], "geom:latitude": 51.11496, "geom:longitude": 1.31258, "geom:hash": "u10fvc5y1r4t", "woe:latitude": 51.11496, "geom:centroid": [1.31258, 51.11496], "woe:longitude": 1.31258, "woe:repo": "woeplanet-poi-gb"}, "geometry": {"coordinates": [1.31258, 51.11496], "type": "Point"}}