{"type": "Feature", "id": 22483236, "geometry": {"type": "Point", "coordinates": [-0.32324, 52.572632]}, "properties": {"woe:id": 22483236, "woe:parent_id": 29050, "woe:name": "Peterborough Milton Golf Club", "woe:placetype": 20, "woe:placetype_name": "POI", "woe:lang": "ENG", "iso:country": "GB", "meta:provider": ["geoplanet:7.3.1", "geoplanet:7.3.2", "geoplanet:7.4.0", "geoplanet:7.4.1", "geoplanet:7.5.1", "geoplanet:7.5.2", "geoplanet:7.6.0", "geoplanet:7.8.1", "geoplanet:7.9.0", "geoplanet:7.10.0", "geoplanet:8.0.0", "woeplanet:8.0.0"], "meta:indexed": "2020-08-20T19:45:33.121122", "meta:updated": "2020-10-14T11:22:07.700925", "woe:hierarchy": {"continent": 24865675, "country": 23424975, "town": 0, "planet": 1, "county": 12602140, "suburb": 0, "state": 24554868, "region": 0, "localadmin": 12696170}, "woe:timezone_id": 28350903, "woe:hash": "gcrg0ds9gbyv", "woe:centroid": [-0.32324, 52.572632], "geom:latitude": 52.572632, "geom:longitude": -0.32324, "geom:hash": "gcrg0ds9gbyv", "woe:latitude": 52.572632, "geom:centroid": [-0.32324, 52.572632], "woe:longitude": -0.32324, "woe:repo": "woeplanet-poi-gb", "geom:area": 0.0, "woe:scale": 19}}