{"type": "Feature", "id": 22475366, "properties": {"woe:id": 22475366, "woe:parent_id": 20094364, "woe:name": "London Brass Rubbing Centre", "woe:placetype": 20, "woe:placetype_name": "POI", "woe:lang": "ENG", "iso:country": "GB", "meta:provider": ["geoplanet:7.3.1", "geoplanet:7.3.2", "geoplanet:7.4.0", "geoplanet:7.4.1", "geoplanet:7.5.1", "geoplanet:7.5.2", "geoplanet:7.6.0", "geoplanet:7.8.1", "geoplanet:7.9.0", "geoplanet:7.10.0", "geoplanet:8.0.0", "woeplanet:8.0.0"], "meta:indexed": "2020-08-20T19:45:32.563672", "meta:updated": "2020-08-22T02:03:29.186318", "woe:hierarchy": {"continent": 24865675, "country": 23424975, "town": 0, "planet": 1, "county": 23416974, "suburb": 0, "state": 24554868, "region": 0, "localadmin": 12695819}, "woe:timezone_id": 28350903, "woe:hash": "gcpvj0g7yx6c", "woe:centroid": [-0.12709, 51.508709], "geom:latitude": 51.508709, "geom:longitude": -0.12709, "geom:hash": "gcpvj0g7yx6c", "woe:latitude": 51.508709, "geom:centroid": [-0.12709, 51.508709], "woe:longitude": -0.12709, "woe:repo": "woeplanet-poi-gb"}, "geometry": {"coordinates": [-0.12709, 51.508709], "type": "Point"}}