{"type": "Feature", "id": 22476155, "properties": {"woe:id": 22476155, "woe:parent_id": 35498, "woe:name": "Shoreditch Underground Station", "woe:placetype": 20, "woe:placetype_name": "POI", "woe:lang": "ENG", "iso:country": "GB", "meta:provider": ["geoplanet:7.3.1", "geoplanet:7.3.2", "geoplanet:7.4.0", "geoplanet:7.4.1", "geoplanet:7.5.1", "geoplanet:7.5.2", "geoplanet:7.6.0", "geoplanet:7.8.1", "geoplanet:7.9.0", "geoplanet:7.10.0", "geoplanet:8.0.0", "woeplanet:8.0.0"], "meta:indexed": "2020-08-20T19:45:32.664381", "woe:alias_ENG_V": ["Shoreditch Tube", "Shoreditch Underground", "Shoreditch Station", "Shoreditch Tube Station"], "meta:updated": "2020-08-22T02:03:29.233464", "woe:hierarchy": {"continent": 24865675, "country": 23424975, "town": 0, "planet": 1, "county": 23416974, "suburb": 0, "state": 24554868, "region": 0, "localadmin": 12695817}, "woe:timezone_id": 28350903, "woe:hash": "gcpvn7kj252c", "woe:centroid": [-0.07141, 51.522678], "geom:latitude": 51.522678, "geom:longitude": -0.07141, "geom:hash": "gcpvn7kj252c", "woe:latitude": 51.522678, "geom:centroid": [-0.07141, 51.522678], "woe:longitude": -0.07141, "woe:repo": "woeplanet-poi-gb"}, "geometry": {"coordinates": [-0.07141, 51.522678], "type": "Point"}}