{"type": "Feature", "id": 22462585, "geometry": {"type": "Point", "coordinates": [-2.54898, 50.6861]}, "properties": {"woe:id": 22462585, "woe:parent_id": 38927, "woe:name": "Hardy Monument", "woe:placetype": 20, "woe:placetype_name": "POI", "woe:lang": "ENG", "iso:country": "GB", "meta:provider": ["geoplanet:7.3.1", "geoplanet:7.3.2", "geoplanet:7.4.0", "geoplanet:7.4.1", "geoplanet:7.5.1", "geoplanet:7.5.2", "geoplanet:7.6.0", "geoplanet:7.8.1", "geoplanet:7.9.0", "geoplanet:7.10.0", "geoplanet:8.0.0", "woeplanet:8.0.0"], "meta:indexed": "2020-08-20T19:45:31.664745", "meta:updated": "2020-10-14T11:22:08.368034", "woe:hierarchy": {"continent": 24865675, "country": 23424975, "town": 0, "planet": 1, "county": 12602183, "suburb": 0, "state": 24554868, "region": 0, "localadmin": 12695926}, "woe:timezone_id": 28350903, "woe:hash": "gcn0mgpgumyg", "woe:centroid": [-2.54898, 50.6861], "geom:latitude": 50.6861, "geom:longitude": -2.54898, "geom:hash": "gcn0mgpgumyg", "woe:latitude": 50.6861, "geom:centroid": [-2.54898, 50.6861], "woe:longitude": -2.54898, "woe:repo": "woeplanet-poi-gb", "geom:area": 0.0, "woe:scale": 19}}