{"type": "Feature", "id": 22493691, "properties": {"woe:id": 22493691, "woe:parent_id": 39493, "woe:name": "Wembley Central Railway Station", "woe:placetype": 20, "woe:placetype_name": "POI", "woe:lang": "ENG", "iso:country": "GB", "meta:provider": ["geoplanet:7.3.1", "geoplanet:7.3.2", "geoplanet:7.4.0", "geoplanet:7.4.1", "geoplanet:7.5.1", "geoplanet:7.5.2", "geoplanet:7.6.0", "geoplanet:7.8.1", "geoplanet:7.9.0", "geoplanet:7.10.0", "geoplanet:8.0.0", "woeplanet:8.0.0"], "meta:indexed": "2020-08-20T19:45:33.696631", "woe:alias_ENG_V": ["Wembley Central Station"], "meta:updated": "2020-08-22T02:03:29.714906", "woe:hierarchy": {"continent": 24865675, "country": 23424975, "town": 0, "planet": 1, "county": 23416974, "suburb": 0, "state": 24554868, "region": 0, "localadmin": 12695823}, "woe:timezone_id": 28350903, "woe:hash": "gcpv30zfsx8c", "woe:centroid": [-0.29678, 51.552441], "geom:latitude": 51.552441, "geom:longitude": -0.29678, "geom:hash": "gcpv30zfsx8c", "woe:latitude": 51.552441, "geom:centroid": [-0.29678, 51.552441], "woe:longitude": -0.29678, "woe:repo": "woeplanet-poi-gb"}, "geometry": {"coordinates": [-0.29678, 51.552441], "type": "Point"}}