{"type": "Feature", "id": 22453130, "geometry": {"type": "Point", "coordinates": [-2.30316, 51.386349]}, "properties": {"woe:id": 22453130, "woe:parent_id": 12063, "woe:name": "Bath Assembly Rooms", "woe:placetype": 20, "woe:placetype_name": "POI", "woe:lang": "ENG", "iso:country": "GB", "meta:provider": ["geoplanet:7.3.1", "geoplanet:7.3.2", "geoplanet:7.4.0", "geoplanet:7.4.1", "geoplanet:7.5.1", "geoplanet:7.5.2", "geoplanet:7.6.0", "geoplanet:7.8.1", "geoplanet:7.9.0", "geoplanet:7.10.0", "geoplanet:8.0.0", "woeplanet:8.0.0"], "meta:indexed": "2020-08-20T19:45:31.114788", "meta:updated": "2020-10-14T11:22:08.729025", "woe:hierarchy": {"continent": 24865675, "country": 23424975, "town": 0, "planet": 1, "county": 12602185, "suburb": 0, "state": 24554868, "region": 0, "localadmin": 12696136}, "woe:timezone_id": 28350903, "woe:hash": "gcnk7ddghmxr", "woe:centroid": [-2.30316, 51.386349], "geom:latitude": 51.386349, "geom:longitude": -2.30316, "geom:hash": "gcnk7ddghmxr", "woe:latitude": 51.386349, "geom:centroid": [-2.30316, 51.386349], "woe:longitude": -2.30316, "woe:repo": "woeplanet-poi-gb", "geom:area": 0.0, "woe:scale": 19}}