{"type": "Feature", "id": 22461371, "geometry": {"type": "Point", "coordinates": [1.29293, 52.930382]}, "properties": {"woe:id": 22461371, "woe:parent_id": 17381, "woe:name": "Cromer Railway Station", "woe:placetype": 20, "woe:placetype_name": "POI", "woe:lang": "ENG", "iso:country": "GB", "meta:provider": ["geoplanet:7.3.1", "geoplanet:7.3.2", "geoplanet:7.4.0", "geoplanet:7.4.1", "geoplanet:7.5.1", "geoplanet:7.5.2", "geoplanet:7.6.0", "geoplanet:7.8.1", "geoplanet:7.9.0", "geoplanet:7.10.0", "geoplanet:8.0.0", "woeplanet:8.0.0"], "meta:indexed": "2020-08-20T19:45:31.602176", "woe:alias_ENG_V": ["Cromer Station"], "meta:updated": "2020-10-14T11:22:09.561069", "woe:hierarchy": {"continent": 24865675, "country": 23424975, "town": 0, "planet": 1, "county": 12602141, "suburb": 0, "state": 24554868, "region": 0, "localadmin": 12696027}, "woe:timezone_id": 28350903, "woe:hash": "u12vj7tmz6q7", "woe:centroid": [1.29293, 52.930382], "geom:latitude": 52.930382, "geom:longitude": 1.29293, "geom:hash": "u12vj7tmz6q7", "woe:latitude": 52.930382, "geom:centroid": [1.29293, 52.930382], "woe:longitude": 1.29293, "woe:repo": "woeplanet-poi-gb", "geom:area": 0.0, "woe:scale": 19}}