{"type": "Feature", "id": 23702229, "geometry": {"type": "Point", "coordinates": [-1.58125, 54.76379]}, "properties": {"woe:id": 23702229, "woe:parent_id": 18760, "woe:name": "Teikyo University in Durham", "woe:placetype": 20, "woe:placetype_name": "POI", "woe:lang": "ENG", "iso:country": "GB", "meta:provider": ["geoplanet:7.3.1", "geoplanet:7.3.2", "geoplanet:7.4.0", "geoplanet:7.4.1", "geoplanet:7.5.1", "geoplanet:7.5.2", "geoplanet:7.6.0", "geoplanet:7.8.1", "geoplanet:7.9.0", "geoplanet:7.10.0", "geoplanet:8.0.0", "woeplanet:8.0.0"], "meta:indexed": "2020-08-20T19:45:34.223415", "meta:updated": "2020-10-14T11:21:47.724045", "woe:alias_ENG_V": ["Teikyo University of Japan", "Teikyo University in Japan"], "woe:hierarchy": {"continent": 24865675, "country": 23424975, "town": 0, "planet": 1, "county": 12602150, "suburb": 0, "state": 24554868, "region": 0, "localadmin": 12695930}, "woe:timezone_id": 28350903, "woe:hash": "gcwzs12w4nqs", "woe:centroid": [-1.58125, 54.76379], "geom:latitude": 54.76379, "geom:longitude": -1.58125, "geom:hash": "gcwzs12w4nqs", "woe:latitude": 54.76379, "geom:centroid": [-1.58125, 54.76379], "woe:longitude": -1.58125, "woe:repo": "woeplanet-poi-gb", "geom:area": 0.0, "woe:scale": 19}}