{"type": "Feature", "id": 22464475, "properties": {"woe:id": 22464475, "woe:parent_id": 39604, "woe:name": "Pinhoe Railway Station", "woe:placetype": 20, "woe:placetype_name": "POI", "woe:lang": "ENG", "iso:country": "GB", "meta:provider": ["geoplanet:7.3.1", "geoplanet:7.3.2", "geoplanet:7.4.0", "geoplanet:7.4.1", "geoplanet:7.5.1", "geoplanet:7.5.2", "geoplanet:7.6.0", "geoplanet:7.8.1", "geoplanet:7.9.0", "geoplanet:7.10.0", "geoplanet:8.0.0", "woeplanet:8.0.0"], "meta:indexed": "2020-08-20T19:45:31.779535", "woe:alias_ENG_V": ["Pinhoe Station"], "meta:updated": "2020-08-22T02:03:28.802147", "woe:hierarchy": {"continent": 24865675, "country": 23424975, "town": 0, "planet": 1, "county": 12602182, "suburb": 0, "state": 24554868, "region": 0, "localadmin": 12695915}, "woe:timezone_id": 28350903, "woe:hash": "gcj89h92tbux", "woe:centroid": [-3.46971, 50.737701], "geom:latitude": 50.737701, "geom:longitude": -3.46971, "geom:hash": "gcj89h92tbux", "woe:latitude": 50.737701, "geom:centroid": [-3.46971, 50.737701], "woe:longitude": -3.46971, "woe:repo": "woeplanet-poi-gb"}, "geometry": {"coordinates": [-3.46971, 50.737701], "type": "Point"}}