{"type": "Feature", "id": 22473565, "geometry": {"type": "Point", "coordinates": [-3.37848, 52.243172]}, "properties": {"woe:id": 22473565, "woe:parent_id": 26849, "woe:name": "Llandrindod Railway Station", "woe:placetype": 20, "woe:placetype_name": "POI", "woe:lang": "ENG", "iso:country": "GB", "meta:provider": ["geoplanet:7.3.1", "geoplanet:7.3.2", "geoplanet:7.4.0", "geoplanet:7.4.1", "geoplanet:7.5.1", "geoplanet:7.5.2", "geoplanet:7.6.0", "geoplanet:7.8.1", "geoplanet:7.9.0", "geoplanet:7.10.0", "geoplanet:8.0.0", "woeplanet:8.0.0"], "meta:indexed": "2020-08-20T19:45:32.348516", "woe:alias_ENG_V": ["Llandrindod Station"], "meta:updated": "2020-10-14T11:22:08.309045", "woe:hierarchy": {"continent": 24865675, "country": 23424975, "town": 0, "planet": 1, "county": 12602227, "suburb": 0, "state": 12578049, "region": 0, "localadmin": 12696134}, "woe:timezone_id": 28350903, "woe:hash": "gcm95nefe9ne", "woe:centroid": [-3.37848, 52.243172], "geom:latitude": 52.243172, "geom:longitude": -3.37848, "geom:hash": "gcm95nefe9ne", "woe:latitude": 52.243172, "geom:centroid": [-3.37848, 52.243172], "woe:longitude": -3.37848, "woe:repo": "woeplanet-poi-gb", "geom:area": 0.0, "woe:scale": 19}}