{"type": "Feature", "id": 23702277, "properties": {"woe:id": 23702277, "woe:parent_id": 18846, "woe:name": "University of East Anglia", "woe:placetype": 20, "woe:placetype_name": "POI", "woe:lang": "ENG", "iso:country": "GB", "meta:provider": ["geoplanet:7.3.1", "geoplanet:7.3.2", "geoplanet:7.4.0", "geoplanet:7.4.1", "geoplanet:7.5.1", "geoplanet:7.5.2", "geoplanet:7.6.0", "geoplanet:7.8.1", "geoplanet:7.9.0", "geoplanet:7.10.0", "geoplanet:8.0.0", "woeplanet:8.0.0"], "meta:indexed": "2020-08-20T19:45:34.230282", "woe:alias_ENG_V": ["UEA", "East Anglia University"], "meta:updated": "2020-08-22T02:03:57.976015", "woe:hierarchy": {"continent": 24865675, "country": 23424975, "town": 0, "planet": 1, "county": 12602141, "suburb": 0, "state": 24554868, "region": 0, "localadmin": 12696028}, "woe:timezone_id": 28350903, "woe:hash": "u12gk5zk7s57", "woe:centroid": [1.24058, 52.62389], "geom:latitude": 52.62389, "geom:longitude": 1.24058, "geom:hash": "u12gk5zk7s57", "woe:latitude": 52.62389, "geom:centroid": [1.24058, 52.62389], "woe:longitude": 1.24058, "woe:repo": "woeplanet-poi-gb"}, "geometry": {"coordinates": [1.24058, 52.62389], "type": "Point"}}