{"type": "Feature", "id": 22473030, "geometry": {"type": "Point", "coordinates": [-2.87397, 53.33622]}, "properties": {"woe:id": 22473030, "woe:parent_id": 36973, "woe:name": "20 Forthlin Road Allerton", "woe:placetype": 20, "woe:placetype_name": "POI", "woe:lang": "ENG", "iso:country": "GB", "meta:provider": ["geoplanet:7.3.1", "geoplanet:7.3.2", "geoplanet:7.4.0", "geoplanet:7.4.1", "geoplanet:7.5.1", "geoplanet:7.5.2", "geoplanet:7.6.0", "geoplanet:7.8.1", "geoplanet:7.9.0", "geoplanet:7.10.0", "geoplanet:8.0.0", "woeplanet:8.0.0"], "meta:indexed": "2020-08-20T19:45:32.312496", "meta:updated": "2020-10-14T11:22:08.135482", "woe:hierarchy": {"continent": 24865675, "country": 23424975, "town": 0, "planet": 1, "county": 12602161, "suburb": 0, "state": 24554868, "region": 0, "localadmin": 12695850}, "woe:timezone_id": 28350903, "woe:hash": "gcmzqte4p8h9", "woe:centroid": [-2.87397, 53.33622], "geom:latitude": 53.33622, "geom:longitude": -2.87397, "geom:hash": "gcmzqte4p8h9", "woe:latitude": 53.33622, "geom:centroid": [-2.87397, 53.33622], "woe:longitude": -2.87397, "woe:repo": "woeplanet-poi-gb", "geom:area": 0.0, "woe:scale": 19}}