{"type": "Feature", "id": 22458470, "geometry": {"type": "Point", "coordinates": [-3.1789, 51.47575]}, "properties": {"woe:id": 22458470, "woe:parent_id": 15127, "woe:name": "Cardiff Central Railway Station", "woe:placetype": 20, "woe:placetype_name": "POI", "woe:lang": "ENG", "iso:country": "GB", "meta:provider": ["geoplanet:7.3.1", "geoplanet:7.3.2", "geoplanet:7.4.0", "geoplanet:7.4.1", "geoplanet:7.5.1", "geoplanet:7.5.2", "geoplanet:7.6.0", "geoplanet:7.8.1", "geoplanet:7.9.0", "geoplanet:7.10.0", "geoplanet:8.0.0", "woeplanet:8.0.0"], "meta:indexed": "2020-08-20T19:45:31.433016", "woe:alias_ENG_V": ["Cardiff Central Station"], "meta:updated": "2020-10-14T11:22:09.086547", "woe:alias_UNK_Q": ["Caerdydd Canolog"], "woe:hierarchy": {"continent": 24865675, "country": 23424975, "town": 0, "planet": 1, "county": 12602215, "suburb": 0, "state": 12578049, "region": 0, "localadmin": 12696132}, "woe:timezone_id": 28350903, "woe:hash": "gcjszdv5yr23", "woe:centroid": [-3.1789, 51.47575], "geom:latitude": 51.47575, "geom:longitude": -3.1789, "geom:hash": "gcjszdv5yr23", "woe:latitude": 51.47575, "geom:centroid": [-3.1789, 51.47575], "woe:longitude": -3.1789, "woe:repo": "woeplanet-poi-gb", "geom:area": 0.0, "woe:scale": 19}}