{"type": "Feature", "id": 23701955, "properties": {"woe:id": 23701955, "woe:parent_id": 25211, "woe:name": "Kingston Communications", "woe:placetype": 20, "woe:placetype_name": "POI", "woe:lang": "ENG", "iso:country": "GB", "meta:provider": ["geoplanet:7.3.1", "geoplanet:7.3.2", "geoplanet:7.4.0", "geoplanet:7.4.1", "geoplanet:7.5.1", "geoplanet:7.5.2", "geoplanet:7.6.0", "geoplanet:7.8.1", "geoplanet:7.9.0", "geoplanet:7.10.0", "geoplanet:8.0.0", "woeplanet:8.0.0"], "meta:indexed": "2020-08-20T19:45:33.915518", "meta:updated": "2020-08-22T02:03:29.814023", "woe:alias_ENG_V": ["Kingston Communications Stadium", "Kingston Communication Stadium"], "woe:hierarchy": {"continent": 24865675, "country": 23424975, "town": 0, "planet": 1, "county": 12602193, "suburb": 0, "state": 24554868, "region": 0, "localadmin": 12696140}, "woe:timezone_id": 28350903, "woe:hash": "gcx9z8h590qg", "woe:centroid": [-0.36799, 53.74572], "geom:latitude": 53.74572, "geom:longitude": -0.36799, "geom:hash": "gcx9z8h590qg", "woe:latitude": 53.74572, "geom:centroid": [-0.36799, 53.74572], "woe:longitude": -0.36799, "woe:repo": "woeplanet-poi-gb"}, "geometry": {"coordinates": [-0.36799, 53.74572], "type": "Point"}}