{"type": "Feature", "id": 22460790, "geometry": {"type": "Point", "coordinates": [-0.15423, 51.31876]}, "properties": {"woe:id": 22460790, "woe:parent_id": 17002, "woe:name": "Woodmansterne Railway Station", "woe:placetype": 20, "woe:placetype_name": "POI", "woe:lang": "ENG", "iso:country": "GB", "meta:provider": ["geoplanet:7.3.1", "geoplanet:7.3.2", "geoplanet:7.4.0", "geoplanet:7.4.1", "geoplanet:7.5.1", "geoplanet:7.5.2", "geoplanet:7.6.0", "geoplanet:7.8.1", "geoplanet:7.9.0", "geoplanet:7.10.0", "geoplanet:8.0.0", "woeplanet:8.0.0"], "meta:indexed": "2020-08-20T19:45:31.570353", "woe:alias_ENG_V": ["Woodmansterne Station"], "meta:updated": "2020-10-14T11:22:08.722627", "woe:hierarchy": {"continent": 24865675, "country": 23424975, "town": 0, "planet": 1, "county": 23416974, "suburb": 0, "state": 24554868, "region": 0, "localadmin": 12695825}, "woe:timezone_id": 28350903, "woe:hash": "gcpguqr9qnjz", "woe:centroid": [-0.15423, 51.31876], "geom:latitude": 51.31876, "geom:longitude": -0.15423, "geom:hash": "gcpguqr9qnjz", "woe:latitude": 51.31876, "geom:centroid": [-0.15423, 51.31876], "woe:longitude": -0.15423, "woe:repo": "woeplanet-poi-gb", "geom:area": 0.0, "woe:scale": 19}}