{"type": "Feature", "id": 56072250, "properties": {"woe:id": 56072250, "woe:parent_id": 40052, "woe:name": "Haughley New Street", "woe:placetype": 20, "woe:placetype_name": "POI", "woe:lang": "ENG", "iso:country": "GB", "meta:provider": ["geoplanet:7.4.0", "geoplanet:7.4.1", "geoplanet:7.5.1", "geoplanet:7.5.2", "geoplanet:7.6.0", "geoplanet:7.8.1", "geoplanet:7.9.0", "geoplanet:7.10.0", "geoplanet:8.0.0", "woeplanet:8.0.0"], "meta:indexed": "2020-08-20T23:16:09.523458", "meta:updated": "2020-08-22T02:03:58.157451", "woe:hierarchy": {"continent": 24865675, "country": 23424975, "town": 0, "planet": 1, "county": 12602142, "suburb": 0, "state": 24554868, "region": 0, "localadmin": 12696083}, "woe:timezone_id": 28350903, "woe:hash": "u129jd1csq8n", "woe:centroid": [0.94741, 52.218311], "geom:latitude": 52.218311, "geom:longitude": 0.94741, "geom:hash": "u129jd1csq8n", "woe:latitude": 52.218311, "geom:centroid": [0.94741, 52.218311], "woe:longitude": 0.94741, "woe:repo": "woeplanet-poi-gb"}, "geometry": {"coordinates": [0.94741, 52.218311], "type": "Point"}}