{"type": "Feature", "id": 23702273, "geometry": {"type": "Point", "coordinates": [-0.13454, 51.524269]}, "properties": {"woe:id": 23702273, "woe:parent_id": 43265, "woe:name": "University of London University College", "woe:placetype": 20, "woe:placetype_name": "POI", "woe:lang": "ENG", "iso:country": "GB", "meta:provider": ["geoplanet:7.3.1", "geoplanet:7.3.2", "geoplanet:7.4.0", "geoplanet:7.4.1", "geoplanet:7.5.1", "geoplanet:7.5.2", "geoplanet:7.6.0", "geoplanet:7.8.1", "geoplanet:7.9.0", "geoplanet:7.10.0", "geoplanet:8.0.0", "woeplanet:8.0.0"], "meta:indexed": "2020-08-20T19:45:34.316403", "woe:alias_ENG_V": ["UCL", "University College London"], "meta:updated": "2020-10-14T11:21:47.753578", "woe:hierarchy": {"continent": 24865675, "country": 23424975, "town": 0, "planet": 1, "county": 23416974, "suburb": 0, "state": 24554868, "region": 0, "localadmin": 12695807}, "woe:timezone_id": 28350903, "woe:hash": "gcpvhgwn8gzs", "woe:centroid": [-0.13454, 51.524269], "geom:latitude": 51.524269, "geom:longitude": -0.13454, "geom:hash": "gcpvhgwn8gzs", "woe:latitude": 51.524269, "geom:centroid": [-0.13454, 51.524269], "woe:longitude": -0.13454, "woe:repo": "woeplanet-poi-gb", "geom:area": 0.0, "woe:scale": 19}}