{"type": "Feature", "id": 22488525, "geometry": {"type": "Point", "coordinates": [-1.52644, 50.889839]}, "properties": {"woe:id": 22488525, "woe:parent_id": 11229, "woe:name": "Lyndhurst Road Railway Station", "woe:placetype": 20, "woe:placetype_name": "POI", "woe:lang": "ENG", "iso:country": "GB", "meta:provider": ["geoplanet:7.3.1", "geoplanet:7.3.2", "geoplanet:7.4.0", "geoplanet:7.4.1", "geoplanet:7.5.1", "geoplanet:7.5.2", "geoplanet:7.6.0", "geoplanet:7.8.1", "geoplanet:7.9.0", "geoplanet:7.10.0", "geoplanet:8.0.0", "woeplanet:8.0.0"], "meta:indexed": "2020-08-20T19:45:33.434554", "woe:alias_ENG_V": ["Lyndhurst Road Station"], "meta:updated": "2020-10-14T11:22:08.115074", "woe:hierarchy": {"continent": 24865675, "country": 23424975, "town": 0, "planet": 1, "county": 12602169, "suburb": 0, "state": 24554868, "region": 0, "localadmin": 12695965}, "woe:timezone_id": 28350903, "woe:hash": "gcnct20qz3ef", "woe:centroid": [-1.52644, 50.889839], "geom:latitude": 50.889839, "geom:longitude": -1.52644, "geom:hash": "gcnct20qz3ef", "woe:latitude": 50.889839, "geom:centroid": [-1.52644, 50.889839], "woe:longitude": -1.52644, "woe:repo": "woeplanet-poi-gb", "geom:area": 0.0, "woe:scale": 19}}