{"type": "Feature", "id": 22470049, "geometry": {"type": "Point", "coordinates": [1.18243, 52.05022]}, "properties": {"woe:id": 22470049, "woe:parent_id": 23415578, "woe:name": "Derby Road Railway Station", "woe:placetype": 20, "woe:placetype_name": "POI", "woe:lang": "ENG", "iso:country": "GB", "meta:provider": ["geoplanet:7.3.1", "geoplanet:7.3.2", "geoplanet:7.4.0", "geoplanet:7.4.1", "geoplanet:7.5.1", "geoplanet:7.5.2", "geoplanet:7.6.0", "geoplanet:7.8.1", "geoplanet:7.9.0", "geoplanet:7.10.0", "geoplanet:8.0.0", "woeplanet:8.0.0"], "meta:indexed": "2020-08-20T19:45:32.162925", "woe:alias_ENG_V": ["Derby Road Station"], "meta:updated": "2020-10-14T11:22:07.997874", "woe:hierarchy": {"continent": 24865675, "country": 23424975, "town": 0, "planet": 1, "county": 12602142, "suburb": 0, "state": 24554868, "region": 0, "localadmin": 12696082}, "woe:timezone_id": 28350903, "woe:hash": "u12b4gmn8878", "woe:centroid": [1.18243, 52.05022], "geom:latitude": 52.05022, "geom:longitude": 1.18243, "geom:hash": "u12b4gmn8878", "woe:latitude": 52.05022, "geom:centroid": [1.18243, 52.05022], "woe:longitude": 1.18243, "woe:repo": "woeplanet-poi-gb", "geom:area": 0.0, "woe:scale": 19}}