{"type": "Feature", "id": 22495291, "properties": {"woe:id": 22495291, "woe:parent_id": 40859, "woe:name": "Wolverhampton Railway Station", "woe:placetype": 20, "woe:placetype_name": "POI", "woe:lang": "ENG", "iso:country": "GB", "meta:provider": ["geoplanet:7.3.1", "geoplanet:7.3.2", "geoplanet:7.4.0", "geoplanet:7.4.1", "geoplanet:7.5.1", "geoplanet:7.5.2", "geoplanet:7.6.0", "geoplanet:7.8.1", "geoplanet:7.9.0", "geoplanet:7.10.0", "geoplanet:8.0.0", "woeplanet:8.0.0"], "meta:indexed": "2020-08-20T19:45:33.793358", "woe:alias_ENG_V": ["Wolverhampton Station"], "meta:updated": "2020-08-22T02:03:29.764193", "woe:hierarchy": {"continent": 24865675, "country": 23424975, "town": 0, "planet": 1, "county": 12602191, "suburb": 0, "state": 24554868, "region": 0, "localadmin": 12695869}, "woe:timezone_id": 28350903, "woe:hash": "gcq7pv21h0xh", "woe:centroid": [-2.12018, 52.587608], "geom:latitude": 52.587608, "geom:longitude": -2.12018, "geom:hash": "gcq7pv21h0xh", "woe:latitude": 52.587608, "geom:centroid": [-2.12018, 52.587608], "woe:longitude": -2.12018, "woe:repo": "woeplanet-poi-gb"}, "geometry": {"coordinates": [-2.12018, 52.587608], "type": "Point"}}