{"type": "Feature", "id": 22474660, "geometry": {"type": "Point", "coordinates": [-0.19316, 51.49221]}, "properties": {"woe:id": 22474660, "woe:parent_id": 18851, "woe:name": "Earl's Court Underground Station", "woe:placetype": 20, "woe:placetype_name": "POI", "woe:lang": "ENG", "iso:country": "GB", "meta:provider": ["geoplanet:7.3.1", "geoplanet:7.3.2", "geoplanet:7.4.0", "geoplanet:7.4.1", "geoplanet:7.5.1", "geoplanet:7.5.2", "geoplanet:7.6.0", "geoplanet:7.8.1", "geoplanet:7.9.0", "geoplanet:7.10.0", "geoplanet:8.0.0", "woeplanet:8.0.0"], "meta:indexed": "2020-08-20T19:45:32.473576", "woe:alias_ENG_V": ["Earl's Court Tube Station", "Earls Court Station", "Earls Court Tube Station", "Earls Court Underground Station", "Earl's Court Tube", "Earls Court Tube", "Earl's Court Underground", "Earls Court Underground", "Earl's Court Station"], "meta:updated": "2020-10-14T11:22:08.844003", "woe:hierarchy": {"continent": 24865675, "country": 23424975, "town": 0, "planet": 1, "county": 23416974, "suburb": 0, "state": 24554868, "region": 0, "localadmin": 12695812}, "woe:timezone_id": 28350903, "woe:hash": "gcpugtg7g59m", "woe:centroid": [-0.19316, 51.49221], "geom:latitude": 51.49221, "geom:longitude": -0.19316, "geom:hash": "gcpugtg7g59m", "woe:latitude": 51.49221, "geom:centroid": [-0.19316, 51.49221], "woe:longitude": -0.19316, "woe:repo": "woeplanet-poi-gb", "geom:area": 0.0, "woe:scale": 19}}