{"type": "Feature", "id": 22493875, "geometry": {"type": "Point", "coordinates": [0.69153, 51.537331]}, "properties": {"woe:id": 22493875, "woe:parent_id": 39880, "woe:name": "Westcliff Railway Station", "woe:placetype": 20, "woe:placetype_name": "POI", "woe:lang": "ENG", "iso:country": "GB", "meta:provider": ["geoplanet:7.3.1", "geoplanet:7.3.2", "geoplanet:7.4.0", "geoplanet:7.4.1", "geoplanet:7.5.1", "geoplanet:7.5.2", "geoplanet:7.6.0", "geoplanet:7.8.1", "geoplanet:7.9.0", "geoplanet:7.10.0", "geoplanet:8.0.0", "woeplanet:8.0.0"], "meta:indexed": "2020-08-20T19:45:33.709846", "woe:alias_ENG_V": ["Westcliff Station"], "meta:updated": "2020-10-14T11:22:08.755190", "woe:hierarchy": {"continent": 24865675, "country": 23424975, "town": 0, "planet": 1, "county": 12602168, "suburb": 0, "state": 24554868, "region": 0, "localadmin": 12696175}, "woe:timezone_id": 28350903, "woe:hash": "u10mpwpd9yf4", "woe:centroid": [0.69153, 51.537331], "geom:latitude": 51.537331, "geom:longitude": 0.69153, "geom:hash": "u10mpwpd9yf4", "woe:latitude": 51.537331, "geom:centroid": [0.69153, 51.537331], "woe:longitude": 0.69153, "woe:repo": "woeplanet-poi-gb", "geom:area": 0.0, "woe:scale": 19}}