{"type": "Feature", "id": 22473882, "geometry": {"type": "Point", "coordinates": [-3.32407, 55.044868]}, "properties": {"woe:id": 22473882, "woe:parent_id": 28870, "woe:name": "Hoddom Castle Golf Club", "woe:placetype": 20, "woe:placetype_name": "POI", "woe:lang": "ENG", "iso:country": "GB", "meta:provider": ["geoplanet:7.3.1", "geoplanet:7.3.2", "geoplanet:7.4.0", "geoplanet:7.4.1", "geoplanet:7.5.1", "geoplanet:7.5.2", "geoplanet:7.6.0", "geoplanet:7.8.1", "geoplanet:7.9.0", "geoplanet:7.10.0", "geoplanet:8.0.0", "woeplanet:8.0.0"], "meta:indexed": "2020-08-20T19:45:32.367466", "meta:updated": "2020-10-14T11:22:08.634964", "woe:hierarchy": {"continent": 24865675, "country": 23424975, "town": 0, "planet": 1, "county": 12602200, "suburb": 0, "state": 12578048, "region": 0, "localadmin": 12696189}, "woe:timezone_id": 28350903, "woe:hash": "gcv9hke7xe1g", "woe:centroid": [-3.32407, 55.044868], "geom:latitude": 55.044868, "geom:longitude": -3.32407, "geom:hash": "gcv9hke7xe1g", "woe:latitude": 55.044868, "geom:centroid": [-3.32407, 55.044868], "woe:longitude": -3.32407, "woe:repo": "woeplanet-poi-gb", "geom:area": 0.0, "woe:scale": 19}}