{"type": "Feature", "id": 22469642, "geometry": {"type": "Point", "coordinates": [-2.08486, 53.451439]}, "properties": {"woe:id": 22469642, "woe:parent_id": 24257, "woe:name": "Hyde Central Railway Station", "woe:placetype": 20, "woe:placetype_name": "POI", "woe:lang": "ENG", "iso:country": "GB", "meta:provider": ["geoplanet:7.3.1", "geoplanet:7.3.2", "geoplanet:7.4.0", "geoplanet:7.4.1", "geoplanet:7.5.1", "geoplanet:7.5.2", "geoplanet:7.6.0", "geoplanet:7.8.1", "geoplanet:7.9.0", "geoplanet:7.10.0", "geoplanet:8.0.0", "woeplanet:8.0.0"], "meta:indexed": "2020-08-20T19:45:32.142881", "woe:alias_ENG_V": ["Hyde Central Station"], "meta:updated": "2020-10-14T11:22:08.598307", "woe:hierarchy": {"continent": 24865675, "country": 23424975, "town": 0, "planet": 1, "county": 12602158, "suburb": 0, "state": 24554868, "region": 0, "localadmin": 12695846}, "woe:timezone_id": 28350903, "woe:hash": "gcw80d9c5nrt", "woe:centroid": [-2.08486, 53.451439], "geom:latitude": 53.451439, "geom:longitude": -2.08486, "geom:hash": "gcw80d9c5nrt", "woe:latitude": 53.451439, "geom:centroid": [-2.08486, 53.451439], "woe:longitude": -2.08486, "woe:repo": "woeplanet-poi-gb", "geom:area": 0.0, "woe:scale": 19}}