{"type": "Feature", "id": 22465420, "geometry": {"type": "Point", "coordinates": [-1.5424, 54.952709]}, "properties": {"woe:id": 22465420, "woe:parent_id": 20034, "woe:name": "Pelaw Station", "woe:placetype": 20, "woe:placetype_name": "POI", "woe:lang": "ENG", "iso:country": "GB", "meta:provider": ["geoplanet:7.3.1", "geoplanet:7.3.2", "geoplanet:7.4.0", "geoplanet:7.4.1", "geoplanet:7.5.1", "geoplanet:7.5.2", "geoplanet:7.6.0", "geoplanet:7.8.1", "geoplanet:7.9.0", "geoplanet:7.10.0", "geoplanet:8.0.0", "woeplanet:8.0.0"], "meta:indexed": "2020-08-20T19:45:31.848123", "meta:updated": "2020-10-14T11:22:09.946338", "woe:hierarchy": {"continent": 24865675, "country": 23424975, "town": 0, "planet": 1, "county": 12602156, "suburb": 0, "state": 24554868, "region": 0, "localadmin": 12695858}, "woe:timezone_id": 28350903, "woe:hash": "gcybsguferrj", "woe:centroid": [-1.5424, 54.952709], "geom:latitude": 54.952709, "geom:longitude": -1.5424, "geom:hash": "gcybsguferrj", "woe:latitude": 54.952709, "geom:centroid": [-1.5424, 54.952709], "woe:longitude": -1.5424, "woe:repo": "woeplanet-poi-gb", "geom:area": 0.0, "woe:scale": 19}}