{"type": "Feature", "id": 22483812, "properties": {"woe:id": 22483812, "woe:parent_id": 13383, "woe:name": "Brownsea Island", "woe:placetype": 20, "woe:placetype_name": "POI", "woe:lang": "ENG", "iso:country": "GB", "meta:provider": ["geoplanet:7.3.1", "geoplanet:7.3.2", "geoplanet:7.4.0", "geoplanet:7.4.1", "geoplanet:7.5.1", "geoplanet:7.5.2", "geoplanet:7.6.0", "geoplanet:7.8.1", "geoplanet:7.9.0", "geoplanet:7.10.0", "geoplanet:8.0.0", "woeplanet:8.0.0"], "meta:indexed": "2020-08-20T19:45:33.154422", "meta:updated": "2020-08-22T02:03:58.090693", "woe:hierarchy": {"continent": 24865675, "country": 23424975, "town": 0, "planet": 1, "county": 12602183, "suburb": 0, "state": 24554868, "region": 0, "localadmin": 12695925}, "woe:timezone_id": 28350903, "woe:hash": "gcn875uf8key", "woe:centroid": [-1.971, 50.689999], "geom:latitude": 50.689999, "geom:longitude": -1.971, "geom:hash": "gcn875uf8key", "woe:latitude": 50.689999, "geom:centroid": [-1.971, 50.689999], "woe:longitude": -1.971, "woe:repo": "woeplanet-poi-gb"}, "geometry": {"coordinates": [-1.971, 50.689999], "type": "Point"}}