{"type": "Feature", "id": 22451811, "geometry": {"type": "Point", "coordinates": [-0.54714, 50.8479]}, "properties": {"woe:id": 22451811, "woe:parent_id": 17454, "woe:name": "Arundel Railway Station", "woe:placetype": 20, "woe:placetype_name": "POI", "woe:lang": "ENG", "iso:country": "GB", "meta:provider": ["geoplanet:7.3.1", "geoplanet:7.3.2", "geoplanet:7.4.0", "geoplanet:7.4.1", "geoplanet:7.5.1", "geoplanet:7.5.2", "geoplanet:7.6.0", "geoplanet:7.8.1", "geoplanet:7.9.0", "geoplanet:7.10.0", "geoplanet:8.0.0", "woeplanet:8.0.0"], "meta:indexed": "2020-08-20T19:45:31.018942", "woe:alias_ENG_V": ["Arundel Station"], "meta:updated": "2020-10-14T11:22:09.136428", "woe:hierarchy": {"continent": 24865675, "country": 23424975, "town": 0, "planet": 1, "county": 12602177, "suburb": 0, "state": 24554868, "region": 0, "localadmin": 12696104}, "woe:timezone_id": 28350903, "woe:hash": "gcp9789d6xwf", "woe:centroid": [-0.54714, 50.8479], "geom:latitude": 50.8479, "geom:longitude": -0.54714, "geom:hash": "gcp9789d6xwf", "woe:latitude": 50.8479, "geom:centroid": [-0.54714, 50.8479], "woe:longitude": -0.54714, "woe:repo": "woeplanet-poi-gb", "geom:area": 0.0, "woe:scale": 19}}