{"type": "Feature", "id": 22493647, "geometry": {"type": "Point", "coordinates": [-0.20509, 51.800968]}, "properties": {"woe:id": 22493647, "woe:parent_id": 39490, "woe:name": "Welwyn Garden City Railway Station", "woe:placetype": 20, "woe:placetype_name": "POI", "woe:lang": "ENG", "iso:country": "GB", "meta:provider": ["geoplanet:7.3.1", "geoplanet:7.3.2", "geoplanet:7.4.0", "geoplanet:7.4.1", "geoplanet:7.5.1", "geoplanet:7.5.2", "geoplanet:7.6.0", "geoplanet:7.8.1", "geoplanet:7.9.0", "geoplanet:7.10.0", "geoplanet:8.0.0", "woeplanet:8.0.0"], "meta:indexed": "2020-08-20T19:45:33.692358", "woe:alias_ENG_V": ["Welwyn Garden City Station"], "meta:updated": "2020-10-14T11:22:08.735673", "woe:hierarchy": {"continent": 24865675, "country": 23424975, "town": 0, "planet": 1, "county": 12602170, "suburb": 0, "state": 24554868, "region": 0, "localadmin": 12695984}, "woe:timezone_id": 28350903, "woe:hash": "gcpyeq4dt03f", "woe:centroid": [-0.20509, 51.800968], "geom:latitude": 51.800968, "geom:longitude": -0.20509, "geom:hash": "gcpyeq4dt03f", "woe:latitude": 51.800968, "geom:centroid": [-0.20509, 51.800968], "woe:longitude": -0.20509, "woe:repo": "woeplanet-poi-gb", "geom:area": 0.0, "woe:scale": 19}}