{"type": "Feature", "id": 22492349, "geometry": {"type": "Point", "coordinates": [0.09636, 50.968639]}, "properties": {"woe:id": 22492349, "woe:parent_id": 38491, "woe:name": "Uckfield Railway Station", "woe:placetype": 20, "woe:placetype_name": "POI", "woe:lang": "ENG", "iso:country": "GB", "meta:provider": ["geoplanet:7.3.1", "geoplanet:7.3.2", "geoplanet:7.4.0", "geoplanet:7.4.1", "geoplanet:7.5.1", "geoplanet:7.5.2", "geoplanet:7.6.0", "geoplanet:7.8.1", "geoplanet:7.9.0", "geoplanet:7.10.0", "geoplanet:8.0.0", "woeplanet:8.0.0"], "meta:indexed": "2020-08-20T19:45:33.624086", "woe:alias_ENG_V": ["Uckfield Station"], "meta:updated": "2020-10-14T11:22:08.967702", "woe:hierarchy": {"continent": 24865675, "country": 23424975, "town": 0, "planet": 1, "county": 12602167, "suburb": 0, "state": 24554868, "region": 0, "localadmin": 12695939}, "woe:timezone_id": 28350903, "woe:hash": "u101fnw1v6gn", "woe:centroid": [0.09636, 50.968639], "geom:latitude": 50.968639, "geom:longitude": 0.09636, "geom:hash": "u101fnw1v6gn", "woe:latitude": 50.968639, "geom:centroid": [0.09636, 50.968639], "woe:longitude": 0.09636, "woe:repo": "woeplanet-poi-gb", "geom:area": 0.0, "woe:scale": 19}}