{"type": "Feature", "id": 22489161, "geometry": {"type": "Point", "coordinates": [0.19942, 51.901279]}, "properties": {"woe:id": 22489161, "woe:parent_id": 35932, "woe:name": "Stansted Mountfitchet Railway Station", "woe:placetype": 20, "woe:placetype_name": "POI", "woe:lang": "ENG", "iso:country": "GB", "meta:provider": ["geoplanet:7.3.1", "geoplanet:7.3.2", "geoplanet:7.4.0", "geoplanet:7.4.1", "geoplanet:7.5.1", "geoplanet:7.5.2", "geoplanet:7.6.0", "geoplanet:7.8.1", "geoplanet:7.9.0", "geoplanet:7.10.0", "geoplanet:8.0.0", "woeplanet:8.0.0"], "meta:indexed": "2020-08-20T19:45:33.472969", "woe:alias_ENG_V": ["Stansted Mountfitchet Station"], "meta:updated": "2020-10-14T11:22:09.144719", "woe:hierarchy": {"continent": 24865675, "country": 23424975, "town": 0, "planet": 1, "county": 12602168, "suburb": 0, "state": 24554868, "region": 0, "localadmin": 12695951}, "woe:timezone_id": 28350903, "woe:hash": "u10pk834ygdk", "woe:centroid": [0.19942, 51.901279], "geom:latitude": 51.901279, "geom:longitude": 0.19942, "geom:hash": "u10pk834ygdk", "woe:latitude": 51.901279, "geom:centroid": [0.19942, 51.901279], "woe:longitude": 0.19942, "woe:repo": "woeplanet-poi-gb", "geom:area": 0.0, "woe:scale": 19}}