{"type": "Feature", "id": 22488746, "properties": {"woe:id": 22488746, "woe:parent_id": 43988, "woe:name": "Thorpe Bay Railway Station", "woe:placetype": 20, "woe:placetype_name": "POI", "woe:lang": "ENG", "iso:country": "GB", "meta:provider": ["geoplanet:7.3.1", "geoplanet:7.3.2", "geoplanet:7.4.0", "geoplanet:7.4.1", "geoplanet:7.5.1", "geoplanet:7.5.2", "geoplanet:7.6.0", "geoplanet:7.8.1", "geoplanet:7.9.0", "geoplanet:7.10.0", "geoplanet:8.0.0", "woeplanet:8.0.0"], "meta:indexed": "2020-08-20T19:45:33.451316", "woe:alias_ENG_V": ["Thorpe Bay Station"], "meta:updated": "2020-08-22T02:03:29.596569", "woe:hierarchy": {"continent": 24865675, "country": 23424975, "town": 0, "planet": 1, "county": 12602168, "suburb": 0, "state": 24554868, "region": 0, "localadmin": 12696175}, "woe:timezone_id": 28350903, "woe:hash": "u10t1q4kwegq", "woe:centroid": [0.76143, 51.537659], "geom:latitude": 51.537659, "geom:longitude": 0.76143, "geom:hash": "u10t1q4kwegq", "woe:latitude": 51.537659, "geom:centroid": [0.76143, 51.537659], "woe:longitude": 0.76143, "woe:repo": "woeplanet-poi-gb"}, "geometry": {"coordinates": [0.76143, 51.537659], "type": "Point"}}