{"type": "Feature", "id": 22467173, "geometry": {"type": "Point", "coordinates": [-0.52444, 51.215199]}, "properties": {"woe:id": 22467173, "woe:parent_id": 12879, "woe:name": "Chilworth Railway Station", "woe:placetype": 20, "woe:placetype_name": "POI", "woe:lang": "ENG", "iso:country": "GB", "meta:provider": ["geoplanet:7.3.1", "geoplanet:7.3.2", "geoplanet:7.4.0", "geoplanet:7.4.1", "geoplanet:7.5.1", "geoplanet:7.5.2", "geoplanet:7.6.0", "geoplanet:7.8.1", "geoplanet:7.9.0", "geoplanet:7.10.0", "geoplanet:8.0.0", "woeplanet:8.0.0"], "meta:indexed": "2020-08-20T19:45:31.999289", "woe:alias_ENG_V": ["Chilworth Station"], "meta:updated": "2020-10-14T11:22:08.566279", "woe:hierarchy": {"continent": 24865675, "country": 23424975, "town": 0, "planet": 1, "county": 12602176, "suburb": 0, "state": 24554868, "region": 0, "localadmin": 12696089}, "woe:timezone_id": 28350903, "woe:hash": "gcpek56n5tj4", "woe:centroid": [-0.52444, 51.215199], "geom:latitude": 51.215199, "geom:longitude": -0.52444, "geom:hash": "gcpek56n5tj4", "woe:latitude": 51.215199, "geom:centroid": [-0.52444, 51.215199], "woe:longitude": -0.52444, "woe:repo": "woeplanet-poi-gb", "geom:area": 0.0, "woe:scale": 19}}