{"type": "Feature", "id": 22471565, "properties": {"woe:id": 22471565, "woe:parent_id": 25877, "woe:name": "Lauder Golf Course", "woe:placetype": 20, "woe:placetype_name": "POI", "woe:lang": "ENG", "iso:country": "GB", "meta:provider": ["geoplanet:7.3.1", "geoplanet:7.3.2", "geoplanet:7.4.0", "geoplanet:7.4.1", "geoplanet:7.5.1", "geoplanet:7.5.2", "geoplanet:7.6.0", "geoplanet:7.8.1", "geoplanet:7.9.0", "geoplanet:7.10.0", "geoplanet:8.0.0", "woeplanet:8.0.0"], "meta:indexed": "2020-08-20T19:45:32.246137", "meta:updated": "2020-08-22T02:03:29.026069", "woe:hierarchy": {"continent": 24865675, "country": 23424975, "town": 0, "planet": 1, "county": 12602209, "suburb": 0, "state": 12578048, "region": 0, "localadmin": 12696186}, "woe:timezone_id": 28350903, "woe:hash": "gcyhcmvu8gzk", "woe:centroid": [-2.74963, 55.71109], "geom:latitude": 55.71109, "geom:longitude": -2.74963, "geom:hash": "gcyhcmvu8gzk", "woe:latitude": 55.71109, "geom:centroid": [-2.74963, 55.71109], "woe:longitude": -2.74963, "woe:repo": "woeplanet-poi-gb"}, "geometry": {"coordinates": [-2.74963, 55.71109], "type": "Point"}}