{"type": "Feature", "id": 23702261, "geometry": {"type": "Point", "coordinates": [-0.12879, 51.521961]}, "properties": {"woe:id": 23702261, "woe:parent_id": 13064, "woe:name": "University of London School of Oriental and African Studies", "woe:placetype": 20, "woe:placetype_name": "POI", "woe:lang": "ENG", "iso:country": "GB", "meta:provider": ["geoplanet:7.3.1", "geoplanet:7.3.2", "geoplanet:7.4.0", "geoplanet:7.4.1", "geoplanet:7.5.1", "geoplanet:7.5.2", "geoplanet:7.6.0", "geoplanet:7.8.1", "geoplanet:7.9.0", "geoplanet:7.10.0", "geoplanet:8.0.0", "woeplanet:8.0.0"], "meta:indexed": "2020-08-20T19:45:34.312966", "woe:alias_ENG_V": ["School Oriental and African Studies", "SOAS", "University of London School of Oriental & African Studies", "School of Oriental and African Studies"], "meta:updated": "2020-10-14T11:21:47.730822", "woe:hierarchy": {"continent": 24865675, "country": 23424975, "town": 0, "planet": 1, "county": 23416974, "suburb": 0, "state": 24554868, "region": 0, "localadmin": 12695807}, "woe:timezone_id": 28350903, "woe:hash": "gcpvj561nvxh", "woe:centroid": [-0.12879, 51.521961], "geom:latitude": 51.521961, "geom:longitude": -0.12879, "geom:hash": "gcpvj561nvxh", "woe:latitude": 51.521961, "geom:centroid": [-0.12879, 51.521961], "woe:longitude": -0.12879, "woe:repo": "woeplanet-poi-gb", "geom:area": 0.0, "woe:scale": 19}}