{"type": "Feature", "id": 22485214, "properties": {"woe:id": 22485214, "woe:parent_id": 14559, "woe:name": "Burley Golf Club", "woe:placetype": 20, "woe:placetype_name": "POI", "woe:lang": "ENG", "iso:country": "GB", "meta:provider": ["geoplanet:7.3.1", "geoplanet:7.3.2", "geoplanet:7.4.0", "geoplanet:7.4.1", "geoplanet:7.5.1", "geoplanet:7.5.2", "geoplanet:7.6.0", "geoplanet:7.8.1", "geoplanet:7.9.0", "geoplanet:7.10.0", "geoplanet:8.0.0", "woeplanet:8.0.0"], "meta:indexed": "2020-08-20T19:45:33.242046", "meta:updated": "2020-08-22T02:03:29.499178", "woe:alias_ENG_V": ["Burley Golf Course"], "woe:hierarchy": {"continent": 24865675, "country": 23424975, "town": 0, "planet": 1, "county": 12602169, "suburb": 0, "state": 24554868, "region": 0, "localadmin": 12695965}, "woe:timezone_id": 28350903, "woe:hash": "gcnc1kmn4rvc", "woe:centroid": [-1.69591, 50.825199], "geom:latitude": 50.825199, "geom:longitude": -1.69591, "geom:hash": "gcnc1kmn4rvc", "woe:latitude": 50.825199, "geom:centroid": [-1.69591, 50.825199], "woe:longitude": -1.69591, "woe:repo": "woeplanet-poi-gb"}, "geometry": {"coordinates": [-1.69591, 50.825199], "type": "Point"}}