{"type": "Feature", "id": 22487403, "properties": {"woe:id": 22487403, "woe:parent_id": 12138, "woe:name": "Beadlow Manor Hotel Golf Club", "woe:placetype": 20, "woe:placetype_name": "POI", "woe:lang": "ENG", "iso:country": "GB", "meta:provider": ["geoplanet:7.3.1", "geoplanet:7.3.2", "geoplanet:7.4.0", "geoplanet:7.4.1", "geoplanet:7.5.1", "geoplanet:7.5.2", "geoplanet:7.6.0", "geoplanet:7.8.1", "geoplanet:7.9.0", "geoplanet:7.10.0", "geoplanet:8.0.0", "woeplanet:8.0.0"], "meta:indexed": "2020-08-20T19:45:33.363293", "meta:updated": "2020-08-22T02:03:29.556624", "woe:hierarchy": {"continent": 24865675, "country": 23424975, "town": 0, "planet": 1, "county": 12602163, "suburb": 0, "state": 24554868, "region": 0, "localadmin": 12695875}, "woe:timezone_id": 28350903, "woe:hash": "gcpxzpyqy2ug", "woe:centroid": [-0.38665, 52.03104], "geom:latitude": 52.03104, "geom:longitude": -0.38665, "geom:hash": "gcpxzpyqy2ug", "woe:latitude": 52.03104, "geom:centroid": [-0.38665, 52.03104], "woe:longitude": -0.38665, "woe:repo": "woeplanet-poi-gb"}, "geometry": {"coordinates": [-0.38665, 52.03104], "type": "Point"}}