{"type": "Feature", "id": 22489148, "geometry": {"type": "Point", "coordinates": [-0.30307, 51.619709]}, "properties": {"woe:id": 22489148, "woe:parent_id": 35918, "woe:name": "Stanmore Underground Station", "woe:placetype": 20, "woe:placetype_name": "POI", "woe:lang": "ENG", "iso:country": "GB", "meta:provider": ["geoplanet:7.3.1", "geoplanet:7.3.2", "geoplanet:7.4.0", "geoplanet:7.4.1", "geoplanet:7.5.1", "geoplanet:7.5.2", "geoplanet:7.6.0", "geoplanet:7.8.1", "geoplanet:7.9.0", "geoplanet:7.10.0", "geoplanet:8.0.0", "woeplanet:8.0.0"], "meta:indexed": "2020-08-20T19:45:33.471292", "woe:alias_ENG_V": ["Stanmore Tube", "Stanmore Underground", "Stanmore Station", "Stanmore Tube Station"], "meta:updated": "2020-10-14T11:22:09.145463", "woe:hierarchy": {"continent": 24865675, "country": 23424975, "town": 0, "planet": 1, "county": 23416974, "suburb": 0, "state": 24554868, "region": 0, "localadmin": 12695829}, "woe:timezone_id": 28350903, "woe:hash": "gcpv9j569gnw", "woe:centroid": [-0.30307, 51.619709], "geom:latitude": 51.619709, "geom:longitude": -0.30307, "geom:hash": "gcpv9j569gnw", "woe:latitude": 51.619709, "geom:centroid": [-0.30307, 51.619709], "woe:longitude": -0.30307, "woe:repo": "woeplanet-poi-gb", "geom:area": 0.0, "woe:scale": 19}}