{"type": "Feature", "id": 23702062, "geometry": {"type": "Point", "coordinates": [-3.32722, 51.589199]}, "properties": {"woe:id": 23702062, "woe:parent_id": 32317, "woe:name": "University of Glamoragn", "woe:placetype": 20, "woe:placetype_name": "POI", "woe:lang": "ENG", "iso:country": "GB", "meta:provider": ["geoplanet:7.3.1", "geoplanet:7.3.2", "geoplanet:7.4.0", "geoplanet:7.4.1", "geoplanet:7.5.1", "geoplanet:7.5.2", "geoplanet:7.6.0", "geoplanet:7.8.1", "geoplanet:7.9.0", "geoplanet:7.10.0", "geoplanet:8.0.0", "woeplanet:8.0.0"], "meta:indexed": "2020-08-20T19:45:34.131830", "woe:alias_ENG_V": ["University of Glamorgan", "Glamoragn University"], "meta:updated": "2020-10-14T11:21:47.843396", "woe:hierarchy": {"continent": 24865675, "country": 23424975, "town": 0, "planet": 1, "county": 12602228, "suburb": 0, "state": 12578049, "region": 0, "localadmin": 12696115}, "woe:timezone_id": 28350903, "woe:hash": "gcjtkr90y5sz", "woe:centroid": [-3.32722, 51.589199], "geom:latitude": 51.589199, "geom:longitude": -3.32722, "geom:hash": "gcjtkr90y5sz", "woe:latitude": 51.589199, "geom:centroid": [-3.32722, 51.589199], "woe:longitude": -3.32722, "woe:repo": "woeplanet-poi-gb", "geom:area": 0.0, "woe:scale": 19}}