{"type": "Feature", "id": 22471734, "geometry": {"type": "Point", "coordinates": [-1.57756, 53.812069]}, "properties": {"woe:id": 22471734, "woe:parent_id": 26042, "woe:name": "Burley Park Railway Station", "woe:placetype": 20, "woe:placetype_name": "POI", "woe:lang": "ENG", "iso:country": "GB", "meta:provider": ["geoplanet:7.3.1", "geoplanet:7.3.2", "geoplanet:7.4.0", "geoplanet:7.4.1", "geoplanet:7.5.1", "geoplanet:7.5.2", "geoplanet:7.6.0", "geoplanet:7.8.1", "geoplanet:7.9.0", "geoplanet:7.10.0", "geoplanet:8.0.0", "woeplanet:8.0.0"], "meta:indexed": "2020-08-20T19:45:32.252005", "woe:alias_ENG_V": ["Burley Park Station"], "meta:updated": "2020-10-14T11:22:08.189750", "woe:hierarchy": {"continent": 24865675, "country": 23424975, "town": 0, "planet": 1, "county": 12602197, "suburb": 0, "state": 24554868, "region": 0, "localadmin": 12695873}, "woe:timezone_id": 28350903, "woe:hash": "gcwfhh5q00wp", "woe:centroid": [-1.57756, 53.812069], "geom:latitude": 53.812069, "geom:longitude": -1.57756, "geom:hash": "gcwfhh5q00wp", "woe:latitude": 53.812069, "geom:centroid": [-1.57756, 53.812069], "woe:longitude": -1.57756, "woe:repo": "woeplanet-poi-gb", "geom:area": 0.0, "woe:scale": 19}}