{"type": "Feature", "id": 22453845, "properties": {"woe:id": 22453845, "woe:parent_id": 12695938, "woe:name": "Collington Railway Station", "woe:placetype": 20, "woe:placetype_name": "POI", "woe:lang": "ENG", "iso:country": "GB", "meta:provider": ["geoplanet:7.3.1", "geoplanet:7.3.2", "geoplanet:7.4.0", "geoplanet:7.4.1", "geoplanet:7.5.1", "geoplanet:7.5.2", "geoplanet:7.6.0", "geoplanet:7.8.1", "geoplanet:7.9.0", "geoplanet:7.10.0", "geoplanet:8.0.0", "woeplanet:8.0.0"], "meta:indexed": "2020-08-20T19:45:31.171368", "woe:alias_ENG_V": ["Collington Station"], "meta:updated": "2020-08-22T02:03:28.541746", "woe:hierarchy": {"continent": 24865675, "country": 23424975, "town": 0, "planet": 1, "county": 12602167, "suburb": 0, "state": 24554868, "region": 0, "localadmin": 12695938}, "woe:timezone_id": 28350903, "woe:hash": "u1034quzqswr", "woe:centroid": [0.45725, 50.83913], "geom:latitude": 50.83913, "geom:longitude": 0.45725, "geom:hash": "u1034quzqswr", "woe:latitude": 50.83913, "geom:centroid": [0.45725, 50.83913], "woe:longitude": 0.45725, "woe:repo": "woeplanet-poi-gb"}, "geometry": {"coordinates": [0.45725, 50.83913], "type": "Point"}}