{"type": "Feature", "id": 22463477, "geometry": {"type": "Point", "coordinates": [-0.34272, 51.402679]}, "properties": {"woe:id": 22463477, "woe:parent_id": 19055, "woe:name": "Hampton Court Railway Station", "woe:placetype": 20, "woe:placetype_name": "POI", "woe:lang": "ENG", "iso:country": "GB", "meta:provider": ["geoplanet:7.3.1", "geoplanet:7.3.2", "geoplanet:7.4.0", "geoplanet:7.4.1", "geoplanet:7.5.1", "geoplanet:7.5.2", "geoplanet:7.6.0", "geoplanet:7.8.1", "geoplanet:7.9.0", "geoplanet:7.10.0", "geoplanet:8.0.0", "woeplanet:8.0.0"], "meta:indexed": "2020-08-20T19:45:31.716101", "woe:alias_ENG_V": ["Hampton Court Station"], "meta:updated": "2020-10-14T11:22:10.022594", "woe:hierarchy": {"continent": 24865675, "country": 23424975, "town": 0, "planet": 1, "county": 12602176, "suburb": 0, "state": 24554868, "region": 0, "localadmin": 12696087}, "woe:timezone_id": 28350903, "woe:hash": "gcpu2jw6q1c7", "woe:centroid": [-0.34272, 51.402679], "geom:latitude": 51.402679, "geom:longitude": -0.34272, "geom:hash": "gcpu2jw6q1c7", "woe:latitude": 51.402679, "geom:centroid": [-0.34272, 51.402679], "woe:longitude": -0.34272, "woe:repo": "woeplanet-poi-gb", "geom:area": 0.0, "woe:scale": 19}}