{"type": "Feature", "id": 22460649, "geometry": {"type": "Point", "coordinates": [-2.21048, 53.147888]}, "properties": {"woe:id": 22460649, "woe:parent_id": 30026, "woe:name": "Astbury Golf Club", "woe:placetype": 20, "woe:placetype_name": "POI", "woe:lang": "ENG", "iso:country": "GB", "meta:provider": ["geoplanet:7.3.1", "geoplanet:7.3.2", "geoplanet:7.4.0", "geoplanet:7.4.1", "geoplanet:7.5.1", "geoplanet:7.5.2", "geoplanet:7.6.0", "geoplanet:7.8.1", "geoplanet:7.9.0", "geoplanet:7.10.0", "geoplanet:8.0.0", "woeplanet:8.0.0"], "meta:indexed": "2020-08-20T19:45:31.559319", "meta:updated": "2020-10-14T11:22:09.476386", "woe:alias_ENG_V": ["Astbury Golf Course"], "woe:hierarchy": {"continent": 24865675, "country": 23424975, "town": 0, "planet": 1, "county": 12602157, "suburb": 0, "state": 24554868, "region": 0, "localadmin": 12695888}, "woe:timezone_id": 28350903, "woe:hash": "gcqqmeq2uh6t", "woe:centroid": [-2.21048, 53.147888], "geom:latitude": 53.147888, "geom:longitude": -2.21048, "geom:hash": "gcqqmeq2uh6t", "woe:latitude": 53.147888, "geom:centroid": [-2.21048, 53.147888], "woe:longitude": -2.21048, "woe:repo": "woeplanet-poi-gb", "geom:area": 0.0, "woe:scale": 19}}