{"type": "Feature", "id": 22454747, "properties": {"woe:id": 22454747, "woe:parent_id": 28276213, "woe:name": "Witton Railway Station", "woe:placetype": 20, "woe:placetype_name": "POI", "woe:lang": "ENG", "iso:country": "GB", "meta:provider": ["geoplanet:7.3.1", "geoplanet:7.3.2", "geoplanet:7.4.0", "geoplanet:7.4.1", "geoplanet:7.5.1", "geoplanet:7.5.2", "geoplanet:7.6.0", "geoplanet:7.8.1", "geoplanet:7.9.0", "geoplanet:7.10.0", "geoplanet:8.0.0", "woeplanet:8.0.0"], "meta:indexed": "2020-08-20T19:45:31.229455", "woe:alias_ENG_V": ["Witton Station"], "meta:updated": "2020-08-22T02:03:28.566978", "woe:hierarchy": {"continent": 24865675, "country": 23424975, "town": 0, "planet": 1, "county": 12602191, "suburb": 0, "state": 24554868, "region": 0, "localadmin": 12695863}, "woe:timezone_id": 28350903, "woe:hash": "gcqdtpe9vjjm", "woe:centroid": [-1.88462, 52.51223], "geom:latitude": 52.51223, "geom:longitude": -1.88462, "geom:hash": "gcqdtpe9vjjm", "woe:latitude": 52.51223, "geom:centroid": [-1.88462, 52.51223], "woe:longitude": -1.88462, "woe:repo": "woeplanet-poi-gb"}, "geometry": {"coordinates": [-1.88462, 52.51223], "type": "Point"}}