{"type": "Feature", "id": 22467194, "geometry": {"type": "Point", "coordinates": [-0.53659, 51.240601]}, "properties": {"woe:id": 22467194, "woe:parent_id": 28745, "woe:name": "Guildford Golf Course", "woe:placetype": 20, "woe:placetype_name": "POI", "woe:lang": "ENG", "iso:country": "GB", "meta:provider": ["geoplanet:7.3.1", "geoplanet:7.3.2", "geoplanet:7.4.0", "geoplanet:7.4.1", "geoplanet:7.5.1", "geoplanet:7.5.2", "geoplanet:7.6.0", "geoplanet:7.8.1", "geoplanet:7.9.0", "geoplanet:7.10.0", "geoplanet:8.0.0", "woeplanet:8.0.0"], "meta:indexed": "2020-08-20T19:45:32.002342", "meta:updated": "2020-10-14T11:22:08.564205", "woe:hierarchy": {"continent": 24865675, "country": 23424975, "town": 0, "planet": 1, "county": 12602176, "suburb": 0, "state": 24554868, "region": 0, "localadmin": 12696089}, "woe:timezone_id": 28350903, "woe:hash": "gcpeeb160s37", "woe:centroid": [-0.53659, 51.240601], "geom:latitude": 51.240601, "geom:longitude": -0.53659, "geom:hash": "gcpeeb160s37", "woe:latitude": 51.240601, "geom:centroid": [-0.53659, 51.240601], "woe:longitude": -0.53659, "woe:repo": "woeplanet-poi-gb", "geom:area": 0.0, "woe:scale": 19}}