{"type": "Feature", "id": 22467601, "properties": {"woe:id": 22467601, "woe:parent_id": 22514, "woe:name": "Harrogate Railway Station", "woe:placetype": 20, "woe:placetype_name": "POI", "woe:lang": "ENG", "iso:country": "GB", "meta:provider": ["geoplanet:7.3.1", "geoplanet:7.3.2", "geoplanet:7.4.0", "geoplanet:7.4.1", "geoplanet:7.5.1", "geoplanet:7.5.2", "geoplanet:7.6.0", "geoplanet:7.8.1", "geoplanet:7.9.0", "geoplanet:7.10.0", "geoplanet:8.0.0", "woeplanet:8.0.0"], "meta:indexed": "2020-08-20T19:45:32.021043", "woe:alias_ENG_V": ["Harrogate Station"], "meta:updated": "2020-08-22T02:03:28.916633", "woe:hierarchy": {"continent": 24865675, "country": 23424975, "town": 0, "planet": 1, "county": 12602195, "suburb": 0, "state": 24554868, "region": 0, "localadmin": 12696045}, "woe:timezone_id": 28350903, "woe:hash": "gcwgjj0veygb", "woe:centroid": [-1.53689, 53.99329], "geom:latitude": 53.99329, "geom:longitude": -1.53689, "geom:hash": "gcwgjj0veygb", "woe:latitude": 53.99329, "geom:centroid": [-1.53689, 53.99329], "woe:longitude": -1.53689, "woe:repo": "woeplanet-poi-gb"}, "geometry": {"coordinates": [-1.53689, 53.99329], "type": "Point"}}