{"type": "Feature", "id": 22462671, "geometry": {"type": "Point", "coordinates": [-0.32126, 51.181019]}, "properties": {"woe:id": 22462671, "woe:parent_id": 23415852, "woe:name": "Holmwood Railway Station", "woe:placetype": 20, "woe:placetype_name": "POI", "woe:lang": "ENG", "iso:country": "GB", "meta:provider": ["geoplanet:7.3.1", "geoplanet:7.3.2", "geoplanet:7.4.0", "geoplanet:7.4.1", "geoplanet:7.5.1", "geoplanet:7.5.2", "geoplanet:7.6.0", "geoplanet:7.8.1", "geoplanet:7.9.0", "geoplanet:7.10.0", "geoplanet:8.0.0", "woeplanet:8.0.0"], "meta:indexed": "2020-08-20T19:45:31.670790", "woe:alias_ENG_V": ["Holmwood Station"], "meta:updated": "2020-10-14T11:22:08.094170", "woe:hierarchy": {"continent": 24865675, "country": 23424975, "town": 0, "planet": 1, "county": 12602176, "suburb": 0, "state": 24554868, "region": 0, "localadmin": 12696090}, "woe:timezone_id": 28350903, "woe:hash": "gcpg0tnp417n", "woe:centroid": [-0.32126, 51.181019], "geom:latitude": 51.181019, "geom:longitude": -0.32126, "geom:hash": "gcpg0tnp417n", "woe:latitude": 51.181019, "geom:centroid": [-0.32126, 51.181019], "woe:longitude": -0.32126, "woe:repo": "woeplanet-poi-gb", "geom:area": 0.0, "woe:scale": 19}}