{"type": "Feature", "id": 22464412, "geometry": {"type": "Point", "coordinates": [-3.56092, 50.641289]}, "properties": {"woe:id": 22464412, "woe:parent_id": 24787, "woe:name": "Exeter Racecourse", "woe:placetype": 20, "woe:placetype_name": "POI", "woe:lang": "ENG", "iso:country": "GB", "meta:provider": ["geoplanet:7.3.1", "geoplanet:7.3.2", "geoplanet:7.4.0", "geoplanet:7.4.1", "geoplanet:7.5.1", "geoplanet:7.5.2", "geoplanet:7.6.0", "geoplanet:7.8.1", "geoplanet:7.9.0", "geoplanet:7.10.0", "geoplanet:8.0.0", "woeplanet:8.0.0"], "meta:indexed": "2020-08-20T19:45:31.776255", "meta:updated": "2020-10-14T11:22:08.859522", "woe:hierarchy": {"continent": 24865675, "country": 23424975, "town": 0, "planet": 1, "county": 12602182, "suburb": 0, "state": 24554868, "region": 0, "localadmin": 12695919}, "woe:timezone_id": 28350903, "woe:hash": "gcj2nfznbs3x", "woe:centroid": [-3.56092, 50.641289], "geom:latitude": 50.641289, "geom:longitude": -3.56092, "geom:hash": "gcj2nfznbs3x", "woe:latitude": 50.641289, "geom:centroid": [-3.56092, 50.641289], "woe:longitude": -3.56092, "woe:repo": "woeplanet-poi-gb", "geom:area": 0.0, "woe:scale": 19}}