{"type": "Feature", "id": 22464606, "geometry": {"type": "Point", "coordinates": [0.85352, 52.823299]}, "properties": {"woe:id": 22464606, "woe:parent_id": 32654, "woe:name": "Fakenham Racecourse", "woe:placetype": 20, "woe:placetype_name": "POI", "woe:lang": "ENG", "iso:country": "GB", "meta:provider": ["geoplanet:7.3.1", "geoplanet:7.3.2", "geoplanet:7.4.0", "geoplanet:7.4.1", "geoplanet:7.5.1", "geoplanet:7.5.2", "geoplanet:7.6.0", "geoplanet:7.8.1", "geoplanet:7.9.0", "geoplanet:7.10.0", "geoplanet:8.0.0", "woeplanet:8.0.0"], "meta:indexed": "2020-08-20T19:45:31.790433", "meta:updated": "2020-10-14T11:22:09.034683", "woe:hierarchy": {"continent": 24865675, "country": 23424975, "town": 0, "planet": 1, "county": 12602141, "suburb": 0, "state": 24554868, "region": 0, "localadmin": 12696027}, "woe:timezone_id": 28350903, "woe:hash": "u12se2jw02ws", "woe:centroid": [0.85352, 52.823299], "geom:latitude": 52.823299, "geom:longitude": 0.85352, "geom:hash": "u12se2jw02ws", "woe:latitude": 52.823299, "geom:centroid": [0.85352, 52.823299], "woe:longitude": 0.85352, "woe:repo": "woeplanet-poi-gb", "geom:area": 0.0, "woe:scale": 19}}