{"type": "Feature", "id": 22478639, "geometry": {"type": "Point", "coordinates": [-3.49422, 54.711521]}, "properties": {"woe:id": 22478639, "woe:parent_id": 28499, "woe:name": "Maryport Railway Station", "woe:placetype": 20, "woe:placetype_name": "POI", "woe:lang": "ENG", "iso:country": "GB", "meta:provider": ["geoplanet:7.3.1", "geoplanet:7.3.2", "geoplanet:7.4.0", "geoplanet:7.4.1", "geoplanet:7.5.1", "geoplanet:7.5.2", "geoplanet:7.6.0", "geoplanet:7.8.1", "geoplanet:7.9.0", "geoplanet:7.10.0", "geoplanet:8.0.0", "woeplanet:8.0.0"], "meta:indexed": "2020-08-20T19:45:32.875694", "woe:alias_ENG_V": ["Maryport Station"], "meta:updated": "2020-10-14T11:22:09.155870", "woe:hierarchy": {"continent": 24865675, "country": 23424975, "town": 0, "planet": 1, "county": 12602148, "suburb": 0, "state": 24554868, "region": 0, "localadmin": 12695900}, "woe:timezone_id": 28350903, "woe:hash": "gctx0rztdy8x", "woe:centroid": [-3.49422, 54.711521], "geom:latitude": 54.711521, "geom:longitude": -3.49422, "geom:hash": "gctx0rztdy8x", "woe:latitude": 54.711521, "geom:centroid": [-3.49422, 54.711521], "woe:longitude": -3.49422, "woe:repo": "woeplanet-poi-gb", "geom:area": 0.0, "woe:scale": 19}}