{"type": "Feature", "id": 22451336, "geometry": {"type": "Point", "coordinates": [-4.58316, 56.002209]}, "properties": {"woe:id": 22451336, "woe:parent_id": 11691, "woe:name": "Balloch Railway Station", "woe:placetype": 20, "woe:placetype_name": "POI", "woe:lang": "ENG", "iso:country": "GB", "meta:provider": ["geoplanet:7.3.1", "geoplanet:7.3.2", "geoplanet:7.4.0", "geoplanet:7.4.1", "geoplanet:7.5.1", "geoplanet:7.5.2", "geoplanet:7.6.0", "geoplanet:7.8.1", "geoplanet:7.9.0", "geoplanet:7.10.0", "geoplanet:8.0.0", "woeplanet:8.0.0"], "meta:indexed": "2020-08-20T19:45:30.975275", "woe:alias_ENG_V": ["Balloch Station"], "meta:updated": "2020-10-14T11:22:09.278798", "woe:hierarchy": {"continent": 24865675, "country": 23424975, "town": 0, "planet": 1, "county": 12602207, "suburb": 0, "state": 12578048, "region": 0, "localadmin": 12696188}, "woe:timezone_id": 28350903, "woe:hash": "gcuwxdyss8kj", "woe:centroid": [-4.58316, 56.002209], "geom:latitude": 56.002209, "geom:longitude": -4.58316, "geom:hash": "gcuwxdyss8kj", "woe:latitude": 56.002209, "geom:centroid": [-4.58316, 56.002209], "woe:longitude": -4.58316, "woe:repo": "woeplanet-poi-gb", "geom:area": 0.0, "woe:scale": 19}}