{"type": "Feature", "id": 22461146, "geometry": {"type": "Point", "coordinates": [-0.18671, 51.11224]}, "properties": {"woe:id": 22461146, "woe:parent_id": 17233, "woe:name": "Crawley Railway Station", "woe:placetype": 20, "woe:placetype_name": "POI", "woe:lang": "ENG", "iso:country": "GB", "meta:provider": ["geoplanet:7.3.1", "geoplanet:7.3.2", "geoplanet:7.4.0", "geoplanet:7.4.1", "geoplanet:7.5.1", "geoplanet:7.5.2", "geoplanet:7.6.0", "geoplanet:7.8.1", "geoplanet:7.9.0", "geoplanet:7.10.0", "geoplanet:8.0.0", "woeplanet:8.0.0"], "meta:indexed": "2020-08-20T19:45:31.581767", "woe:alias_ENG_V": ["Crawley Station"], "meta:updated": "2020-10-14T11:22:09.197827", "woe:hierarchy": {"continent": 24865675, "country": 23424975, "town": 0, "planet": 1, "county": 12602177, "suburb": 0, "state": 24554868, "region": 0, "localadmin": 12696106}, "woe:timezone_id": 28350903, "woe:hash": "gcpfgb8n3k4g", "woe:centroid": [-0.18671, 51.11224], "geom:latitude": 51.11224, "geom:longitude": -0.18671, "geom:hash": "gcpfgb8n3k4g", "woe:latitude": 51.11224, "geom:centroid": [-0.18671, 51.11224], "woe:longitude": -0.18671, "woe:repo": "woeplanet-poi-gb", "geom:area": 0.0, "woe:scale": 19}}